Workbook
Name ActualNumberOfPayments: IFERROR(IF('Loan Summary '!LoanIsGood,IF('Loan Summary '!PaymentsPerYear=1,1,MATCH(0.01,'Loan Summary '!End_Bal,-1)+1)),"")
Name ColumnTitle1: #REF!
Name End_Bal: #REF!
Name ExtraPayments: 'Loan Summary '!#REF!
Name InterestRate: 'Loan Summary '!$E$6
Name LastCol: MATCH(REPT("z",255),'Loan Summary '!$13:$13)
Name LastCol: MATCH(REPT("z",255),#REF!)
Name LastRow: MATCH(9.99E+307,'Loan Summary '!$B:$B)
Name LastRow: MATCH(9.99E+307,#REF!)
Name LenderName: 'Loan Summary '!#REF!
Name LoanAmount: 'Loan Summary '!$E$5
Name LoanIsGood: ('Loan Summary '!$E$5*'Loan Summary '!$E$6*'Loan Summary '!$E$11*'Loan Summary '!$E$13)>0
Name LoanPeriod: 'Loan Summary '!$E$11
Name LoanStartDate: 'Loan Summary '!$E$13
Name PaymentsPerYear: 'Loan Summary '!$E$12
Name PrintArea_SET: OFFSET('Loan Summary '!#REF!,,,'Loan Summary '!LastRow,'Loan Summary '!LastCol)
Name RowTitleRegion1..E9: 'Loan Summary '!$B$5:$D$5
Name RowTitleRegion2..I7: 'Loan Summary '!#REF!
Name RowTitleRegion3..E9: 'Loan Summary '!#REF!
Name RowTitleRegion4..H9: 'Loan Summary '!#REF!
Name ScheduledNumberOfPayments: 'Loan Summary '!#REF!
Name ScheduledPayment: 'Loan Summary '!#REF!
Name TotalEarlyPayments: SUM(#REF!)
Name TotalInterest: SUM(#REF!)

Sheet Loan Summary 
C2: Drip's Flex Line amortization schedule summary
B4: Client Terms | G4: Loan Details | Q4: Payment Schedule
B5: Approved Credit Line | E5: 100000 | G5: Loan # | H5: Loan Amount | I5: Loan Date | J5: Loan Payment Start Date | K5: Loan Payment End Date | L5: Monthly Principal Repayment | M5: Total Interest | N5: Draw Possible | O5: Remaining Limit | Q5: Payment date | R5: Beginning balance | S5: Principal Payment | T5: Interest | U5: Draw Fee | V5: Other Fees | W5: Extra Payment | X5: Delay in Payment | Y5: Overdue Interest | Z5: Actual Payment Date | AA5: Ending balance | AB5: Total Payment
B6: Annual interest rate | E6: 0.18 | G6: =IFERROR(RANK(Table4[[#This Row],[Loan Date]],Table4[[#All],[Loan Date]],1) +COUNTIF($I$6:I6,I6)-1,"") -> 1 | H6: 30000 | I6: 45315 | J6: =IF(Table4[[#This Row],[Loan Date]]<>"",IF($E$14 = "End of Month", EOMONTH(Table4[[#This Row],[Loan Date]],IF(DAY(EOMONTH(Table4[[#This Row],[Loan Date]],0)) - DAY(Table4[[#This Row],[Loan Date]])<=$E$15,1,0)),IF($E$14 = "Mid of Month", EOMONTH(Table4[[#This Row],[Loan Date]],IF(15 - DAY(Table4[[#This Row],[Loan Date]])<=$E$15,0,-1))+15,IF($E$14 = "Start of Month", EOMONTH(Table4[[#This Row],[Loan Date]],IF(DAY(EOMONTH(Table4[[#This Row],[Loan Date]],0)) - DAY(Table4[[#This Row],[Loan Date]])<=$E$15,1,0))) + 1)),"") -> 45352 | K6: =IF(Table4[[#This Row],[Loan Date]]<>"", IF($E$14 = "End of Month", EOMONTH(Table4[[#This Row],[Loan Date]],6+IF(DAY(EOMONTH(Table4[[#This Row],[Loan Date]],0)) - DAY(Table4[[#This Row],[Loan Date]])<=$E$15,0,-1)), IF($E$14 = "Mid of Month", EOMONTH(Table4[[#This Row],[Loan Date]],6+IF(15 - DAY(Table4[[#This Row],[Loan Date]])<=$E$15,-1,-2))+15, IF($E$14 = "Start of Month", EOMONTH(Table4[[#This Row],[Loan Date]],6+IF(DAY(EOMONTH(Table4[[#This Row],[Loan Date]],0)) - DAY(Table4[[#This Row],[Loan Date]])<=$E$15,0,-1)) + 1) ) ),"") -> 45505 | L6: =IF(Table4[[#This Row],[Loan Date]]<>"",Table4[[#This Row],[Loan Amount]]/PaymentsPerYear,"") -> 5000 | M6: {=IF(Table4[[#This Row],[Loan Date]]<>"", ((Table4[[#This Row],[Loan Payment Start Date]]-Table4[[#This Row],[Loan Date]])*Table4[[#This Row],[Loan Amount]]*InterestRate/360) + SUM((_xlfn.SEQUENCE(6, 1, Table4[[#This Row],[Loan Amount]]-Table4[[#This Row],[Loan Amount]]/6, -Table4[[#This Row],[Loan Amount]]/6))* (IF($E$14 = "End of Month", EOMONTH(EDATE(Table4[[#This Row],[Loan Payment Start Date]],_xlfn.SEQUENCE(6,1,1,1)),0),IF($E$14 = "Mid of Month",EDATE(Table4[[#This Row],[Loan Payment Start Date]],_xlfn.SEQUENCE(6,1,1,1)), IF($E$14 = "Start of Month", EOMONTH(EDATE(Table4[[#This Row],[Loan Payment Start Date]],_xlfn.SEQUENCE(6,1,1,1)),-1)+1))) - IF($E$14 = "End of Month", EOMONTH(EDATE(Table4[[#This Row],[Loan Payment Start Date]],_xlfn.SEQUENCE(6,1,1,1)),-1),IF($E$14 = "Mid of Month",EDATE(Table4[[#This Row],[Loan Payment Start Date]],_xlfn.SEQUENCE(6,1,0,1)), IF($E$14 = "Start of Month", EOMONTH(EDATE(Table4[[#This Row],[Loan Payment Start Date]],_xlfn.SEQUENCE(6,1,1,1)),-2)+1))))*InterestRate/360),"")} -> 1702.5 | N6: =IF(Table4[[#This Row],[Loan Amount]]<>"", IF((LoanAmount - (SUMIFS(Table4[Loan Amount],Table4[Loan Date],"<"&Table4[[#This Row],[Loan Date]]) -SUMIFS(Table5[Principal Payment],Table5[Payment date],"<="&Table4[[#This Row],[Loan Date]]) - SUMIFS(Table5[Extra Payment],Table5[Payment date],"<="&Table4[[#This Row],[Loan Date]])) > Table4[[#This Row],[Loan Amount]]),"Yes","No"),"") -> Yes | O6: =IF(Table4[[#This Row],[Loan Amount]]<>"", LoanAmount - (SUMIFS(Table4[Loan Amount],Table4[Loan Date],"<"&Table4[[#This Row],[Loan Date]]) -SUMIFS(Table5[Principal Payment],Table5[Payment date],"<="&Table4[[#This Row],[Loan Date]]) - SUMIFS(Table5[Extra Payment],Table5[Payment date],"<="&Table4[[#This Row],[Loan Date]])) - Table4[[#This Row],[Loan Amount]],"") -> 70000 | Q6: =IF($E$14="Mid of Month",(IF(EDATE(MIN(Table4[[#All],[Loan Date]]), ROW()-ROW($Q$6)) > EDATE(MAX(Table4[[#All],[Loan Payment End Date]]),1), "", (EOMONTH(EDATE(MIN(Table4[[#All],[Loan Date]]), ROW()-ROW($Q$6)),IF(DAY(EOMONTH(MIN(Table4[[#All],[Loan Date]]),0)) - DAY(MIN(Table4[[#All],[Loan Date]])) <= $E$15, 0, -1))+ 15))), IF($E$14="End of Month",(IF(EDATE(MIN(Table4[[#All],[Loan Date]]), ROW()-ROW($Q$6)) > MAX(Table4[[#All],[Loan Payment End Date]]), "", (EOMONTH(EDATE(MIN(Table4[[#All],[Loan Date]]), ROW()-ROW($Q$6)),IF(31 - DAY(MIN(Table4[[#All],[Loan Date]])) <= $E$15, 1, 0))))), IF($E$14="Start of Month",(IF(EDATE(MIN(Table4[[#All],[Loan Date]]), ROW()-ROW($Q$6)) > MAX(Table4[[#All],[Loan Payment End Date]]), "", (EOMONTH(EDATE(MIN(Table4[[#All],[Loan Date]]), ROW()-ROW($Q$6)),IF(31 - DAY(MIN(Table4[[#All],[Loan Date]])) <= $E$15, 1, 0))) + 1 ))) ) ) -> 45352 | R6: =IF(Table5[[#This Row],[Payment date]]<>"", SUMIFS(Table4[[#All],[Loan Amount]],Table4[[#All],[Loan Date]],"<="&Table5[[#This Row],[Payment date]]) - SUM($S$5:S5)- SUM($W$5:W5),"") -> 50000 | S6: =IF(Table5[[#This Row],[Payment date]]<>"",SUM('Individual Loan Schedule'!C9:HR9) - SUM('Early Payments'!D9:HS9),"") -> 5000 | T6: {=IF(Table5[[#This Row],[Payment date]]<>"",((SUMIFS(Table4[Loan Amount],Table4[Loan Payment Start Date],"<"&Table5[[#This Row],[Payment date]]) - SUM($S$5:$S5) - SUM($W$5:W5))*InterestRate*(Table5[[#This Row],[Payment date]] - IF($E$14="End of Month",EOMONTH(Table5[[#This Row],[Payment date]],-1), IF($E$14="Mid of Month",EOMONTH(Table5[[#This Row],[Payment date]],-2)+15, IF($E$14="Start of Month",EOMONTH(Table5[[#This Row],[Payment date]],-2) + 1))) )/360) + (SUM(IFERROR((IF(Table4[Loan Payment Start Date]=Table5[[#This Row],[Payment date]],Table4[Loan Amount],"")*(Table4[Loan Payment Start Date]-Table4[Loan Date])*InterestRate/360),0),0)),"")} -> 555 | U6: =IF(Table5[[#This Row],[Payment date]]<>"",SUMIFS(Table4[[#All],[Loan Amount]],Table4[[#All],[Loan Payment Start Date]],"="&Table5[[#This Row],[Payment date]])*($E$7),"") -> 90 | V6: {=IF(Table5[[#This Row],[Payment date]]<>"",IF(Table5[[#This Row],[Payment date]]=MIN(Table4[[#All],[Loan Payment Start Date]]),$E$8+$E$10*LoanAmount,0) + IF(Table5[[#This Row],[Payment date]] =MIN(_xlfn._xlws.FILTER(Table5[Payment date],(Table5[Payment date]>=EDATE(LoanStartDate,12*DATEDIF(LoanStartDate,Table5[[#This Row],[Payment date]],"y")))*(Table5[Beginning balance]<>0))), $E$9*LoanAmount,0),"")} -> 849 | X6: 10 | Y6: =IF(Table5[[#This Row],[Payment date]]<>"",(SUMIFS(Table4[Loan Amount],Table4[Loan Payment Start Date],"<="&Table5[[#This Row],[Payment date]]) - SUM($S$5:$S5) - - SUM($W$5:W5))*Table5[[#This Row],[Delay in Payment ]]*($E$16+ InterestRate)/365,"") -> 443.83562 | Z6: =IF(Table5[[#This Row],[Payment date]]<>"",Table5[[#This Row],[Payment date]]+Table5[[#This Row],[Delay in Payment ]],"") -> 45362 | AA6: =IF(Table5[[#This Row],[Payment date]]<>"",Table5[[#This Row],[Beginning balance]]-Table5[[#This Row],[Principal Payment]] - Table5[[#This Row],[Extra Payment]],"") -> 45000 | AB6: =IF(Table5[[#This Row],[Payment date]]<>"",Table5[[#This Row],[Draw Fee]]+Table5[[#This Row],[Interest]]+Table5[[#This Row],[Principal Payment]]+Table5[[#This Row],[Overdue Interest]],"") -> 6088.8356
B7: Transaction Fee | E7: 0.003 | G7: =IFERROR(RANK(Table4[[#This Row],[Loan Date]],Table4[[#All],[Loan Date]],1) +COUNTIF($I$6:I7,I7)-1,"") -> 2 | H7: 20000 | I7: 45345 | J7: =IF(Table4[[#This Row],[Loan Date]]<>"",IF($E$14 = "End of Month", EOMONTH(Table4[[#This Row],[Loan Date]],IF(DAY(EOMONTH(Table4[[#This Row],[Loan Date]],0)) - DAY(Table4[[#This Row],[Loan Date]])<=$E$15,1,0)),IF($E$14 = "Mid of Month", EOMONTH(Table4[[#This Row],[Loan Date]],IF(15 - DAY(Table4[[#This Row],[Loan Date]])<=$E$15,0,-1))+15,IF($E$14 = "Start of Month", EOMONTH(Table4[[#This Row],[Loan Date]],IF(DAY(EOMONTH(Table4[[#This Row],[Loan Date]],0)) - DAY(Table4[[#This Row],[Loan Date]])<=$E$15,1,0))) + 1)),"") -> 45383 | K7: =IF(Table4[[#This Row],[Loan Date]]<>"", IF($E$14 = "End of Month", EOMONTH(Table4[[#This Row],[Loan Date]],6+IF(DAY(EOMONTH(Table4[[#This Row],[Loan Date]],0)) - DAY(Table4[[#This Row],[Loan Date]])<=$E$15,0,-1)), IF($E$14 = "Mid of Month", EOMONTH(Table4[[#This Row],[Loan Date]],6+IF(15 - DAY(Table4[[#This Row],[Loan Date]])<=$E$15,-1,-2))+15, IF($E$14 = "Start of Month", EOMONTH(Table4[[#This Row],[Loan Date]],6+IF(DAY(EOMONTH(Table4[[#This Row],[Loan Date]],0)) - DAY(Table4[[#This Row],[Loan Date]])<=$E$15,0,-1)) + 1) ) ),"") -> 45536 | L7: =IF(Table4[[#This Row],[Loan Date]]<>"",Table4[[#This Row],[Loan Amount]]/PaymentsPerYear,"") -> 3333.3333 | M7: {=IF(Table4[[#This Row],[Loan Date]]<>"", ((Table4[[#This Row],[Loan Payment Start Date]]-Table4[[#This Row],[Loan Date]])*Table4[[#This Row],[Loan Amount]]*InterestRate/360) + SUM((_xlfn.SEQUENCE(6, 1, Table4[[#This Row],[Loan Amount]]-Table4[[#This Row],[Loan Amount]]/6, -Table4[[#This Row],[Loan Amount]]/6))* (IF($E$14 = "End of Month", EOMONTH(EDATE(Table4[[#This Row],[Loan Payment Start Date]],_xlfn.SEQUENCE(6,1,1,1)),0),IF($E$14 = "Mid of Month",EDATE(Table4[[#This Row],[Loan Payment Start Date]],_xlfn.SEQUENCE(6,1,1,1)), IF($E$14 = "Start of Month", EOMONTH(EDATE(Table4[[#This Row],[Loan Payment Start Date]],_xlfn.SEQUENCE(6,1,1,1)),-1)+1))) - IF($E$14 = "End of Month", EOMONTH(EDATE(Table4[[#This Row],[Loan Payment Start Date]],_xlfn.SEQUENCE(6,1,1,1)),-1),IF($E$14 = "Mid of Month",EDATE(Table4[[#This Row],[Loan Payment Start Date]],_xlfn.SEQUENCE(6,1,0,1)), IF($E$14 = "Start of Month", EOMONTH(EDATE(Table4[[#This Row],[Loan Payment Start Date]],_xlfn.SEQUENCE(6,1,1,1)),-2)+1))))*InterestRate/360),"")} -> 1141.6667 | N7: =IF(Table4[[#This Row],[Loan Amount]]<>"", IF((LoanAmount - (SUMIFS(Table4[Loan Amount],Table4[Loan Date],"<"&Table4[[#This Row],[Loan Date]]) -SUMIFS(Table5[Principal Payment],Table5[Payment date],"<="&Table4[[#This Row],[Loan Date]]) - SUMIFS(Table5[Extra Payment],Table5[Payment date],"<="&Table4[[#This Row],[Loan Date]])) > Table4[[#This Row],[Loan Amount]]),"Yes","No"),"") -> Yes | O7: =IF(Table4[[#This Row],[Loan Amount]]<>"", LoanAmount - (SUMIFS(Table4[Loan Amount],Table4[Loan Date],"<"&Table4[[#This Row],[Loan Date]]) -SUMIFS(Table5[Principal Payment],Table5[Payment date],"<="&Table4[[#This Row],[Loan Date]]) - SUMIFS(Table5[Extra Payment],Table5[Payment date],"<="&Table4[[#This Row],[Loan Date]])) - Table4[[#This Row],[Loan Amount]],"") -> 50000 | Q7: =IF($E$14="Mid of Month",(IF(EDATE(MIN(Table4[[#All],[Loan Date]]), ROW()-ROW($Q$6)) > EDATE(MAX(Table4[[#All],[Loan Payment End Date]]),1), "", (EOMONTH(EDATE(MIN(Table4[[#All],[Loan Date]]), ROW()-ROW($Q$6)),IF(DAY(EOMONTH(MIN(Table4[[#All],[Loan Date]]),0)) - DAY(MIN(Table4[[#All],[Loan Date]])) <= $E$15, 0, -1))+ 15))), IF($E$14="End of Month",(IF(EDATE(MIN(Table4[[#All],[Loan Date]]), ROW()-ROW($Q$6)) > MAX(Table4[[#All],[Loan Payment End Date]]), "", (EOMONTH(EDATE(MIN(Table4[[#All],[Loan Date]]), ROW()-ROW($Q$6)),IF(31 - DAY(MIN(Table4[[#All],[Loan Date]])) <= $E$15, 1, 0))))), IF($E$14="Start of Month",(IF(EDATE(MIN(Table4[[#All],[Loan Date]]), ROW()-ROW($Q$6)) > MAX(Table4[[#All],[Loan Payment End Date]]), "", (EOMONTH(EDATE(MIN(Table4[[#All],[Loan Date]]), ROW()-ROW($Q$6)),IF(31 - DAY(MIN(Table4[[#All],[Loan Date]])) <= $E$15, 1, 0))) + 1 ))) ) ) -> 45383 | R7: =IF(Table5[[#This Row],[Payment date]]<>"", SUMIFS(Table4[[#All],[Loan Amount]],Table4[[#All],[Loan Date]],"<="&Table5[[#This Row],[Payment date]]) - SUM($S$5:S6)- SUM($W$5:W6),"") -> 45000 | S7: =IF(Table5[[#This Row],[Payment date]]<>"",SUM('Individual Loan Schedule'!C10:HR10) - SUM('Early Payments'!D10:HS10),"") -> 8333.3333 | T7: {=IF(Table5[[#This Row],[Payment date]]<>"",((SUMIFS(Table4[Loan Amount],Table4[Loan Payment Start Date],"<"&Table5[[#This Row],[Payment date]]) - SUM($S$5:$S6) - SUM($W$5:W6))*InterestRate*(Table5[[#This Row],[Payment date]] - IF($E$14="End of Month",EOMONTH(Table5[[#This Row],[Payment date]],-1), IF($E$14="Mid of Month",EOMONTH(Table5[[#This Row],[Payment date]],-2)+15, IF($E$14="Start of Month",EOMONTH(Table5[[#This Row],[Payment date]],-2) + 1))) )/360) + (SUM(IFERROR((IF(Table4[Loan Payment Start Date]=Table5[[#This Row],[Payment date]],Table4[Loan Amount],"")*(Table4[Loan Payment Start Date]-Table4[Loan Date])*InterestRate/360),0),0)),"")} -> 767.5 | U7: =IF(Table5[[#This Row],[Payment date]]<>"",SUMIFS(Table4[[#All],[Loan Amount]],Table4[[#All],[Loan Payment Start Date]],"="&Table5[[#This Row],[Payment date]])*($E$7),"") -> 60 | V7: {=IF(Table5[[#This Row],[Payment date]]<>"",IF(Table5[[#This Row],[Payment date]]=MIN(Table4[[#All],[Loan Payment Start Date]]),$E$8+$E$10*LoanAmount,0) + IF(Table5[[#This Row],[Payment date]] =MIN(_xlfn._xlws.FILTER(Table5[Payment date],(Table5[Payment date]>=EDATE(LoanStartDate,12*DATEDIF(LoanStartDate,Table5[[#This Row],[Payment date]],"y")))*(Table5[Beginning balance]<>0))), $E$9*LoanAmount,0),"")} -> 0 | Y7: =IF(Table5[[#This Row],[Payment date]]<>"",(SUMIFS(Table4[Loan Amount],Table4[Loan Payment Start Date],"<="&Table5[[#This Row],[Payment date]]) - SUM($S$5:$S6) - - SUM($W$5:W6))*Table5[[#This Row],[Delay in Payment ]]*($E$16+ InterestRate)/365,"") -> 0 | Z7: =IF(Table5[[#This Row],[Payment date]]<>"",Table5[[#This Row],[Payment date]]+Table5[[#This Row],[Delay in Payment ]],"") -> 45383 | AA7: =IF(Table5[[#This Row],[Payment date]]<>"",Table5[[#This Row],[Beginning balance]]-Table5[[#This Row],[Principal Payment]] - Table5[[#This Row],[Extra Payment]],"") -> 36666.667 | AB7: =IF(Table5[[#This Row],[Payment date]]<>"",Table5[[#This Row],[Draw Fee]]+Table5[[#This Row],[Interest]]+Table5[[#This Row],[Principal Payment]]+Table5[[#This Row],[Overdue Interest]],"") -> 9160.8333
B8: Credit Evaluation Fee | E8: 99 | G8: =IFERROR(RANK(Table4[[#This Row],[Loan Date]],Table4[[#All],[Loan Date]],1) +COUNTIF($I$6:I8,I8)-1,"") -> 3 | H8: 50000 | I8: 45403 | J8: =IF(Table4[[#This Row],[Loan Date]]<>"",IF($E$14 = "End of Month", EOMONTH(Table4[[#This Row],[Loan Date]],IF(DAY(EOMONTH(Table4[[#This Row],[Loan Date]],0)) - DAY(Table4[[#This Row],[Loan Date]])<=$E$15,1,0)),IF($E$14 = "Mid of Month", EOMONTH(Table4[[#This Row],[Loan Date]],IF(15 - DAY(Table4[[#This Row],[Loan Date]])<=$E$15,0,-1))+15,IF($E$14 = "Start of Month", EOMONTH(Table4[[#This Row],[Loan Date]],IF(DAY(EOMONTH(Table4[[#This Row],[Loan Date]],0)) - DAY(Table4[[#This Row],[Loan Date]])<=$E$15,1,0))) + 1)),"") -> 45413 | K8: =IF(Table4[[#This Row],[Loan Date]]<>"", IF($E$14 = "End of Month", EOMONTH(Table4[[#This Row],[Loan Date]],6+IF(DAY(EOMONTH(Table4[[#This Row],[Loan Date]],0)) - DAY(Table4[[#This Row],[Loan Date]])<=$E$15,0,-1)), IF($E$14 = "Mid of Month", EOMONTH(Table4[[#This Row],[Loan Date]],6+IF(15 - DAY(Table4[[#This Row],[Loan Date]])<=$E$15,-1,-2))+15, IF($E$14 = "Start of Month", EOMONTH(Table4[[#This Row],[Loan Date]],6+IF(DAY(EOMONTH(Table4[[#This Row],[Loan Date]],0)) - DAY(Table4[[#This Row],[Loan Date]])<=$E$15,0,-1)) + 1) ) ),"") -> 45566 | L8: =IF(Table4[[#This Row],[Loan Date]]<>"",Table4[[#This Row],[Loan Amount]]/PaymentsPerYear,"") -> 8333.3333 | M8: {=IF(Table4[[#This Row],[Loan Date]]<>"", ((Table4[[#This Row],[Loan Payment Start Date]]-Table4[[#This Row],[Loan Date]])*Table4[[#This Row],[Loan Amount]]*InterestRate/360) + SUM((_xlfn.SEQUENCE(6, 1, Table4[[#This Row],[Loan Amount]]-Table4[[#This Row],[Loan Amount]]/6, -Table4[[#This Row],[Loan Amount]]/6))* (IF($E$14 = "End of Month", EOMONTH(EDATE(Table4[[#This Row],[Loan Payment Start Date]],_xlfn.SEQUENCE(6,1,1,1)),0),IF($E$14 = "Mid of Month",EDATE(Table4[[#This Row],[Loan Payment Start Date]],_xlfn.SEQUENCE(6,1,1,1)), IF($E$14 = "Start of Month", EOMONTH(EDATE(Table4[[#This Row],[Loan Payment Start Date]],_xlfn.SEQUENCE(6,1,1,1)),-1)+1))) - IF($E$14 = "End of Month", EOMONTH(EDATE(Table4[[#This Row],[Loan Payment Start Date]],_xlfn.SEQUENCE(6,1,1,1)),-1),IF($E$14 = "Mid of Month",EDATE(Table4[[#This Row],[Loan Payment Start Date]],_xlfn.SEQUENCE(6,1,0,1)), IF($E$14 = "Start of Month", EOMONTH(EDATE(Table4[[#This Row],[Loan Payment Start Date]],_xlfn.SEQUENCE(6,1,1,1)),-2)+1))))*InterestRate/360),"")} -> 2166.6667 | N8: =IF(Table4[[#This Row],[Loan Amount]]<>"", IF((LoanAmount - (SUMIFS(Table4[Loan Amount],Table4[Loan Date],"<"&Table4[[#This Row],[Loan Date]]) -SUMIFS(Table5[Principal Payment],Table5[Payment date],"<="&Table4[[#This Row],[Loan Date]]) - SUMIFS(Table5[Extra Payment],Table5[Payment date],"<="&Table4[[#This Row],[Loan Date]])) > Table4[[#This Row],[Loan Amount]]),"Yes","No"),"") -> Yes | O8: =IF(Table4[[#This Row],[Loan Amount]]<>"", LoanAmount - (SUMIFS(Table4[Loan Amount],Table4[Loan Date],"<"&Table4[[#This Row],[Loan Date]]) -SUMIFS(Table5[Principal Payment],Table5[Payment date],"<="&Table4[[#This Row],[Loan Date]]) - SUMIFS(Table5[Extra Payment],Table5[Payment date],"<="&Table4[[#This Row],[Loan Date]])) - Table4[[#This Row],[Loan Amount]],"") -> 13333.333 | Q8: =IF($E$14="Mid of Month",(IF(EDATE(MIN(Table4[[#All],[Loan Date]]), ROW()-ROW($Q$6)) > EDATE(MAX(Table4[[#All],[Loan Payment End Date]]),1), "", (EOMONTH(EDATE(MIN(Table4[[#All],[Loan Date]]), ROW()-ROW($Q$6)),IF(DAY(EOMONTH(MIN(Table4[[#All],[Loan Date]]),0)) - DAY(MIN(Table4[[#All],[Loan Date]])) <= $E$15, 0, -1))+ 15))), IF($E$14="End of Month",(IF(EDATE(MIN(Table4[[#All],[Loan Date]]), ROW()-ROW($Q$6)) > MAX(Table4[[#All],[Loan Payment End Date]]), "", (EOMONTH(EDATE(MIN(Table4[[#All],[Loan Date]]), ROW()-ROW($Q$6)),IF(31 - DAY(MIN(Table4[[#All],[Loan Date]])) <= $E$15, 1, 0))))), IF($E$14="Start of Month",(IF(EDATE(MIN(Table4[[#All],[Loan Date]]), ROW()-ROW($Q$6)) > MAX(Table4[[#All],[Loan Payment End Date]]), "", (EOMONTH(EDATE(MIN(Table4[[#All],[Loan Date]]), ROW()-ROW($Q$6)),IF(31 - DAY(MIN(Table4[[#All],[Loan Date]])) <= $E$15, 1, 0))) + 1 ))) ) ) -> 45413 | R8: =IF(Table5[[#This Row],[Payment date]]<>"", SUMIFS(Table4[[#All],[Loan Amount]],Table4[[#All],[Loan Date]],"<="&Table5[[#This Row],[Payment date]]) - SUM($S$5:S7)- SUM($W$5:W7),"") -> 86666.667 | S8: =IF(Table5[[#This Row],[Payment date]]<>"",SUM('Individual Loan Schedule'!C11:HR11) - SUM('Early Payments'!D11:HS11),"") -> 16666.667 | T8: {=IF(Table5[[#This Row],[Payment date]]<>"",((SUMIFS(Table4[Loan Amount],Table4[Loan Payment Start Date],"<"&Table5[[#This Row],[Payment date]]) - SUM($S$5:$S7) - SUM($W$5:W7))*InterestRate*(Table5[[#This Row],[Payment date]] - IF($E$14="End of Month",EOMONTH(Table5[[#This Row],[Payment date]],-1), IF($E$14="Mid of Month",EOMONTH(Table5[[#This Row],[Payment date]],-2)+15, IF($E$14="Start of Month",EOMONTH(Table5[[#This Row],[Payment date]],-2) + 1))) )/360) + (SUM(IFERROR((IF(Table4[Loan Payment Start Date]=Table5[[#This Row],[Payment date]],Table4[Loan Amount],"")*(Table4[Loan Payment Start Date]-Table4[Loan Date])*InterestRate/360),0),0)),"")} -> 800 | U8: =IF(Table5[[#This Row],[Payment date]]<>"",SUMIFS(Table4[[#All],[Loan Amount]],Table4[[#All],[Loan Payment Start Date]],"="&Table5[[#This Row],[Payment date]])*($E$7),"") -> 150 | V8: {=IF(Table5[[#This Row],[Payment date]]<>"",IF(Table5[[#This Row],[Payment date]]=MIN(Table4[[#All],[Loan Payment Start Date]]),$E$8+$E$10*LoanAmount,0) + IF(Table5[[#This Row],[Payment date]] =MIN(_xlfn._xlws.FILTER(Table5[Payment date],(Table5[Payment date]>=EDATE(LoanStartDate,12*DATEDIF(LoanStartDate,Table5[[#This Row],[Payment date]],"y")))*(Table5[Beginning balance]<>0))), $E$9*LoanAmount,0),"")} -> 0 | W8: 17000 | Y8: =IF(Table5[[#This Row],[Payment date]]<>"",(SUMIFS(Table4[Loan Amount],Table4[Loan Payment Start Date],"<="&Table5[[#This Row],[Payment date]]) - SUM($S$5:$S7) - - SUM($W$5:W7))*Table5[[#This Row],[Delay in Payment ]]*($E$16+ InterestRate)/365,"") -> 0 | Z8: =IF(Table5[[#This Row],[Payment date]]<>"",Table5[[#This Row],[Payment date]]+Table5[[#This Row],[Delay in Payment ]],"") -> 45413 | AA8: =IF(Table5[[#This Row],[Payment date]]<>"",Table5[[#This Row],[Beginning balance]]-Table5[[#This Row],[Principal Payment]] - Table5[[#This Row],[Extra Payment]],"") -> 53000 | AB8: =IF(Table5[[#This Row],[Payment date]]<>"",Table5[[#This Row],[Draw Fee]]+Table5[[#This Row],[Interest]]+Table5[[#This Row],[Principal Payment]]+Table5[[#This Row],[Overdue Interest]],"") -> 17616.667
B9: Annual Fee (of the approved credit line) | E9: 0.005 | G9: =IFERROR(RANK(Table4[[#This Row],[Loan Date]],Table4[[#All],[Loan Date]],1) +COUNTIF($I$6:I9,I9)-1,"") -> 4 | H9: 15000 | I9: 45613 | J9: =IF(Table4[[#This Row],[Loan Date]]<>"",IF($E$14 = "End of Month", EOMONTH(Table4[[#This Row],[Loan Date]],IF(DAY(EOMONTH(Table4[[#This Row],[Loan Date]],0)) - DAY(Table4[[#This Row],[Loan Date]])<=$E$15,1,0)),IF($E$14 = "Mid of Month", EOMONTH(Table4[[#This Row],[Loan Date]],IF(15 - DAY(Table4[[#This Row],[Loan Date]])<=$E$15,0,-1))+15,IF($E$14 = "Start of Month", EOMONTH(Table4[[#This Row],[Loan Date]],IF(DAY(EOMONTH(Table4[[#This Row],[Loan Date]],0)) - DAY(Table4[[#This Row],[Loan Date]])<=$E$15,1,0))) + 1)),"") -> 45627 | K9: =IF(Table4[[#This Row],[Loan Date]]<>"", IF($E$14 = "End of Month", EOMONTH(Table4[[#This Row],[Loan Date]],6+IF(DAY(EOMONTH(Table4[[#This Row],[Loan Date]],0)) - DAY(Table4[[#This Row],[Loan Date]])<=$E$15,0,-1)), IF($E$14 = "Mid of Month", EOMONTH(Table4[[#This Row],[Loan Date]],6+IF(15 - DAY(Table4[[#This Row],[Loan Date]])<=$E$15,-1,-2))+15, IF($E$14 = "Start of Month", EOMONTH(Table4[[#This Row],[Loan Date]],6+IF(DAY(EOMONTH(Table4[[#This Row],[Loan Date]],0)) - DAY(Table4[[#This Row],[Loan Date]])<=$E$15,0,-1)) + 1) ) ),"") -> 45778 | L9: =IF(Table4[[#This Row],[Loan Date]]<>"",Table4[[#This Row],[Loan Amount]]/PaymentsPerYear,"") -> 2500 | M9: {=IF(Table4[[#This Row],[Loan Date]]<>"", ((Table4[[#This Row],[Loan Payment Start Date]]-Table4[[#This Row],[Loan Date]])*Table4[[#This Row],[Loan Amount]]*InterestRate/360) + SUM((_xlfn.SEQUENCE(6, 1, Table4[[#This Row],[Loan Amount]]-Table4[[#This Row],[Loan Amount]]/6, -Table4[[#This Row],[Loan Amount]]/6))* (IF($E$14 = "End of Month", EOMONTH(EDATE(Table4[[#This Row],[Loan Payment Start Date]],_xlfn.SEQUENCE(6,1,1,1)),0),IF($E$14 = "Mid of Month",EDATE(Table4[[#This Row],[Loan Payment Start Date]],_xlfn.SEQUENCE(6,1,1,1)), IF($E$14 = "Start of Month", EOMONTH(EDATE(Table4[[#This Row],[Loan Payment Start Date]],_xlfn.SEQUENCE(6,1,1,1)),-1)+1))) - IF($E$14 = "End of Month", EOMONTH(EDATE(Table4[[#This Row],[Loan Payment Start Date]],_xlfn.SEQUENCE(6,1,1,1)),-1),IF($E$14 = "Mid of Month",EDATE(Table4[[#This Row],[Loan Payment Start Date]],_xlfn.SEQUENCE(6,1,0,1)), IF($E$14 = "Start of Month", EOMONTH(EDATE(Table4[[#This Row],[Loan Payment Start Date]],_xlfn.SEQUENCE(6,1,1,1)),-2)+1))))*InterestRate/360),"")} -> 673.75 | N9: =IF(Table4[[#This Row],[Loan Amount]]<>"", IF((LoanAmount - (SUMIFS(Table4[Loan Amount],Table4[Loan Date],"<"&Table4[[#This Row],[Loan Date]]) -SUMIFS(Table5[Principal Payment],Table5[Payment date],"<="&Table4[[#This Row],[Loan Date]]) - SUMIFS(Table5[Extra Payment],Table5[Payment date],"<="&Table4[[#This Row],[Loan Date]])) > Table4[[#This Row],[Loan Amount]]),"Yes","No"),"") -> Yes | O9: =IF(Table4[[#This Row],[Loan Amount]]<>"", LoanAmount - (SUMIFS(Table4[Loan Amount],Table4[Loan Date],"<"&Table4[[#This Row],[Loan Date]]) -SUMIFS(Table5[Principal Payment],Table5[Payment date],"<="&Table4[[#This Row],[Loan Date]]) - SUMIFS(Table5[Extra Payment],Table5[Payment date],"<="&Table4[[#This Row],[Loan Date]])) - Table4[[#This Row],[Loan Amount]],"") -> 85000 | Q9: =IF($E$14="Mid of Month",(IF(EDATE(MIN(Table4[[#All],[Loan Date]]), ROW()-ROW($Q$6)) > EDATE(MAX(Table4[[#All],[Loan Payment End Date]]),1), "", (EOMONTH(EDATE(MIN(Table4[[#All],[Loan Date]]), ROW()-ROW($Q$6)),IF(DAY(EOMONTH(MIN(Table4[[#All],[Loan Date]]),0)) - DAY(MIN(Table4[[#All],[Loan Date]])) <= $E$15, 0, -1))+ 15))), IF($E$14="End of Month",(IF(EDATE(MIN(Table4[[#All],[Loan Date]]), ROW()-ROW($Q$6)) > MAX(Table4[[#All],[Loan Payment End Date]]), "", (EOMONTH(EDATE(MIN(Table4[[#All],[Loan Date]]), ROW()-ROW($Q$6)),IF(31 - DAY(MIN(Table4[[#All],[Loan Date]])) <= $E$15, 1, 0))))), IF($E$14="Start of Month",(IF(EDATE(MIN(Table4[[#All],[Loan Date]]), ROW()-ROW($Q$6)) > MAX(Table4[[#All],[Loan Payment End Date]]), "", (EOMONTH(EDATE(MIN(Table4[[#All],[Loan Date]]), ROW()-ROW($Q$6)),IF(31 - DAY(MIN(Table4[[#All],[Loan Date]])) <= $E$15, 1, 0))) + 1 ))) ) ) -> 45444 | R9: =IF(Table5[[#This Row],[Payment date]]<>"", SUMIFS(Table4[[#All],[Loan Amount]],Table4[[#All],[Loan Date]],"<="&Table5[[#This Row],[Payment date]]) - SUM($S$5:S8)- SUM($W$5:W8),"") -> 53000 | S9: =IF(Table5[[#This Row],[Payment date]]<>"",SUM('Individual Loan Schedule'!C12:HR12) - SUM('Early Payments'!D12:HS12),"") -> 11666.667 | T9: {=IF(Table5[[#This Row],[Payment date]]<>"",((SUMIFS(Table4[Loan Amount],Table4[Loan Payment Start Date],"<"&Table5[[#This Row],[Payment date]]) - SUM($S$5:$S8) - SUM($W$5:W8))*InterestRate*(Table5[[#This Row],[Payment date]] - IF($E$14="End of Month",EOMONTH(Table5[[#This Row],[Payment date]],-1), IF($E$14="Mid of Month",EOMONTH(Table5[[#This Row],[Payment date]],-2)+15, IF($E$14="Start of Month",EOMONTH(Table5[[#This Row],[Payment date]],-2) + 1))) )/360) + (SUM(IFERROR((IF(Table4[Loan Payment Start Date]=Table5[[#This Row],[Payment date]],Table4[Loan Amount],"")*(Table4[Loan Payment Start Date]-Table4[Loan Date])*InterestRate/360),0),0)),"")} -> 821.5 | U9: =IF(Table5[[#This Row],[Payment date]]<>"",SUMIFS(Table4[[#All],[Loan Amount]],Table4[[#All],[Loan Payment Start Date]],"="&Table5[[#This Row],[Payment date]])*($E$7),"") -> 0 | V9: {=IF(Table5[[#This Row],[Payment date]]<>"",IF(Table5[[#This Row],[Payment date]]=MIN(Table4[[#All],[Loan Payment Start Date]]),$E$8+$E$10*LoanAmount,0) + IF(Table5[[#This Row],[Payment date]] =MIN(_xlfn._xlws.FILTER(Table5[Payment date],(Table5[Payment date]>=EDATE(LoanStartDate,12*DATEDIF(LoanStartDate,Table5[[#This Row],[Payment date]],"y")))*(Table5[Beginning balance]<>0))), $E$9*LoanAmount,0),"")} -> 0 | Y9: =IF(Table5[[#This Row],[Payment date]]<>"",(SUMIFS(Table4[Loan Amount],Table4[Loan Payment Start Date],"<="&Table5[[#This Row],[Payment date]]) - SUM($S$5:$S8) - - SUM($W$5:W8))*Table5[[#This Row],[Delay in Payment ]]*($E$16+ InterestRate)/365,"") -> 0 | Z9: =IF(Table5[[#This Row],[Payment date]]<>"",Table5[[#This Row],[Payment date]]+Table5[[#This Row],[Delay in Payment ]],"") -> 45444 | AA9: =IF(Table5[[#This Row],[Payment date]]<>"",Table5[[#This Row],[Beginning balance]]-Table5[[#This Row],[Principal Payment]] - Table5[[#This Row],[Extra Payment]],"") -> 41333.333 | AB9: =IF(Table5[[#This Row],[Payment date]]<>"",Table5[[#This Row],[Draw Fee]]+Table5[[#This Row],[Interest]]+Table5[[#This Row],[Principal Payment]]+Table5[[#This Row],[Overdue Interest]],"") -> 12488.167
B10: Onboarding Fee (of the approved credit line) | E10: 0.0025 | G10: =IFERROR(RANK(Table4[[#This Row],[Loan Date]],Table4[[#All],[Loan Date]],1) +COUNTIF($I$6:I10,I10)-1,"") | J10: =IF(Table4[[#This Row],[Loan Date]]<>"",IF($E$14 = "End of Month", EOMONTH(Table4[[#This Row],[Loan Date]],IF(DAY(EOMONTH(Table4[[#This Row],[Loan Date]],0)) - DAY(Table4[[#This Row],[Loan Date]])<=$E$15,1,0)),IF($E$14 = "Mid of Month", EOMONTH(Table4[[#This Row],[Loan Date]],IF(15 - DAY(Table4[[#This Row],[Loan Date]])<=$E$15,0,-1))+15,IF($E$14 = "Start of Month", EOMONTH(Table4[[#This Row],[Loan Date]],IF(DAY(EOMONTH(Table4[[#This Row],[Loan Date]],0)) - DAY(Table4[[#This Row],[Loan Date]])<=$E$15,1,0))) + 1)),"") | K10: =IF(Table4[[#This Row],[Loan Date]]<>"", IF($E$14 = "End of Month", EOMONTH(Table4[[#This Row],[Loan Date]],6+IF(DAY(EOMONTH(Table4[[#This Row],[Loan Date]],0)) - DAY(Table4[[#This Row],[Loan Date]])<=$E$15,0,-1)), IF($E$14 = "Mid of Month", EOMONTH(Table4[[#This Row],[Loan Date]],6+IF(15 - DAY(Table4[[#This Row],[Loan Date]])<=$E$15,-1,-2))+15, IF($E$14 = "Start of Month", EOMONTH(Table4[[#This Row],[Loan Date]],6+IF(DAY(EOMONTH(Table4[[#This Row],[Loan Date]],0)) - DAY(Table4[[#This Row],[Loan Date]])<=$E$15,0,-1)) + 1) ) ),"") | L10: =IF(Table4[[#This Row],[Loan Date]]<>"",Table4[[#This Row],[Loan Amount]]/PaymentsPerYear,"") | M10: {=IF(Table4[[#This Row],[Loan Date]]<>"", ((Table4[[#This Row],[Loan Payment Start Date]]-Table4[[#This Row],[Loan Date]])*Table4[[#This Row],[Loan Amount]]*InterestRate/360) + SUM((_xlfn.SEQUENCE(6, 1, Table4[[#This Row],[Loan Amount]]-Table4[[#This Row],[Loan Amount]]/6, -Table4[[#This Row],[Loan Amount]]/6))* (IF($E$14 = "End of Month", EOMONTH(EDATE(Table4[[#This Row],[Loan Payment Start Date]],_xlfn.SEQUENCE(6,1,1,1)),0),IF($E$14 = "Mid of Month",EDATE(Table4[[#This Row],[Loan Payment Start Date]],_xlfn.SEQUENCE(6,1,1,1)), IF($E$14 = "Start of Month", EOMONTH(EDATE(Table4[[#This Row],[Loan Payment Start Date]],_xlfn.SEQUENCE(6,1,1,1)),-1)+1))) - IF($E$14 = "End of Month", EOMONTH(EDATE(Table4[[#This Row],[Loan Payment Start Date]],_xlfn.SEQUENCE(6,1,1,1)),-1),IF($E$14 = "Mid of Month",EDATE(Table4[[#This Row],[Loan Payment Start Date]],_xlfn.SEQUENCE(6,1,0,1)), IF($E$14 = "Start of Month", EOMONTH(EDATE(Table4[[#This Row],[Loan Payment Start Date]],_xlfn.SEQUENCE(6,1,1,1)),-2)+1))))*InterestRate/360),"")} | N10: =IF(Table4[[#This Row],[Loan Amount]]<>"", IF((LoanAmount - (SUMIFS(Table4[Loan Amount],Table4[Loan Date],"<"&Table4[[#This Row],[Loan Date]]) -SUMIFS(Table5[Principal Payment],Table5[Payment date],"<="&Table4[[#This Row],[Loan Date]]) - SUMIFS(Table5[Extra Payment],Table5[Payment date],"<="&Table4[[#This Row],[Loan Date]])) > Table4[[#This Row],[Loan Amount]]),"Yes","No"),"") | O10: =IF(Table4[[#This Row],[Loan Amount]]<>"", LoanAmount - (SUMIFS(Table4[Loan Amount],Table4[Loan Date],"<"&Table4[[#This Row],[Loan Date]]) -SUMIFS(Table5[Principal Payment],Table5[Payment date],"<="&Table4[[#This Row],[Loan Date]]) - SUMIFS(Table5[Extra Payment],Table5[Payment date],"<="&Table4[[#This Row],[Loan Date]])) - Table4[[#This Row],[Loan Amount]],"") | Q10: =IF($E$14="Mid of Month",(IF(EDATE(MIN(Table4[[#All],[Loan Date]]), ROW()-ROW($Q$6)) > EDATE(MAX(Table4[[#All],[Loan Payment End Date]]),1), "", (EOMONTH(EDATE(MIN(Table4[[#All],[Loan Date]]), ROW()-ROW($Q$6)),IF(DAY(EOMONTH(MIN(Table4[[#All],[Loan Date]]),0)) - DAY(MIN(Table4[[#All],[Loan Date]])) <= $E$15, 0, -1))+ 15))), IF($E$14="End of Month",(IF(EDATE(MIN(Table4[[#All],[Loan Date]]), ROW()-ROW($Q$6)) > MAX(Table4[[#All],[Loan Payment End Date]]), "", (EOMONTH(EDATE(MIN(Table4[[#All],[Loan Date]]), ROW()-ROW($Q$6)),IF(31 - DAY(MIN(Table4[[#All],[Loan Date]])) <= $E$15, 1, 0))))), IF($E$14="Start of Month",(IF(EDATE(MIN(Table4[[#All],[Loan Date]]), ROW()-ROW($Q$6)) > MAX(Table4[[#All],[Loan Payment End Date]]), "", (EOMONTH(EDATE(MIN(Table4[[#All],[Loan Date]]), ROW()-ROW($Q$6)),IF(31 - DAY(MIN(Table4[[#All],[Loan Date]])) <= $E$15, 1, 0))) + 1 ))) ) ) -> 45474 | R10: =IF(Table5[[#This Row],[Payment date]]<>"", SUMIFS(Table4[[#All],[Loan Amount]],Table4[[#All],[Loan Date]],"<="&Table5[[#This Row],[Payment date]]) - SUM($S$5:S9)- SUM($W$5:W9),"") -> 41333.333 | S10: =IF(Table5[[#This Row],[Payment date]]<>"",SUM('Individual Loan Schedule'!C13:HR13) - SUM('Early Payments'!D13:HS13),"") -> 11666.667 | T10: {=IF(Table5[[#This Row],[Payment date]]<>"",((SUMIFS(Table4[Loan Amount],Table4[Loan Payment Start Date],"<"&Table5[[#This Row],[Payment date]]) - SUM($S$5:$S9) - SUM($W$5:W9))*InterestRate*(Table5[[#This Row],[Payment date]] - IF($E$14="End of Month",EOMONTH(Table5[[#This Row],[Payment date]],-1), IF($E$14="Mid of Month",EOMONTH(Table5[[#This Row],[Payment date]],-2)+15, IF($E$14="Start of Month",EOMONTH(Table5[[#This Row],[Payment date]],-2) + 1))) )/360) + (SUM(IFERROR((IF(Table4[Loan Payment Start Date]=Table5[[#This Row],[Payment date]],Table4[Loan Amount],"")*(Table4[Loan Payment Start Date]-Table4[Loan Date])*InterestRate/360),0),0)),"")} -> 620 | U10: =IF(Table5[[#This Row],[Payment date]]<>"",SUMIFS(Table4[[#All],[Loan Amount]],Table4[[#All],[Loan Payment Start Date]],"="&Table5[[#This Row],[Payment date]])*($E$7),"") -> 0 | V10: {=IF(Table5[[#This Row],[Payment date]]<>"",IF(Table5[[#This Row],[Payment date]]=MIN(Table4[[#All],[Loan Payment Start Date]]),$E$8+$E$10*LoanAmount,0) + IF(Table5[[#This Row],[Payment date]] =MIN(_xlfn._xlws.FILTER(Table5[Payment date],(Table5[Payment date]>=EDATE(LoanStartDate,12*DATEDIF(LoanStartDate,Table5[[#This Row],[Payment date]],"y")))*(Table5[Beginning balance]<>0))), $E$9*LoanAmount,0),"")} -> 0 | Y10: =IF(Table5[[#This Row],[Payment date]]<>"",(SUMIFS(Table4[Loan Amount],Table4[Loan Payment Start Date],"<="&Table5[[#This Row],[Payment date]]) - SUM($S$5:$S9) - - SUM($W$5:W9))*Table5[[#This Row],[Delay in Payment ]]*($E$16+ InterestRate)/365,"") -> 0 | Z10: =IF(Table5[[#This Row],[Payment date]]<>"",Table5[[#This Row],[Payment date]]+Table5[[#This Row],[Delay in Payment ]],"") -> 45474 | AA10: =IF(Table5[[#This Row],[Payment date]]<>"",Table5[[#This Row],[Beginning balance]]-Table5[[#This Row],[Principal Payment]] - Table5[[#This Row],[Extra Payment]],"") -> 29666.667 | AB10: =IF(Table5[[#This Row],[Payment date]]<>"",Table5[[#This Row],[Draw Fee]]+Table5[[#This Row],[Interest]]+Table5[[#This Row],[Principal Payment]]+Table5[[#This Row],[Overdue Interest]],"") -> 12286.667
B11: Loan period in years | E11: 1 | G11: =IFERROR(RANK(Table4[[#This Row],[Loan Date]],Table4[[#All],[Loan Date]],1) +COUNTIF($I$6:I11,I11)-1,"") | J11: =IF(Table4[[#This Row],[Loan Date]]<>"",IF($E$14 = "End of Month", EOMONTH(Table4[[#This Row],[Loan Date]],IF(DAY(EOMONTH(Table4[[#This Row],[Loan Date]],0)) - DAY(Table4[[#This Row],[Loan Date]])<=$E$15,1,0)),IF($E$14 = "Mid of Month", EOMONTH(Table4[[#This Row],[Loan Date]],IF(15 - DAY(Table4[[#This Row],[Loan Date]])<=$E$15,0,-1))+15,IF($E$14 = "Start of Month", EOMONTH(Table4[[#This Row],[Loan Date]],IF(DAY(EOMONTH(Table4[[#This Row],[Loan Date]],0)) - DAY(Table4[[#This Row],[Loan Date]])<=$E$15,1,0))) + 1)),"") | K11: =IF(Table4[[#This Row],[Loan Date]]<>"", IF($E$14 = "End of Month", EOMONTH(Table4[[#This Row],[Loan Date]],6+IF(DAY(EOMONTH(Table4[[#This Row],[Loan Date]],0)) - DAY(Table4[[#This Row],[Loan Date]])<=$E$15,0,-1)), IF($E$14 = "Mid of Month", EOMONTH(Table4[[#This Row],[Loan Date]],6+IF(15 - DAY(Table4[[#This Row],[Loan Date]])<=$E$15,-1,-2))+15, IF($E$14 = "Start of Month", EOMONTH(Table4[[#This Row],[Loan Date]],6+IF(DAY(EOMONTH(Table4[[#This Row],[Loan Date]],0)) - DAY(Table4[[#This Row],[Loan Date]])<=$E$15,0,-1)) + 1) ) ),"") | L11: =IF(Table4[[#This Row],[Loan Date]]<>"",Table4[[#This Row],[Loan Amount]]/PaymentsPerYear,"") | M11: {=IF(Table4[[#This Row],[Loan Date]]<>"", ((Table4[[#This Row],[Loan Payment Start Date]]-Table4[[#This Row],[Loan Date]])*Table4[[#This Row],[Loan Amount]]*InterestRate/360) + SUM((_xlfn.SEQUENCE(6, 1, Table4[[#This Row],[Loan Amount]]-Table4[[#This Row],[Loan Amount]]/6, -Table4[[#This Row],[Loan Amount]]/6))* (IF($E$14 = "End of Month", EOMONTH(EDATE(Table4[[#This Row],[Loan Payment Start Date]],_xlfn.SEQUENCE(6,1,1,1)),0),IF($E$14 = "Mid of Month",EDATE(Table4[[#This Row],[Loan Payment Start Date]],_xlfn.SEQUENCE(6,1,1,1)), IF($E$14 = "Start of Month", EOMONTH(EDATE(Table4[[#This Row],[Loan Payment Start Date]],_xlfn.SEQUENCE(6,1,1,1)),-1)+1))) - IF($E$14 = "End of Month", EOMONTH(EDATE(Table4[[#This Row],[Loan Payment Start Date]],_xlfn.SEQUENCE(6,1,1,1)),-1),IF($E$14 = "Mid of Month",EDATE(Table4[[#This Row],[Loan Payment Start Date]],_xlfn.SEQUENCE(6,1,0,1)), IF($E$14 = "Start of Month", EOMONTH(EDATE(Table4[[#This Row],[Loan Payment Start Date]],_xlfn.SEQUENCE(6,1,1,1)),-2)+1))))*InterestRate/360),"")} | N11: =IF(Table4[[#This Row],[Loan Amount]]<>"", IF((LoanAmount - (SUMIFS(Table4[Loan Amount],Table4[Loan Date],"<"&Table4[[#This Row],[Loan Date]]) -SUMIFS(Table5[Principal Payment],Table5[Payment date],"<="&Table4[[#This Row],[Loan Date]]) - SUMIFS(Table5[Extra Payment],Table5[Payment date],"<="&Table4[[#This Row],[Loan Date]])) > Table4[[#This Row],[Loan Amount]]),"Yes","No"),"") | O11: =IF(Table4[[#This Row],[Loan Amount]]<>"", LoanAmount - (SUMIFS(Table4[Loan Amount],Table4[Loan Date],"<"&Table4[[#This Row],[Loan Date]]) -SUMIFS(Table5[Principal Payment],Table5[Payment date],"<="&Table4[[#This Row],[Loan Date]]) - SUMIFS(Table5[Extra Payment],Table5[Payment date],"<="&Table4[[#This Row],[Loan Date]])) - Table4[[#This Row],[Loan Amount]],"") | Q11: =IF($E$14="Mid of Month",(IF(EDATE(MIN(Table4[[#All],[Loan Date]]), ROW()-ROW($Q$6)) > EDATE(MAX(Table4[[#All],[Loan Payment End Date]]),1), "", (EOMONTH(EDATE(MIN(Table4[[#All],[Loan Date]]), ROW()-ROW($Q$6)),IF(DAY(EOMONTH(MIN(Table4[[#All],[Loan Date]]),0)) - DAY(MIN(Table4[[#All],[Loan Date]])) <= $E$15, 0, -1))+ 15))), IF($E$14="End of Month",(IF(EDATE(MIN(Table4[[#All],[Loan Date]]), ROW()-ROW($Q$6)) > MAX(Table4[[#All],[Loan Payment End Date]]), "", (EOMONTH(EDATE(MIN(Table4[[#All],[Loan Date]]), ROW()-ROW($Q$6)),IF(31 - DAY(MIN(Table4[[#All],[Loan Date]])) <= $E$15, 1, 0))))), IF($E$14="Start of Month",(IF(EDATE(MIN(Table4[[#All],[Loan Date]]), ROW()-ROW($Q$6)) > MAX(Table4[[#All],[Loan Payment End Date]]), "", (EOMONTH(EDATE(MIN(Table4[[#All],[Loan Date]]), ROW()-ROW($Q$6)),IF(31 - DAY(MIN(Table4[[#All],[Loan Date]])) <= $E$15, 1, 0))) + 1 ))) ) ) -> 45505 | R11: =IF(Table5[[#This Row],[Payment date]]<>"", SUMIFS(Table4[[#All],[Loan Amount]],Table4[[#All],[Loan Date]],"<="&Table5[[#This Row],[Payment date]]) - SUM($S$5:S10)- SUM($W$5:W10),"") -> 29666.667 | S11: =IF(Table5[[#This Row],[Payment date]]<>"",SUM('Individual Loan Schedule'!C14:HR14) - SUM('Early Payments'!D14:HS14),"") -> 11666.667 | T11: {=IF(Table5[[#This Row],[Payment date]]<>"",((SUMIFS(Table4[Loan Amount],Table4[Loan Payment Start Date],"<"&Table5[[#This Row],[Payment date]]) - SUM($S$5:$S10) - SUM($W$5:W10))*InterestRate*(Table5[[#This Row],[Payment date]] - IF($E$14="End of Month",EOMONTH(Table5[[#This Row],[Payment date]],-1), IF($E$14="Mid of Month",EOMONTH(Table5[[#This Row],[Payment date]],-2)+15, IF($E$14="Start of Month",EOMONTH(Table5[[#This Row],[Payment date]],-2) + 1))) )/360) + (SUM(IFERROR((IF(Table4[Loan Payment Start Date]=Table5[[#This Row],[Payment date]],Table4[Loan Amount],"")*(Table4[Loan Payment Start Date]-Table4[Loan Date])*InterestRate/360),0),0)),"")} -> 459.83333 | U11: =IF(Table5[[#This Row],[Payment date]]<>"",SUMIFS(Table4[[#All],[Loan Amount]],Table4[[#All],[Loan Payment Start Date]],"="&Table5[[#This Row],[Payment date]])*($E$7),"") -> 0 | V11: {=IF(Table5[[#This Row],[Payment date]]<>"",IF(Table5[[#This Row],[Payment date]]=MIN(Table4[[#All],[Loan Payment Start Date]]),$E$8+$E$10*LoanAmount,0) + IF(Table5[[#This Row],[Payment date]] =MIN(_xlfn._xlws.FILTER(Table5[Payment date],(Table5[Payment date]>=EDATE(LoanStartDate,12*DATEDIF(LoanStartDate,Table5[[#This Row],[Payment date]],"y")))*(Table5[Beginning balance]<>0))), $E$9*LoanAmount,0),"")} -> 0 | Y11: =IF(Table5[[#This Row],[Payment date]]<>"",(SUMIFS(Table4[Loan Amount],Table4[Loan Payment Start Date],"<="&Table5[[#This Row],[Payment date]]) - SUM($S$5:$S10) - - SUM($W$5:W10))*Table5[[#This Row],[Delay in Payment ]]*($E$16+ InterestRate)/365,"") -> 0 | Z11: =IF(Table5[[#This Row],[Payment date]]<>"",Table5[[#This Row],[Payment date]]+Table5[[#This Row],[Delay in Payment ]],"") -> 45505 | AA11: =IF(Table5[[#This Row],[Payment date]]<>"",Table5[[#This Row],[Beginning balance]]-Table5[[#This Row],[Principal Payment]] - Table5[[#This Row],[Extra Payment]],"") -> 18000 | AB11: =IF(Table5[[#This Row],[Payment date]]<>"",Table5[[#This Row],[Draw Fee]]+Table5[[#This Row],[Interest]]+Table5[[#This Row],[Principal Payment]]+Table5[[#This Row],[Overdue Interest]],"") -> 12126.5
B12: Max Number of payments | E12: 6 | G12: =IFERROR(RANK(Table4[[#This Row],[Loan Date]],Table4[[#All],[Loan Date]],1) +COUNTIF($I$6:I12,I12)-1,"") | J12: =IF(Table4[[#This Row],[Loan Date]]<>"",IF($E$14 = "End of Month", EOMONTH(Table4[[#This Row],[Loan Date]],IF(DAY(EOMONTH(Table4[[#This Row],[Loan Date]],0)) - DAY(Table4[[#This Row],[Loan Date]])<=$E$15,1,0)),IF($E$14 = "Mid of Month", EOMONTH(Table4[[#This Row],[Loan Date]],IF(15 - DAY(Table4[[#This Row],[Loan Date]])<=$E$15,0,-1))+15,IF($E$14 = "Start of Month", EOMONTH(Table4[[#This Row],[Loan Date]],IF(DAY(EOMONTH(Table4[[#This Row],[Loan Date]],0)) - DAY(Table4[[#This Row],[Loan Date]])<=$E$15,1,0))) + 1)),"") | K12: =IF(Table4[[#This Row],[Loan Date]]<>"", IF($E$14 = "End of Month", EOMONTH(Table4[[#This Row],[Loan Date]],6+IF(DAY(EOMONTH(Table4[[#This Row],[Loan Date]],0)) - DAY(Table4[[#This Row],[Loan Date]])<=$E$15,0,-1)), IF($E$14 = "Mid of Month", EOMONTH(Table4[[#This Row],[Loan Date]],6+IF(15 - DAY(Table4[[#This Row],[Loan Date]])<=$E$15,-1,-2))+15, IF($E$14 = "Start of Month", EOMONTH(Table4[[#This Row],[Loan Date]],6+IF(DAY(EOMONTH(Table4[[#This Row],[Loan Date]],0)) - DAY(Table4[[#This Row],[Loan Date]])<=$E$15,0,-1)) + 1) ) ),"") | L12: =IF(Table4[[#This Row],[Loan Date]]<>"",Table4[[#This Row],[Loan Amount]]/PaymentsPerYear,"") | M12: {=IF(Table4[[#This Row],[Loan Date]]<>"", ((Table4[[#This Row],[Loan Payment Start Date]]-Table4[[#This Row],[Loan Date]])*Table4[[#This Row],[Loan Amount]]*InterestRate/360) + SUM((_xlfn.SEQUENCE(6, 1, Table4[[#This Row],[Loan Amount]]-Table4[[#This Row],[Loan Amount]]/6, -Table4[[#This Row],[Loan Amount]]/6))* (IF($E$14 = "End of Month", EOMONTH(EDATE(Table4[[#This Row],[Loan Payment Start Date]],_xlfn.SEQUENCE(6,1,1,1)),0),IF($E$14 = "Mid of Month",EDATE(Table4[[#This Row],[Loan Payment Start Date]],_xlfn.SEQUENCE(6,1,1,1)), IF($E$14 = "Start of Month", EOMONTH(EDATE(Table4[[#This Row],[Loan Payment Start Date]],_xlfn.SEQUENCE(6,1,1,1)),-1)+1))) - IF($E$14 = "End of Month", EOMONTH(EDATE(Table4[[#This Row],[Loan Payment Start Date]],_xlfn.SEQUENCE(6,1,1,1)),-1),IF($E$14 = "Mid of Month",EDATE(Table4[[#This Row],[Loan Payment Start Date]],_xlfn.SEQUENCE(6,1,0,1)), IF($E$14 = "Start of Month", EOMONTH(EDATE(Table4[[#This Row],[Loan Payment Start Date]],_xlfn.SEQUENCE(6,1,1,1)),-2)+1))))*InterestRate/360),"")} | N12: =IF(Table4[[#This Row],[Loan Amount]]<>"", IF((LoanAmount - (SUMIFS(Table4[Loan Amount],Table4[Loan Date],"<"&Table4[[#This Row],[Loan Date]]) -SUMIFS(Table5[Principal Payment],Table5[Payment date],"<="&Table4[[#This Row],[Loan Date]]) - SUMIFS(Table5[Extra Payment],Table5[Payment date],"<="&Table4[[#This Row],[Loan Date]])) > Table4[[#This Row],[Loan Amount]]),"Yes","No"),"") | O12: =IF(Table4[[#This Row],[Loan Amount]]<>"", LoanAmount - (SUMIFS(Table4[Loan Amount],Table4[Loan Date],"<"&Table4[[#This Row],[Loan Date]]) -SUMIFS(Table5[Principal Payment],Table5[Payment date],"<="&Table4[[#This Row],[Loan Date]]) - SUMIFS(Table5[Extra Payment],Table5[Payment date],"<="&Table4[[#This Row],[Loan Date]])) - Table4[[#This Row],[Loan Amount]],"") | Q12: =IF($E$14="Mid of Month",(IF(EDATE(MIN(Table4[[#All],[Loan Date]]), ROW()-ROW($Q$6)) > EDATE(MAX(Table4[[#All],[Loan Payment End Date]]),1), "", (EOMONTH(EDATE(MIN(Table4[[#All],[Loan Date]]), ROW()-ROW($Q$6)),IF(DAY(EOMONTH(MIN(Table4[[#All],[Loan Date]]),0)) - DAY(MIN(Table4[[#All],[Loan Date]])) <= $E$15, 0, -1))+ 15))), IF($E$14="End of Month",(IF(EDATE(MIN(Table4[[#All],[Loan Date]]), ROW()-ROW($Q$6)) > MAX(Table4[[#All],[Loan Payment End Date]]), "", (EOMONTH(EDATE(MIN(Table4[[#All],[Loan Date]]), ROW()-ROW($Q$6)),IF(31 - DAY(MIN(Table4[[#All],[Loan Date]])) <= $E$15, 1, 0))))), IF($E$14="Start of Month",(IF(EDATE(MIN(Table4[[#All],[Loan Date]]), ROW()-ROW($Q$6)) > MAX(Table4[[#All],[Loan Payment End Date]]), "", (EOMONTH(EDATE(MIN(Table4[[#All],[Loan Date]]), ROW()-ROW($Q$6)),IF(31 - DAY(MIN(Table4[[#All],[Loan Date]])) <= $E$15, 1, 0))) + 1 ))) ) ) -> 45536 | R12: =IF(Table5[[#This Row],[Payment date]]<>"", SUMIFS(Table4[[#All],[Loan Amount]],Table4[[#All],[Loan Date]],"<="&Table5[[#This Row],[Payment date]]) - SUM($S$5:S11)- SUM($W$5:W11),"") -> 18000 | S12: =IF(Table5[[#This Row],[Payment date]]<>"",SUM('Individual Loan Schedule'!C15:HR15) - SUM('Early Payments'!D15:HS15),"") -> 9666.6667 | T12: {=IF(Table5[[#This Row],[Payment date]]<>"",((SUMIFS(Table4[Loan Amount],Table4[Loan Payment Start Date],"<"&Table5[[#This Row],[Payment date]]) - SUM($S$5:$S11) - SUM($W$5:W11))*InterestRate*(Table5[[#This Row],[Payment date]] - IF($E$14="End of Month",EOMONTH(Table5[[#This Row],[Payment date]],-1), IF($E$14="Mid of Month",EOMONTH(Table5[[#This Row],[Payment date]],-2)+15, IF($E$14="Start of Month",EOMONTH(Table5[[#This Row],[Payment date]],-2) + 1))) )/360) + (SUM(IFERROR((IF(Table4[Loan Payment Start Date]=Table5[[#This Row],[Payment date]],Table4[Loan Amount],"")*(Table4[Loan Payment Start Date]-Table4[Loan Date])*InterestRate/360),0),0)),"")} -> 279 | U12: =IF(Table5[[#This Row],[Payment date]]<>"",SUMIFS(Table4[[#All],[Loan Amount]],Table4[[#All],[Loan Payment Start Date]],"="&Table5[[#This Row],[Payment date]])*($E$7),"") -> 0 | V12: {=IF(Table5[[#This Row],[Payment date]]<>"",IF(Table5[[#This Row],[Payment date]]=MIN(Table4[[#All],[Loan Payment Start Date]]),$E$8+$E$10*LoanAmount,0) + IF(Table5[[#This Row],[Payment date]] =MIN(_xlfn._xlws.FILTER(Table5[Payment date],(Table5[Payment date]>=EDATE(LoanStartDate,12*DATEDIF(LoanStartDate,Table5[[#This Row],[Payment date]],"y")))*(Table5[Beginning balance]<>0))), $E$9*LoanAmount,0),"")} -> 0 | Y12: =IF(Table5[[#This Row],[Payment date]]<>"",(SUMIFS(Table4[Loan Amount],Table4[Loan Payment Start Date],"<="&Table5[[#This Row],[Payment date]]) - SUM($S$5:$S11) - - SUM($W$5:W11))*Table5[[#This Row],[Delay in Payment ]]*($E$16+ InterestRate)/365,"") -> 0 | Z12: =IF(Table5[[#This Row],[Payment date]]<>"",Table5[[#This Row],[Payment date]]+Table5[[#This Row],[Delay in Payment ]],"") -> 45536 | AA12: =IF(Table5[[#This Row],[Payment date]]<>"",Table5[[#This Row],[Beginning balance]]-Table5[[#This Row],[Principal Payment]] - Table5[[#This Row],[Extra Payment]],"") -> 8333.3333 | AB12: =IF(Table5[[#This Row],[Payment date]]<>"",Table5[[#This Row],[Draw Fee]]+Table5[[#This Row],[Interest]]+Table5[[#This Row],[Principal Payment]]+Table5[[#This Row],[Overdue Interest]],"") -> 9945.6667
B13: Onboarding Date | E13: 45292 | G13: =IFERROR(RANK(Table4[[#This Row],[Loan Date]],Table4[[#All],[Loan Date]],1) +COUNTIF($I$6:I13,I13)-1,"") | J13: =IF(Table4[[#This Row],[Loan Date]]<>"",IF($E$14 = "End of Month", EOMONTH(Table4[[#This Row],[Loan Date]],IF(DAY(EOMONTH(Table4[[#This Row],[Loan Date]],0)) - DAY(Table4[[#This Row],[Loan Date]])<=$E$15,1,0)),IF($E$14 = "Mid of Month", EOMONTH(Table4[[#This Row],[Loan Date]],IF(15 - DAY(Table4[[#This Row],[Loan Date]])<=$E$15,0,-1))+15,IF($E$14 = "Start of Month", EOMONTH(Table4[[#This Row],[Loan Date]],IF(DAY(EOMONTH(Table4[[#This Row],[Loan Date]],0)) - DAY(Table4[[#This Row],[Loan Date]])<=$E$15,1,0))) + 1)),"") | K13: =IF(Table4[[#This Row],[Loan Date]]<>"", IF($E$14 = "End of Month", EOMONTH(Table4[[#This Row],[Loan Date]],6+IF(DAY(EOMONTH(Table4[[#This Row],[Loan Date]],0)) - DAY(Table4[[#This Row],[Loan Date]])<=$E$15,0,-1)), IF($E$14 = "Mid of Month", EOMONTH(Table4[[#This Row],[Loan Date]],6+IF(15 - DAY(Table4[[#This Row],[Loan Date]])<=$E$15,-1,-2))+15, IF($E$14 = "Start of Month", EOMONTH(Table4[[#This Row],[Loan Date]],6+IF(DAY(EOMONTH(Table4[[#This Row],[Loan Date]],0)) - DAY(Table4[[#This Row],[Loan Date]])<=$E$15,0,-1)) + 1) ) ),"") | L13: =IF(Table4[[#This Row],[Loan Date]]<>"",Table4[[#This Row],[Loan Amount]]/PaymentsPerYear,"") | M13: {=IF(Table4[[#This Row],[Loan Date]]<>"", ((Table4[[#This Row],[Loan Payment Start Date]]-Table4[[#This Row],[Loan Date]])*Table4[[#This Row],[Loan Amount]]*InterestRate/360) + SUM((_xlfn.SEQUENCE(6, 1, Table4[[#This Row],[Loan Amount]]-Table4[[#This Row],[Loan Amount]]/6, -Table4[[#This Row],[Loan Amount]]/6))* (IF($E$14 = "End of Month", EOMONTH(EDATE(Table4[[#This Row],[Loan Payment Start Date]],_xlfn.SEQUENCE(6,1,1,1)),0),IF($E$14 = "Mid of Month",EDATE(Table4[[#This Row],[Loan Payment Start Date]],_xlfn.SEQUENCE(6,1,1,1)), IF($E$14 = "Start of Month", EOMONTH(EDATE(Table4[[#This Row],[Loan Payment Start Date]],_xlfn.SEQUENCE(6,1,1,1)),-1)+1))) - IF($E$14 = "End of Month", EOMONTH(EDATE(Table4[[#This Row],[Loan Payment Start Date]],_xlfn.SEQUENCE(6,1,1,1)),-1),IF($E$14 = "Mid of Month",EDATE(Table4[[#This Row],[Loan Payment Start Date]],_xlfn.SEQUENCE(6,1,0,1)), IF($E$14 = "Start of Month", EOMONTH(EDATE(Table4[[#This Row],[Loan Payment Start Date]],_xlfn.SEQUENCE(6,1,1,1)),-2)+1))))*InterestRate/360),"")} | N13: =IF(Table4[[#This Row],[Loan Amount]]<>"", IF((LoanAmount - (SUMIFS(Table4[Loan Amount],Table4[Loan Date],"<"&Table4[[#This Row],[Loan Date]]) -SUMIFS(Table5[Principal Payment],Table5[Payment date],"<="&Table4[[#This Row],[Loan Date]]) - SUMIFS(Table5[Extra Payment],Table5[Payment date],"<="&Table4[[#This Row],[Loan Date]])) > Table4[[#This Row],[Loan Amount]]),"Yes","No"),"") | O13: =IF(Table4[[#This Row],[Loan Amount]]<>"", LoanAmount - (SUMIFS(Table4[Loan Amount],Table4[Loan Date],"<"&Table4[[#This Row],[Loan Date]]) -SUMIFS(Table5[Principal Payment],Table5[Payment date],"<="&Table4[[#This Row],[Loan Date]]) - SUMIFS(Table5[Extra Payment],Table5[Payment date],"<="&Table4[[#This Row],[Loan Date]])) - Table4[[#This Row],[Loan Amount]],"") | Q13: =IF($E$14="Mid of Month",(IF(EDATE(MIN(Table4[[#All],[Loan Date]]), ROW()-ROW($Q$6)) > EDATE(MAX(Table4[[#All],[Loan Payment End Date]]),1), "", (EOMONTH(EDATE(MIN(Table4[[#All],[Loan Date]]), ROW()-ROW($Q$6)),IF(DAY(EOMONTH(MIN(Table4[[#All],[Loan Date]]),0)) - DAY(MIN(Table4[[#All],[Loan Date]])) <= $E$15, 0, -1))+ 15))), IF($E$14="End of Month",(IF(EDATE(MIN(Table4[[#All],[Loan Date]]), ROW()-ROW($Q$6)) > MAX(Table4[[#All],[Loan Payment End Date]]), "", (EOMONTH(EDATE(MIN(Table4[[#All],[Loan Date]]), ROW()-ROW($Q$6)),IF(31 - DAY(MIN(Table4[[#All],[Loan Date]])) <= $E$15, 1, 0))))), IF($E$14="Start of Month",(IF(EDATE(MIN(Table4[[#All],[Loan Date]]), ROW()-ROW($Q$6)) > MAX(Table4[[#All],[Loan Payment End Date]]), "", (EOMONTH(EDATE(MIN(Table4[[#All],[Loan Date]]), ROW()-ROW($Q$6)),IF(31 - DAY(MIN(Table4[[#All],[Loan Date]])) <= $E$15, 1, 0))) + 1 ))) ) ) -> 45566 | R13: =IF(Table5[[#This Row],[Payment date]]<>"", SUMIFS(Table4[[#All],[Loan Amount]],Table4[[#All],[Loan Date]],"<="&Table5[[#This Row],[Payment date]]) - SUM($S$5:S12)- SUM($W$5:W12),"") -> 8333.3333 | S13: =IF(Table5[[#This Row],[Payment date]]<>"",SUM('Individual Loan Schedule'!C16:HR16) - SUM('Early Payments'!D16:HS16),"") -> 8333.3333 | T13: {=IF(Table5[[#This Row],[Payment date]]<>"",((SUMIFS(Table4[Loan Amount],Table4[Loan Payment Start Date],"<"&Table5[[#This Row],[Payment date]]) - SUM($S$5:$S12) - SUM($W$5:W12))*InterestRate*(Table5[[#This Row],[Payment date]] - IF($E$14="End of Month",EOMONTH(Table5[[#This Row],[Payment date]],-1), IF($E$14="Mid of Month",EOMONTH(Table5[[#This Row],[Payment date]],-2)+15, IF($E$14="Start of Month",EOMONTH(Table5[[#This Row],[Payment date]],-2) + 1))) )/360) + (SUM(IFERROR((IF(Table4[Loan Payment Start Date]=Table5[[#This Row],[Payment date]],Table4[Loan Amount],"")*(Table4[Loan Payment Start Date]-Table4[Loan Date])*InterestRate/360),0),0)),"")} -> 125 | U13: =IF(Table5[[#This Row],[Payment date]]<>"",SUMIFS(Table4[[#All],[Loan Amount]],Table4[[#All],[Loan Payment Start Date]],"="&Table5[[#This Row],[Payment date]])*($E$7),"") -> 0 | V13: {=IF(Table5[[#This Row],[Payment date]]<>"",IF(Table5[[#This Row],[Payment date]]=MIN(Table4[[#All],[Loan Payment Start Date]]),$E$8+$E$10*LoanAmount,0) + IF(Table5[[#This Row],[Payment date]] =MIN(_xlfn._xlws.FILTER(Table5[Payment date],(Table5[Payment date]>=EDATE(LoanStartDate,12*DATEDIF(LoanStartDate,Table5[[#This Row],[Payment date]],"y")))*(Table5[Beginning balance]<>0))), $E$9*LoanAmount,0),"")} -> 0 | Y13: =IF(Table5[[#This Row],[Payment date]]<>"",(SUMIFS(Table4[Loan Amount],Table4[Loan Payment Start Date],"<="&Table5[[#This Row],[Payment date]]) - SUM($S$5:$S12) - - SUM($W$5:W12))*Table5[[#This Row],[Delay in Payment ]]*($E$16+ InterestRate)/365,"") -> 0 | Z13: =IF(Table5[[#This Row],[Payment date]]<>"",Table5[[#This Row],[Payment date]]+Table5[[#This Row],[Delay in Payment ]],"") -> 45566 | AA13: =IF(Table5[[#This Row],[Payment date]]<>"",Table5[[#This Row],[Beginning balance]]-Table5[[#This Row],[Principal Payment]] - Table5[[#This Row],[Extra Payment]],"") -> 1.0913936e-11 | AB13: =IF(Table5[[#This Row],[Payment date]]<>"",Table5[[#This Row],[Draw Fee]]+Table5[[#This Row],[Interest]]+Table5[[#This Row],[Principal Payment]]+Table5[[#This Row],[Overdue Interest]],"") -> 8458.3333
B14: Preferred Payment Time (Mid of Month/ End of Month) | E14: Start of Month | G14: =IFERROR(RANK(Table4[[#This Row],[Loan Date]],Table4[[#All],[Loan Date]],1) +COUNTIF($I$6:I14,I14)-1,"") | J14: =IF(Table4[[#This Row],[Loan Date]]<>"",IF($E$14 = "End of Month", EOMONTH(Table4[[#This Row],[Loan Date]],IF(DAY(EOMONTH(Table4[[#This Row],[Loan Date]],0)) - DAY(Table4[[#This Row],[Loan Date]])<=$E$15,1,0)),IF($E$14 = "Mid of Month", EOMONTH(Table4[[#This Row],[Loan Date]],IF(15 - DAY(Table4[[#This Row],[Loan Date]])<=$E$15,0,-1))+15,IF($E$14 = "Start of Month", EOMONTH(Table4[[#This Row],[Loan Date]],IF(DAY(EOMONTH(Table4[[#This Row],[Loan Date]],0)) - DAY(Table4[[#This Row],[Loan Date]])<=$E$15,1,0))) + 1)),"") | K14: =IF(Table4[[#This Row],[Loan Date]]<>"", IF($E$14 = "End of Month", EOMONTH(Table4[[#This Row],[Loan Date]],6+IF(DAY(EOMONTH(Table4[[#This Row],[Loan Date]],0)) - DAY(Table4[[#This Row],[Loan Date]])<=$E$15,0,-1)), IF($E$14 = "Mid of Month", EOMONTH(Table4[[#This Row],[Loan Date]],6+IF(15 - DAY(Table4[[#This Row],[Loan Date]])<=$E$15,-1,-2))+15, IF($E$14 = "Start of Month", EOMONTH(Table4[[#This Row],[Loan Date]],6+IF(DAY(EOMONTH(Table4[[#This Row],[Loan Date]],0)) - DAY(Table4[[#This Row],[Loan Date]])<=$E$15,0,-1)) + 1) ) ),"") | L14: =IF(Table4[[#This Row],[Loan Date]]<>"",Table4[[#This Row],[Loan Amount]]/PaymentsPerYear,"") | M14: {=IF(Table4[[#This Row],[Loan Date]]<>"", ((Table4[[#This Row],[Loan Payment Start Date]]-Table4[[#This Row],[Loan Date]])*Table4[[#This Row],[Loan Amount]]*InterestRate/360) + SUM((_xlfn.SEQUENCE(6, 1, Table4[[#This Row],[Loan Amount]]-Table4[[#This Row],[Loan Amount]]/6, -Table4[[#This Row],[Loan Amount]]/6))* (IF($E$14 = "End of Month", EOMONTH(EDATE(Table4[[#This Row],[Loan Payment Start Date]],_xlfn.SEQUENCE(6,1,1,1)),0),IF($E$14 = "Mid of Month",EDATE(Table4[[#This Row],[Loan Payment Start Date]],_xlfn.SEQUENCE(6,1,1,1)), IF($E$14 = "Start of Month", EOMONTH(EDATE(Table4[[#This Row],[Loan Payment Start Date]],_xlfn.SEQUENCE(6,1,1,1)),-1)+1))) - IF($E$14 = "End of Month", EOMONTH(EDATE(Table4[[#This Row],[Loan Payment Start Date]],_xlfn.SEQUENCE(6,1,1,1)),-1),IF($E$14 = "Mid of Month",EDATE(Table4[[#This Row],[Loan Payment Start Date]],_xlfn.SEQUENCE(6,1,0,1)), IF($E$14 = "Start of Month", EOMONTH(EDATE(Table4[[#This Row],[Loan Payment Start Date]],_xlfn.SEQUENCE(6,1,1,1)),-2)+1))))*InterestRate/360),"")} | N14: =IF(Table4[[#This Row],[Loan Amount]]<>"", IF((LoanAmount - (SUMIFS(Table4[Loan Amount],Table4[Loan Date],"<"&Table4[[#This Row],[Loan Date]]) -SUMIFS(Table5[Principal Payment],Table5[Payment date],"<="&Table4[[#This Row],[Loan Date]]) - SUMIFS(Table5[Extra Payment],Table5[Payment date],"<="&Table4[[#This Row],[Loan Date]])) > Table4[[#This Row],[Loan Amount]]),"Yes","No"),"") | O14: =IF(Table4[[#This Row],[Loan Amount]]<>"", LoanAmount - (SUMIFS(Table4[Loan Amount],Table4[Loan Date],"<"&Table4[[#This Row],[Loan Date]]) -SUMIFS(Table5[Principal Payment],Table5[Payment date],"<="&Table4[[#This Row],[Loan Date]]) - SUMIFS(Table5[Extra Payment],Table5[Payment date],"<="&Table4[[#This Row],[Loan Date]])) - Table4[[#This Row],[Loan Amount]],"") | Q14: =IF($E$14="Mid of Month",(IF(EDATE(MIN(Table4[[#All],[Loan Date]]), ROW()-ROW($Q$6)) > EDATE(MAX(Table4[[#All],[Loan Payment End Date]]),1), "", (EOMONTH(EDATE(MIN(Table4[[#All],[Loan Date]]), ROW()-ROW($Q$6)),IF(DAY(EOMONTH(MIN(Table4[[#All],[Loan Date]]),0)) - DAY(MIN(Table4[[#All],[Loan Date]])) <= $E$15, 0, -1))+ 15))), IF($E$14="End of Month",(IF(EDATE(MIN(Table4[[#All],[Loan Date]]), ROW()-ROW($Q$6)) > MAX(Table4[[#All],[Loan Payment End Date]]), "", (EOMONTH(EDATE(MIN(Table4[[#All],[Loan Date]]), ROW()-ROW($Q$6)),IF(31 - DAY(MIN(Table4[[#All],[Loan Date]])) <= $E$15, 1, 0))))), IF($E$14="Start of Month",(IF(EDATE(MIN(Table4[[#All],[Loan Date]]), ROW()-ROW($Q$6)) > MAX(Table4[[#All],[Loan Payment End Date]]), "", (EOMONTH(EDATE(MIN(Table4[[#All],[Loan Date]]), ROW()-ROW($Q$6)),IF(31 - DAY(MIN(Table4[[#All],[Loan Date]])) <= $E$15, 1, 0))) + 1 ))) ) ) -> 45597 | R14: =IF(Table5[[#This Row],[Payment date]]<>"", SUMIFS(Table4[[#All],[Loan Amount]],Table4[[#All],[Loan Date]],"<="&Table5[[#This Row],[Payment date]]) - SUM($S$5:S13)- SUM($W$5:W13),"") -> 1.4551915e-11 | S14: =IF(Table5[[#This Row],[Payment date]]<>"",SUM('Individual Loan Schedule'!C17:HR17) - SUM('Early Payments'!D17:HS17),"") -> 0 | T14: {=IF(Table5[[#This Row],[Payment date]]<>"",((SUMIFS(Table4[Loan Amount],Table4[Loan Payment Start Date],"<"&Table5[[#This Row],[Payment date]]) - SUM($S$5:$S13) - SUM($W$5:W13))*InterestRate*(Table5[[#This Row],[Payment date]] - IF($E$14="End of Month",EOMONTH(Table5[[#This Row],[Payment date]],-1), IF($E$14="Mid of Month",EOMONTH(Table5[[#This Row],[Payment date]],-2)+15, IF($E$14="Start of Month",EOMONTH(Table5[[#This Row],[Payment date]],-2) + 1))) )/360) + (SUM(IFERROR((IF(Table4[Loan Payment Start Date]=Table5[[#This Row],[Payment date]],Table4[Loan Amount],"")*(Table4[Loan Payment Start Date]-Table4[Loan Date])*InterestRate/360),0),0)),"")} -> 2.2555469e-13 | U14: =IF(Table5[[#This Row],[Payment date]]<>"",SUMIFS(Table4[[#All],[Loan Amount]],Table4[[#All],[Loan Payment Start Date]],"="&Table5[[#This Row],[Payment date]])*($E$7),"") -> 0 | V14: {=IF(Table5[[#This Row],[Payment date]]<>"",IF(Table5[[#This Row],[Payment date]]=MIN(Table4[[#All],[Loan Payment Start Date]]),$E$8+$E$10*LoanAmount,0) + IF(Table5[[#This Row],[Payment date]] =MIN(_xlfn._xlws.FILTER(Table5[Payment date],(Table5[Payment date]>=EDATE(LoanStartDate,12*DATEDIF(LoanStartDate,Table5[[#This Row],[Payment date]],"y")))*(Table5[Beginning balance]<>0))), $E$9*LoanAmount,0),"")} -> 0 | Y14: =IF(Table5[[#This Row],[Payment date]]<>"",(SUMIFS(Table4[Loan Amount],Table4[Loan Payment Start Date],"<="&Table5[[#This Row],[Payment date]]) - SUM($S$5:$S13) - - SUM($W$5:W13))*Table5[[#This Row],[Delay in Payment ]]*($E$16+ InterestRate)/365,"") -> 0 | Z14: =IF(Table5[[#This Row],[Payment date]]<>"",Table5[[#This Row],[Payment date]]+Table5[[#This Row],[Delay in Payment ]],"") -> 45597 | AA14: =IF(Table5[[#This Row],[Payment date]]<>"",Table5[[#This Row],[Beginning balance]]-Table5[[#This Row],[Principal Payment]] - Table5[[#This Row],[Extra Payment]],"") -> 1.4551915e-11 | AB14: =IF(Table5[[#This Row],[Payment date]]<>"",Table5[[#This Row],[Draw Fee]]+Table5[[#This Row],[Interest]]+Table5[[#This Row],[Principal Payment]]+Table5[[#This Row],[Overdue Interest]],"") -> 2.2555469e-13
B15: Spillover Period | E15: 7 | G15: =IFERROR(RANK(Table4[[#This Row],[Loan Date]],Table4[[#All],[Loan Date]],1) +COUNTIF($I$6:I15,I15)-1,"") | J15: =IF(Table4[[#This Row],[Loan Date]]<>"",IF($E$14 = "End of Month", EOMONTH(Table4[[#This Row],[Loan Date]],IF(DAY(EOMONTH(Table4[[#This Row],[Loan Date]],0)) - DAY(Table4[[#This Row],[Loan Date]])<=$E$15,1,0)),IF($E$14 = "Mid of Month", EOMONTH(Table4[[#This Row],[Loan Date]],IF(15 - DAY(Table4[[#This Row],[Loan Date]])<=$E$15,0,-1))+15,IF($E$14 = "Start of Month", EOMONTH(Table4[[#This Row],[Loan Date]],IF(DAY(EOMONTH(Table4[[#This Row],[Loan Date]],0)) - DAY(Table4[[#This Row],[Loan Date]])<=$E$15,1,0))) + 1)),"") | K15: =IF(Table4[[#This Row],[Loan Date]]<>"", IF($E$14 = "End of Month", EOMONTH(Table4[[#This Row],[Loan Date]],6+IF(DAY(EOMONTH(Table4[[#This Row],[Loan Date]],0)) - DAY(Table4[[#This Row],[Loan Date]])<=$E$15,0,-1)), IF($E$14 = "Mid of Month", EOMONTH(Table4[[#This Row],[Loan Date]],6+IF(15 - DAY(Table4[[#This Row],[Loan Date]])<=$E$15,-1,-2))+15, IF($E$14 = "Start of Month", EOMONTH(Table4[[#This Row],[Loan Date]],6+IF(DAY(EOMONTH(Table4[[#This Row],[Loan Date]],0)) - DAY(Table4[[#This Row],[Loan Date]])<=$E$15,0,-1)) + 1) ) ),"") | L15: =IF(Table4[[#This Row],[Loan Date]]<>"",Table4[[#This Row],[Loan Amount]]/PaymentsPerYear,"") | M15: {=IF(Table4[[#This Row],[Loan Date]]<>"", ((Table4[[#This Row],[Loan Payment Start Date]]-Table4[[#This Row],[Loan Date]])*Table4[[#This Row],[Loan Amount]]*InterestRate/360) + SUM((_xlfn.SEQUENCE(6, 1, Table4[[#This Row],[Loan Amount]]-Table4[[#This Row],[Loan Amount]]/6, -Table4[[#This Row],[Loan Amount]]/6))* (IF($E$14 = "End of Month", EOMONTH(EDATE(Table4[[#This Row],[Loan Payment Start Date]],_xlfn.SEQUENCE(6,1,1,1)),0),IF($E$14 = "Mid of Month",EDATE(Table4[[#This Row],[Loan Payment Start Date]],_xlfn.SEQUENCE(6,1,1,1)), IF($E$14 = "Start of Month", EOMONTH(EDATE(Table4[[#This Row],[Loan Payment Start Date]],_xlfn.SEQUENCE(6,1,1,1)),-1)+1))) - IF($E$14 = "End of Month", EOMONTH(EDATE(Table4[[#This Row],[Loan Payment Start Date]],_xlfn.SEQUENCE(6,1,1,1)),-1),IF($E$14 = "Mid of Month",EDATE(Table4[[#This Row],[Loan Payment Start Date]],_xlfn.SEQUENCE(6,1,0,1)), IF($E$14 = "Start of Month", EOMONTH(EDATE(Table4[[#This Row],[Loan Payment Start Date]],_xlfn.SEQUENCE(6,1,1,1)),-2)+1))))*InterestRate/360),"")} | N15: =IF(Table4[[#This Row],[Loan Amount]]<>"", IF((LoanAmount - (SUMIFS(Table4[Loan Amount],Table4[Loan Date],"<"&Table4[[#This Row],[Loan Date]]) -SUMIFS(Table5[Principal Payment],Table5[Payment date],"<="&Table4[[#This Row],[Loan Date]]) - SUMIFS(Table5[Extra Payment],Table5[Payment date],"<="&Table4[[#This Row],[Loan Date]])) > Table4[[#This Row],[Loan Amount]]),"Yes","No"),"") | O15: =IF(Table4[[#This Row],[Loan Amount]]<>"", LoanAmount - (SUMIFS(Table4[Loan Amount],Table4[Loan Date],"<"&Table4[[#This Row],[Loan Date]]) -SUMIFS(Table5[Principal Payment],Table5[Payment date],"<="&Table4[[#This Row],[Loan Date]]) - SUMIFS(Table5[Extra Payment],Table5[Payment date],"<="&Table4[[#This Row],[Loan Date]])) - Table4[[#This Row],[Loan Amount]],"") | Q15: =IF($E$14="Mid of Month",(IF(EDATE(MIN(Table4[[#All],[Loan Date]]), ROW()-ROW($Q$6)) > EDATE(MAX(Table4[[#All],[Loan Payment End Date]]),1), "", (EOMONTH(EDATE(MIN(Table4[[#All],[Loan Date]]), ROW()-ROW($Q$6)),IF(DAY(EOMONTH(MIN(Table4[[#All],[Loan Date]]),0)) - DAY(MIN(Table4[[#All],[Loan Date]])) <= $E$15, 0, -1))+ 15))), IF($E$14="End of Month",(IF(EDATE(MIN(Table4[[#All],[Loan Date]]), ROW()-ROW($Q$6)) > MAX(Table4[[#All],[Loan Payment End Date]]), "", (EOMONTH(EDATE(MIN(Table4[[#All],[Loan Date]]), ROW()-ROW($Q$6)),IF(31 - DAY(MIN(Table4[[#All],[Loan Date]])) <= $E$15, 1, 0))))), IF($E$14="Start of Month",(IF(EDATE(MIN(Table4[[#All],[Loan Date]]), ROW()-ROW($Q$6)) > MAX(Table4[[#All],[Loan Payment End Date]]), "", (EOMONTH(EDATE(MIN(Table4[[#All],[Loan Date]]), ROW()-ROW($Q$6)),IF(31 - DAY(MIN(Table4[[#All],[Loan Date]])) <= $E$15, 1, 0))) + 1 ))) ) ) -> 45627 | R15: =IF(Table5[[#This Row],[Payment date]]<>"", SUMIFS(Table4[[#All],[Loan Amount]],Table4[[#All],[Loan Date]],"<="&Table5[[#This Row],[Payment date]]) - SUM($S$5:S14)- SUM($W$5:W14),"") -> 15000 | S15: =IF(Table5[[#This Row],[Payment date]]<>"",SUM('Individual Loan Schedule'!C18:HR18) - SUM('Early Payments'!D18:HS18),"") -> 2500 | T15: {=IF(Table5[[#This Row],[Payment date]]<>"",((SUMIFS(Table4[Loan Amount],Table4[Loan Payment Start Date],"<"&Table5[[#This Row],[Payment date]]) - SUM($S$5:$S14) - SUM($W$5:W14))*InterestRate*(Table5[[#This Row],[Payment date]] - IF($E$14="End of Month",EOMONTH(Table5[[#This Row],[Payment date]],-1), IF($E$14="Mid of Month",EOMONTH(Table5[[#This Row],[Payment date]],-2)+15, IF($E$14="Start of Month",EOMONTH(Table5[[#This Row],[Payment date]],-2) + 1))) )/360) + (SUM(IFERROR((IF(Table4[Loan Payment Start Date]=Table5[[#This Row],[Payment date]],Table4[Loan Amount],"")*(Table4[Loan Payment Start Date]-Table4[Loan Date])*InterestRate/360),0),0)),"")} -> 105 | U15: =IF(Table5[[#This Row],[Payment date]]<>"",SUMIFS(Table4[[#All],[Loan Amount]],Table4[[#All],[Loan Payment Start Date]],"="&Table5[[#This Row],[Payment date]])*($E$7),"") -> 45 | V15: {=IF(Table5[[#This Row],[Payment date]]<>"",IF(Table5[[#This Row],[Payment date]]=MIN(Table4[[#All],[Loan Payment Start Date]]),$E$8+$E$10*LoanAmount,0) + IF(Table5[[#This Row],[Payment date]] =MIN(_xlfn._xlws.FILTER(Table5[Payment date],(Table5[Payment date]>=EDATE(LoanStartDate,12*DATEDIF(LoanStartDate,Table5[[#This Row],[Payment date]],"y")))*(Table5[Beginning balance]<>0))), $E$9*LoanAmount,0),"")} -> 0 | Y15: =IF(Table5[[#This Row],[Payment date]]<>"",(SUMIFS(Table4[Loan Amount],Table4[Loan Payment Start Date],"<="&Table5[[#This Row],[Payment date]]) - SUM($S$5:$S14) - - SUM($W$5:W14))*Table5[[#This Row],[Delay in Payment ]]*($E$16+ InterestRate)/365,"") -> 0 | Z15: =IF(Table5[[#This Row],[Payment date]]<>"",Table5[[#This Row],[Payment date]]+Table5[[#This Row],[Delay in Payment ]],"") -> 45627 | AA15: =IF(Table5[[#This Row],[Payment date]]<>"",Table5[[#This Row],[Beginning balance]]-Table5[[#This Row],[Principal Payment]] - Table5[[#This Row],[Extra Payment]],"") -> 12500 | AB15: =IF(Table5[[#This Row],[Payment date]]<>"",Table5[[#This Row],[Draw Fee]]+Table5[[#This Row],[Interest]]+Table5[[#This Row],[Principal Payment]]+Table5[[#This Row],[Overdue Interest]],"") -> 2650
B16: Overdue Interest Rate | E16: 0.36 | G16: =IFERROR(RANK(Table4[[#This Row],[Loan Date]],Table4[[#All],[Loan Date]],1) +COUNTIF($I$6:I16,I16)-1,"") | J16: =IF(Table4[[#This Row],[Loan Date]]<>"",IF($E$14 = "End of Month", EOMONTH(Table4[[#This Row],[Loan Date]],IF(DAY(EOMONTH(Table4[[#This Row],[Loan Date]],0)) - DAY(Table4[[#This Row],[Loan Date]])<=$E$15,1,0)),IF($E$14 = "Mid of Month", EOMONTH(Table4[[#This Row],[Loan Date]],IF(15 - DAY(Table4[[#This Row],[Loan Date]])<=$E$15,0,-1))+15,IF($E$14 = "Start of Month", EOMONTH(Table4[[#This Row],[Loan Date]],IF(DAY(EOMONTH(Table4[[#This Row],[Loan Date]],0)) - DAY(Table4[[#This Row],[Loan Date]])<=$E$15,1,0))) + 1)),"") | K16: =IF(Table4[[#This Row],[Loan Date]]<>"", IF($E$14 = "End of Month", EOMONTH(Table4[[#This Row],[Loan Date]],6+IF(DAY(EOMONTH(Table4[[#This Row],[Loan Date]],0)) - DAY(Table4[[#This Row],[Loan Date]])<=$E$15,0,-1)), IF($E$14 = "Mid of Month", EOMONTH(Table4[[#This Row],[Loan Date]],6+IF(15 - DAY(Table4[[#This Row],[Loan Date]])<=$E$15,-1,-2))+15, IF($E$14 = "Start of Month", EOMONTH(Table4[[#This Row],[Loan Date]],6+IF(DAY(EOMONTH(Table4[[#This Row],[Loan Date]],0)) - DAY(Table4[[#This Row],[Loan Date]])<=$E$15,0,-1)) + 1) ) ),"") | L16: =IF(Table4[[#This Row],[Loan Date]]<>"",Table4[[#This Row],[Loan Amount]]/PaymentsPerYear,"") | M16: {=IF(Table4[[#This Row],[Loan Date]]<>"", ((Table4[[#This Row],[Loan Payment Start Date]]-Table4[[#This Row],[Loan Date]])*Table4[[#This Row],[Loan Amount]]*InterestRate/360) + SUM((_xlfn.SEQUENCE(6, 1, Table4[[#This Row],[Loan Amount]]-Table4[[#This Row],[Loan Amount]]/6, -Table4[[#This Row],[Loan Amount]]/6))* (IF($E$14 = "End of Month", EOMONTH(EDATE(Table4[[#This Row],[Loan Payment Start Date]],_xlfn.SEQUENCE(6,1,1,1)),0),IF($E$14 = "Mid of Month",EDATE(Table4[[#This Row],[Loan Payment Start Date]],_xlfn.SEQUENCE(6,1,1,1)), IF($E$14 = "Start of Month", EOMONTH(EDATE(Table4[[#This Row],[Loan Payment Start Date]],_xlfn.SEQUENCE(6,1,1,1)),-1)+1))) - IF($E$14 = "End of Month", EOMONTH(EDATE(Table4[[#This Row],[Loan Payment Start Date]],_xlfn.SEQUENCE(6,1,1,1)),-1),IF($E$14 = "Mid of Month",EDATE(Table4[[#This Row],[Loan Payment Start Date]],_xlfn.SEQUENCE(6,1,0,1)), IF($E$14 = "Start of Month", EOMONTH(EDATE(Table4[[#This Row],[Loan Payment Start Date]],_xlfn.SEQUENCE(6,1,1,1)),-2)+1))))*InterestRate/360),"")} | N16: =IF(Table4[[#This Row],[Loan Amount]]<>"", IF((LoanAmount - (SUMIFS(Table4[Loan Amount],Table4[Loan Date],"<"&Table4[[#This Row],[Loan Date]]) -SUMIFS(Table5[Principal Payment],Table5[Payment date],"<="&Table4[[#This Row],[Loan Date]]) - SUMIFS(Table5[Extra Payment],Table5[Payment date],"<="&Table4[[#This Row],[Loan Date]])) > Table4[[#This Row],[Loan Amount]]),"Yes","No"),"") | O16: =IF(Table4[[#This Row],[Loan Amount]]<>"", LoanAmount - (SUMIFS(Table4[Loan Amount],Table4[Loan Date],"<"&Table4[[#This Row],[Loan Date]]) -SUMIFS(Table5[Principal Payment],Table5[Payment date],"<="&Table4[[#This Row],[Loan Date]]) - SUMIFS(Table5[Extra Payment],Table5[Payment date],"<="&Table4[[#This Row],[Loan Date]])) - Table4[[#This Row],[Loan Amount]],"") | Q16: =IF($E$14="Mid of Month",(IF(EDATE(MIN(Table4[[#All],[Loan Date]]), ROW()-ROW($Q$6)) > EDATE(MAX(Table4[[#All],[Loan Payment End Date]]),1), "", (EOMONTH(EDATE(MIN(Table4[[#All],[Loan Date]]), ROW()-ROW($Q$6)),IF(DAY(EOMONTH(MIN(Table4[[#All],[Loan Date]]),0)) - DAY(MIN(Table4[[#All],[Loan Date]])) <= $E$15, 0, -1))+ 15))), IF($E$14="End of Month",(IF(EDATE(MIN(Table4[[#All],[Loan Date]]), ROW()-ROW($Q$6)) > MAX(Table4[[#All],[Loan Payment End Date]]), "", (EOMONTH(EDATE(MIN(Table4[[#All],[Loan Date]]), ROW()-ROW($Q$6)),IF(31 - DAY(MIN(Table4[[#All],[Loan Date]])) <= $E$15, 1, 0))))), IF($E$14="Start of Month",(IF(EDATE(MIN(Table4[[#All],[Loan Date]]), ROW()-ROW($Q$6)) > MAX(Table4[[#All],[Loan Payment End Date]]), "", (EOMONTH(EDATE(MIN(Table4[[#All],[Loan Date]]), ROW()-ROW($Q$6)),IF(31 - DAY(MIN(Table4[[#All],[Loan Date]])) <= $E$15, 1, 0))) + 1 ))) ) ) -> 45658 | R16: =IF(Table5[[#This Row],[Payment date]]<>"", SUMIFS(Table4[[#All],[Loan Amount]],Table4[[#All],[Loan Date]],"<="&Table5[[#This Row],[Payment date]]) - SUM($S$5:S15)- SUM($W$5:W15),"") -> 12500 | S16: =IF(Table5[[#This Row],[Payment date]]<>"",SUM('Individual Loan Schedule'!C19:HR19) - SUM('Early Payments'!D19:HS19),"") -> 2500 | T16: {=IF(Table5[[#This Row],[Payment date]]<>"",((SUMIFS(Table4[Loan Amount],Table4[Loan Payment Start Date],"<"&Table5[[#This Row],[Payment date]]) - SUM($S$5:$S15) - SUM($W$5:W15))*InterestRate*(Table5[[#This Row],[Payment date]] - IF($E$14="End of Month",EOMONTH(Table5[[#This Row],[Payment date]],-1), IF($E$14="Mid of Month",EOMONTH(Table5[[#This Row],[Payment date]],-2)+15, IF($E$14="Start of Month",EOMONTH(Table5[[#This Row],[Payment date]],-2) + 1))) )/360) + (SUM(IFERROR((IF(Table4[Loan Payment Start Date]=Table5[[#This Row],[Payment date]],Table4[Loan Amount],"")*(Table4[Loan Payment Start Date]-Table4[Loan Date])*InterestRate/360),0),0)),"")} -> 193.75 | U16: =IF(Table5[[#This Row],[Payment date]]<>"",SUMIFS(Table4[[#All],[Loan Amount]],Table4[[#All],[Loan Payment Start Date]],"="&Table5[[#This Row],[Payment date]])*($E$7),"") -> 0 | V16: {=IF(Table5[[#This Row],[Payment date]]<>"",IF(Table5[[#This Row],[Payment date]]=MIN(Table4[[#All],[Loan Payment Start Date]]),$E$8+$E$10*LoanAmount,0) + IF(Table5[[#This Row],[Payment date]] =MIN(_xlfn._xlws.FILTER(Table5[Payment date],(Table5[Payment date]>=EDATE(LoanStartDate,12*DATEDIF(LoanStartDate,Table5[[#This Row],[Payment date]],"y")))*(Table5[Beginning balance]<>0))), $E$9*LoanAmount,0),"")} -> 500 | Y16: =IF(Table5[[#This Row],[Payment date]]<>"",(SUMIFS(Table4[Loan Amount],Table4[Loan Payment Start Date],"<="&Table5[[#This Row],[Payment date]]) - SUM($S$5:$S15) - - SUM($W$5:W15))*Table5[[#This Row],[Delay in Payment ]]*($E$16+ InterestRate)/365,"") -> 0 | Z16: =IF(Table5[[#This Row],[Payment date]]<>"",Table5[[#This Row],[Payment date]]+Table5[[#This Row],[Delay in Payment ]],"") -> 45658 | AA16: =IF(Table5[[#This Row],[Payment date]]<>"",Table5[[#This Row],[Beginning balance]]-Table5[[#This Row],[Principal Payment]] - Table5[[#This Row],[Extra Payment]],"") -> 10000 | AB16: =IF(Table5[[#This Row],[Payment date]]<>"",Table5[[#This Row],[Draw Fee]]+Table5[[#This Row],[Interest]]+Table5[[#This Row],[Principal Payment]]+Table5[[#This Row],[Overdue Interest]],"") -> 2693.75
G17: =IFERROR(RANK(Table4[[#This Row],[Loan Date]],Table4[[#All],[Loan Date]],1) +COUNTIF($I$6:I17,I17)-1,"") | J17: =IF(Table4[[#This Row],[Loan Date]]<>"",IF($E$14 = "End of Month", EOMONTH(Table4[[#This Row],[Loan Date]],IF(DAY(EOMONTH(Table4[[#This Row],[Loan Date]],0)) - DAY(Table4[[#This Row],[Loan Date]])<=$E$15,1,0)),IF($E$14 = "Mid of Month", EOMONTH(Table4[[#This Row],[Loan Date]],IF(15 - DAY(Table4[[#This Row],[Loan Date]])<=$E$15,0,-1))+15,IF($E$14 = "Start of Month", EOMONTH(Table4[[#This Row],[Loan Date]],IF(DAY(EOMONTH(Table4[[#This Row],[Loan Date]],0)) - DAY(Table4[[#This Row],[Loan Date]])<=$E$15,1,0))) + 1)),"") | K17: =IF(Table4[[#This Row],[Loan Date]]<>"", IF($E$14 = "End of Month", EOMONTH(Table4[[#This Row],[Loan Date]],6+IF(DAY(EOMONTH(Table4[[#This Row],[Loan Date]],0)) - DAY(Table4[[#This Row],[Loan Date]])<=$E$15,0,-1)), IF($E$14 = "Mid of Month", EOMONTH(Table4[[#This Row],[Loan Date]],6+IF(15 - DAY(Table4[[#This Row],[Loan Date]])<=$E$15,-1,-2))+15, IF($E$14 = "Start of Month", EOMONTH(Table4[[#This Row],[Loan Date]],6+IF(DAY(EOMONTH(Table4[[#This Row],[Loan Date]],0)) - DAY(Table4[[#This Row],[Loan Date]])<=$E$15,0,-1)) + 1) ) ),"") | L17: =IF(Table4[[#This Row],[Loan Date]]<>"",Table4[[#This Row],[Loan Amount]]/PaymentsPerYear,"") | M17: {=IF(Table4[[#This Row],[Loan Date]]<>"", ((Table4[[#This Row],[Loan Payment Start Date]]-Table4[[#This Row],[Loan Date]])*Table4[[#This Row],[Loan Amount]]*InterestRate/360) + SUM((_xlfn.SEQUENCE(6, 1, Table4[[#This Row],[Loan Amount]]-Table4[[#This Row],[Loan Amount]]/6, -Table4[[#This Row],[Loan Amount]]/6))* (IF($E$14 = "End of Month", EOMONTH(EDATE(Table4[[#This Row],[Loan Payment Start Date]],_xlfn.SEQUENCE(6,1,1,1)),0),IF($E$14 = "Mid of Month",EDATE(Table4[[#This Row],[Loan Payment Start Date]],_xlfn.SEQUENCE(6,1,1,1)), IF($E$14 = "Start of Month", EOMONTH(EDATE(Table4[[#This Row],[Loan Payment Start Date]],_xlfn.SEQUENCE(6,1,1,1)),-1)+1))) - IF($E$14 = "End of Month", EOMONTH(EDATE(Table4[[#This Row],[Loan Payment Start Date]],_xlfn.SEQUENCE(6,1,1,1)),-1),IF($E$14 = "Mid of Month",EDATE(Table4[[#This Row],[Loan Payment Start Date]],_xlfn.SEQUENCE(6,1,0,1)), IF($E$14 = "Start of Month", EOMONTH(EDATE(Table4[[#This Row],[Loan Payment Start Date]],_xlfn.SEQUENCE(6,1,1,1)),-2)+1))))*InterestRate/360),"")} | N17: =IF(Table4[[#This Row],[Loan Amount]]<>"", IF((LoanAmount - (SUMIFS(Table4[Loan Amount],Table4[Loan Date],"<"&Table4[[#This Row],[Loan Date]]) -SUMIFS(Table5[Principal Payment],Table5[Payment date],"<="&Table4[[#This Row],[Loan Date]]) - SUMIFS(Table5[Extra Payment],Table5[Payment date],"<="&Table4[[#This Row],[Loan Date]])) > Table4[[#This Row],[Loan Amount]]),"Yes","No"),"") | O17: =IF(Table4[[#This Row],[Loan Amount]]<>"", LoanAmount - (SUMIFS(Table4[Loan Amount],Table4[Loan Date],"<"&Table4[[#This Row],[Loan Date]]) -SUMIFS(Table5[Principal Payment],Table5[Payment date],"<="&Table4[[#This Row],[Loan Date]]) - SUMIFS(Table5[Extra Payment],Table5[Payment date],"<="&Table4[[#This Row],[Loan Date]])) - Table4[[#This Row],[Loan Amount]],"") | Q17: =IF($E$14="Mid of Month",(IF(EDATE(MIN(Table4[[#All],[Loan Date]]), ROW()-ROW($Q$6)) > EDATE(MAX(Table4[[#All],[Loan Payment End Date]]),1), "", (EOMONTH(EDATE(MIN(Table4[[#All],[Loan Date]]), ROW()-ROW($Q$6)),IF(DAY(EOMONTH(MIN(Table4[[#All],[Loan Date]]),0)) - DAY(MIN(Table4[[#All],[Loan Date]])) <= $E$15, 0, -1))+ 15))), IF($E$14="End of Month",(IF(EDATE(MIN(Table4[[#All],[Loan Date]]), ROW()-ROW($Q$6)) > MAX(Table4[[#All],[Loan Payment End Date]]), "", (EOMONTH(EDATE(MIN(Table4[[#All],[Loan Date]]), ROW()-ROW($Q$6)),IF(31 - DAY(MIN(Table4[[#All],[Loan Date]])) <= $E$15, 1, 0))))), IF($E$14="Start of Month",(IF(EDATE(MIN(Table4[[#All],[Loan Date]]), ROW()-ROW($Q$6)) > MAX(Table4[[#All],[Loan Payment End Date]]), "", (EOMONTH(EDATE(MIN(Table4[[#All],[Loan Date]]), ROW()-ROW($Q$6)),IF(31 - DAY(MIN(Table4[[#All],[Loan Date]])) <= $E$15, 1, 0))) + 1 ))) ) ) -> 45689 | R17: =IF(Table5[[#This Row],[Payment date]]<>"", SUMIFS(Table4[[#All],[Loan Amount]],Table4[[#All],[Loan Date]],"<="&Table5[[#This Row],[Payment date]]) - SUM($S$5:S16)- SUM($W$5:W16),"") -> 10000 | S17: =IF(Table5[[#This Row],[Payment date]]<>"",SUM('Individual Loan Schedule'!C20:HR20) - SUM('Early Payments'!D20:HS20),"") -> 2500 | T17: {=IF(Table5[[#This Row],[Payment date]]<>"",((SUMIFS(Table4[Loan Amount],Table4[Loan Payment Start Date],"<"&Table5[[#This Row],[Payment date]]) - SUM($S$5:$S16) - SUM($W$5:W16))*InterestRate*(Table5[[#This Row],[Payment date]] - IF($E$14="End of Month",EOMONTH(Table5[[#This Row],[Payment date]],-1), IF($E$14="Mid of Month",EOMONTH(Table5[[#This Row],[Payment date]],-2)+15, IF($E$14="Start of Month",EOMONTH(Table5[[#This Row],[Payment date]],-2) + 1))) )/360) + (SUM(IFERROR((IF(Table4[Loan Payment Start Date]=Table5[[#This Row],[Payment date]],Table4[Loan Amount],"")*(Table4[Loan Payment Start Date]-Table4[Loan Date])*InterestRate/360),0),0)),"")} -> 155 | U17: =IF(Table5[[#This Row],[Payment date]]<>"",SUMIFS(Table4[[#All],[Loan Amount]],Table4[[#All],[Loan Payment Start Date]],"="&Table5[[#This Row],[Payment date]])*($E$7),"") -> 0 | V17: {=IF(Table5[[#This Row],[Payment date]]<>"",IF(Table5[[#This Row],[Payment date]]=MIN(Table4[[#All],[Loan Payment Start Date]]),$E$8+$E$10*LoanAmount,0) + IF(Table5[[#This Row],[Payment date]] =MIN(_xlfn._xlws.FILTER(Table5[Payment date],(Table5[Payment date]>=EDATE(LoanStartDate,12*DATEDIF(LoanStartDate,Table5[[#This Row],[Payment date]],"y")))*(Table5[Beginning balance]<>0))), $E$9*LoanAmount,0),"")} -> 0 | Y17: =IF(Table5[[#This Row],[Payment date]]<>"",(SUMIFS(Table4[Loan Amount],Table4[Loan Payment Start Date],"<="&Table5[[#This Row],[Payment date]]) - SUM($S$5:$S16) - - SUM($W$5:W16))*Table5[[#This Row],[Delay in Payment ]]*($E$16+ InterestRate)/365,"") -> 0 | Z17: =IF(Table5[[#This Row],[Payment date]]<>"",Table5[[#This Row],[Payment date]]+Table5[[#This Row],[Delay in Payment ]],"") -> 45689 | AA17: =IF(Table5[[#This Row],[Payment date]]<>"",Table5[[#This Row],[Beginning balance]]-Table5[[#This Row],[Principal Payment]] - Table5[[#This Row],[Extra Payment]],"") -> 7500 | AB17: =IF(Table5[[#This Row],[Payment date]]<>"",Table5[[#This Row],[Draw Fee]]+Table5[[#This Row],[Interest]]+Table5[[#This Row],[Principal Payment]]+Table5[[#This Row],[Overdue Interest]],"") -> 2655
Q18: =IF($E$14="Mid of Month",(IF(EDATE(MIN(Table4[[#All],[Loan Date]]), ROW()-ROW($Q$6)) > EDATE(MAX(Table4[[#All],[Loan Payment End Date]]),1), "", (EOMONTH(EDATE(MIN(Table4[[#All],[Loan Date]]), ROW()-ROW($Q$6)),IF(DAY(EOMONTH(MIN(Table4[[#All],[Loan Date]]),0)) - DAY(MIN(Table4[[#All],[Loan Date]])) <= $E$15, 0, -1))+ 15))), IF($E$14="End of Month",(IF(EDATE(MIN(Table4[[#All],[Loan Date]]), ROW()-ROW($Q$6)) > MAX(Table4[[#All],[Loan Payment End Date]]), "", (EOMONTH(EDATE(MIN(Table4[[#All],[Loan Date]]), ROW()-ROW($Q$6)),IF(31 - DAY(MIN(Table4[[#All],[Loan Date]])) <= $E$15, 1, 0))))), IF($E$14="Start of Month",(IF(EDATE(MIN(Table4[[#All],[Loan Date]]), ROW()-ROW($Q$6)) > MAX(Table4[[#All],[Loan Payment End Date]]), "", (EOMONTH(EDATE(MIN(Table4[[#All],[Loan Date]]), ROW()-ROW($Q$6)),IF(31 - DAY(MIN(Table4[[#All],[Loan Date]])) <= $E$15, 1, 0))) + 1 ))) ) ) -> 45717 | R18: =IF(Table5[[#This Row],[Payment date]]<>"", SUMIFS(Table4[[#All],[Loan Amount]],Table4[[#All],[Loan Date]],"<="&Table5[[#This Row],[Payment date]]) - SUM($S$5:S17)- SUM($W$5:W17),"") -> 7500 | S18: =IF(Table5[[#This Row],[Payment date]]<>"",SUM('Individual Loan Schedule'!C21:HR21) - SUM('Early Payments'!D21:HS21),"") -> 2500 | T18: {=IF(Table5[[#This Row],[Payment date]]<>"",((SUMIFS(Table4[Loan Amount],Table4[Loan Payment Start Date],"<"&Table5[[#This Row],[Payment date]]) - SUM($S$5:$S17) - SUM($W$5:W17))*InterestRate*(Table5[[#This Row],[Payment date]] - IF($E$14="End of Month",EOMONTH(Table5[[#This Row],[Payment date]],-1), IF($E$14="Mid of Month",EOMONTH(Table5[[#This Row],[Payment date]],-2)+15, IF($E$14="Start of Month",EOMONTH(Table5[[#This Row],[Payment date]],-2) + 1))) )/360) + (SUM(IFERROR((IF(Table4[Loan Payment Start Date]=Table5[[#This Row],[Payment date]],Table4[Loan Amount],"")*(Table4[Loan Payment Start Date]-Table4[Loan Date])*InterestRate/360),0),0)),"")} -> 105 | U18: =IF(Table5[[#This Row],[Payment date]]<>"",SUMIFS(Table4[[#All],[Loan Amount]],Table4[[#All],[Loan Payment Start Date]],"="&Table5[[#This Row],[Payment date]])*($E$7),"") -> 0 | V18: {=IF(Table5[[#This Row],[Payment date]]<>"",IF(Table5[[#This Row],[Payment date]]=MIN(Table4[[#All],[Loan Payment Start Date]]),$E$8+$E$10*LoanAmount,0) + IF(Table5[[#This Row],[Payment date]] =MIN(_xlfn._xlws.FILTER(Table5[Payment date],(Table5[Payment date]>=EDATE(LoanStartDate,12*DATEDIF(LoanStartDate,Table5[[#This Row],[Payment date]],"y")))*(Table5[Beginning balance]<>0))), $E$9*LoanAmount,0),"")} -> 0 | Y18: =IF(Table5[[#This Row],[Payment date]]<>"",(SUMIFS(Table4[Loan Amount],Table4[Loan Payment Start Date],"<="&Table5[[#This Row],[Payment date]]) - SUM($S$5:$S17) - - SUM($W$5:W17))*Table5[[#This Row],[Delay in Payment ]]*($E$16+ InterestRate)/365,"") -> 0 | Z18: =IF(Table5[[#This Row],[Payment date]]<>"",Table5[[#This Row],[Payment date]]+Table5[[#This Row],[Delay in Payment ]],"") -> 45717 | AA18: =IF(Table5[[#This Row],[Payment date]]<>"",Table5[[#This Row],[Beginning balance]]-Table5[[#This Row],[Principal Payment]] - Table5[[#This Row],[Extra Payment]],"") -> 5000 | AB18: =IF(Table5[[#This Row],[Payment date]]<>"",Table5[[#This Row],[Draw Fee]]+Table5[[#This Row],[Interest]]+Table5[[#This Row],[Principal Payment]]+Table5[[#This Row],[Overdue Interest]],"") -> 2605
Q19: =IF($E$14="Mid of Month",(IF(EDATE(MIN(Table4[[#All],[Loan Date]]), ROW()-ROW($Q$6)) > EDATE(MAX(Table4[[#All],[Loan Payment End Date]]),1), "", (EOMONTH(EDATE(MIN(Table4[[#All],[Loan Date]]), ROW()-ROW($Q$6)),IF(DAY(EOMONTH(MIN(Table4[[#All],[Loan Date]]),0)) - DAY(MIN(Table4[[#All],[Loan Date]])) <= $E$15, 0, -1))+ 15))), IF($E$14="End of Month",(IF(EDATE(MIN(Table4[[#All],[Loan Date]]), ROW()-ROW($Q$6)) > MAX(Table4[[#All],[Loan Payment End Date]]), "", (EOMONTH(EDATE(MIN(Table4[[#All],[Loan Date]]), ROW()-ROW($Q$6)),IF(31 - DAY(MIN(Table4[[#All],[Loan Date]])) <= $E$15, 1, 0))))), IF($E$14="Start of Month",(IF(EDATE(MIN(Table4[[#All],[Loan Date]]), ROW()-ROW($Q$6)) > MAX(Table4[[#All],[Loan Payment End Date]]), "", (EOMONTH(EDATE(MIN(Table4[[#All],[Loan Date]]), ROW()-ROW($Q$6)),IF(31 - DAY(MIN(Table4[[#All],[Loan Date]])) <= $E$15, 1, 0))) + 1 ))) ) ) -> 45748 | R19: =IF(Table5[[#This Row],[Payment date]]<>"", SUMIFS(Table4[[#All],[Loan Amount]],Table4[[#All],[Loan Date]],"<="&Table5[[#This Row],[Payment date]]) - SUM($S$5:S18)- SUM($W$5:W18),"") -> 5000 | S19: =IF(Table5[[#This Row],[Payment date]]<>"",SUM('Individual Loan Schedule'!C22:HR22) - SUM('Early Payments'!D22:HS22),"") -> 2500 | T19: {=IF(Table5[[#This Row],[Payment date]]<>"",((SUMIFS(Table4[Loan Amount],Table4[Loan Payment Start Date],"<"&Table5[[#This Row],[Payment date]]) - SUM($S$5:$S18) - SUM($W$5:W18))*InterestRate*(Table5[[#This Row],[Payment date]] - IF($E$14="End of Month",EOMONTH(Table5[[#This Row],[Payment date]],-1), IF($E$14="Mid of Month",EOMONTH(Table5[[#This Row],[Payment date]],-2)+15, IF($E$14="Start of Month",EOMONTH(Table5[[#This Row],[Payment date]],-2) + 1))) )/360) + (SUM(IFERROR((IF(Table4[Loan Payment Start Date]=Table5[[#This Row],[Payment date]],Table4[Loan Amount],"")*(Table4[Loan Payment Start Date]-Table4[Loan Date])*InterestRate/360),0),0)),"")} -> 77.5 | U19: =IF(Table5[[#This Row],[Payment date]]<>"",SUMIFS(Table4[[#All],[Loan Amount]],Table4[[#All],[Loan Payment Start Date]],"="&Table5[[#This Row],[Payment date]])*($E$7),"") -> 0 | V19: {=IF(Table5[[#This Row],[Payment date]]<>"",IF(Table5[[#This Row],[Payment date]]=MIN(Table4[[#All],[Loan Payment Start Date]]),$E$8+$E$10*LoanAmount,0) + IF(Table5[[#This Row],[Payment date]] =MIN(_xlfn._xlws.FILTER(Table5[Payment date],(Table5[Payment date]>=EDATE(LoanStartDate,12*DATEDIF(LoanStartDate,Table5[[#This Row],[Payment date]],"y")))*(Table5[Beginning balance]<>0))), $E$9*LoanAmount,0),"")} -> 0 | Y19: =IF(Table5[[#This Row],[Payment date]]<>"",(SUMIFS(Table4[Loan Amount],Table4[Loan Payment Start Date],"<="&Table5[[#This Row],[Payment date]]) - SUM($S$5:$S18) - - SUM($W$5:W18))*Table5[[#This Row],[Delay in Payment ]]*($E$16+ InterestRate)/365,"") -> 0 | Z19: =IF(Table5[[#This Row],[Payment date]]<>"",Table5[[#This Row],[Payment date]]+Table5[[#This Row],[Delay in Payment ]],"") -> 45748 | AA19: =IF(Table5[[#This Row],[Payment date]]<>"",Table5[[#This Row],[Beginning balance]]-Table5[[#This Row],[Principal Payment]] - Table5[[#This Row],[Extra Payment]],"") -> 2500 | AB19: =IF(Table5[[#This Row],[Payment date]]<>"",Table5[[#This Row],[Draw Fee]]+Table5[[#This Row],[Interest]]+Table5[[#This Row],[Principal Payment]]+Table5[[#This Row],[Overdue Interest]],"") -> 2577.5
Q20: =IF($E$14="Mid of Month",(IF(EDATE(MIN(Table4[[#All],[Loan Date]]), ROW()-ROW($Q$6)) > EDATE(MAX(Table4[[#All],[Loan Payment End Date]]),1), "", (EOMONTH(EDATE(MIN(Table4[[#All],[Loan Date]]), ROW()-ROW($Q$6)),IF(DAY(EOMONTH(MIN(Table4[[#All],[Loan Date]]),0)) - DAY(MIN(Table4[[#All],[Loan Date]])) <= $E$15, 0, -1))+ 15))), IF($E$14="End of Month",(IF(EDATE(MIN(Table4[[#All],[Loan Date]]), ROW()-ROW($Q$6)) > MAX(Table4[[#All],[Loan Payment End Date]]), "", (EOMONTH(EDATE(MIN(Table4[[#All],[Loan Date]]), ROW()-ROW($Q$6)),IF(31 - DAY(MIN(Table4[[#All],[Loan Date]])) <= $E$15, 1, 0))))), IF($E$14="Start of Month",(IF(EDATE(MIN(Table4[[#All],[Loan Date]]), ROW()-ROW($Q$6)) > MAX(Table4[[#All],[Loan Payment End Date]]), "", (EOMONTH(EDATE(MIN(Table4[[#All],[Loan Date]]), ROW()-ROW($Q$6)),IF(31 - DAY(MIN(Table4[[#All],[Loan Date]])) <= $E$15, 1, 0))) + 1 ))) ) ) -> 45778 | R20: =IF(Table5[[#This Row],[Payment date]]<>"", SUMIFS(Table4[[#All],[Loan Amount]],Table4[[#All],[Loan Date]],"<="&Table5[[#This Row],[Payment date]]) - SUM($S$5:S19)- SUM($W$5:W19),"") -> 2500 | S20: =IF(Table5[[#This Row],[Payment date]]<>"",SUM('Individual Loan Schedule'!C23:HR23) - SUM('Early Payments'!D23:HS23),"") -> 2500 | T20: {=IF(Table5[[#This Row],[Payment date]]<>"",((SUMIFS(Table4[Loan Amount],Table4[Loan Payment Start Date],"<"&Table5[[#This Row],[Payment date]]) - SUM($S$5:$S19) - SUM($W$5:W19))*InterestRate*(Table5[[#This Row],[Payment date]] - IF($E$14="End of Month",EOMONTH(Table5[[#This Row],[Payment date]],-1), IF($E$14="Mid of Month",EOMONTH(Table5[[#This Row],[Payment date]],-2)+15, IF($E$14="Start of Month",EOMONTH(Table5[[#This Row],[Payment date]],-2) + 1))) )/360) + (SUM(IFERROR((IF(Table4[Loan Payment Start Date]=Table5[[#This Row],[Payment date]],Table4[Loan Amount],"")*(Table4[Loan Payment Start Date]-Table4[Loan Date])*InterestRate/360),0),0)),"")} -> 37.5 | U20: =IF(Table5[[#This Row],[Payment date]]<>"",SUMIFS(Table4[[#All],[Loan Amount]],Table4[[#All],[Loan Payment Start Date]],"="&Table5[[#This Row],[Payment date]])*($E$7),"") -> 0 | V20: {=IF(Table5[[#This Row],[Payment date]]<>"",IF(Table5[[#This Row],[Payment date]]=MIN(Table4[[#All],[Loan Payment Start Date]]),$E$8+$E$10*LoanAmount,0) + IF(Table5[[#This Row],[Payment date]] =MIN(_xlfn._xlws.FILTER(Table5[Payment date],(Table5[Payment date]>=EDATE(LoanStartDate,12*DATEDIF(LoanStartDate,Table5[[#This Row],[Payment date]],"y")))*(Table5[Beginning balance]<>0))), $E$9*LoanAmount,0),"")} -> 0 | Y20: =IF(Table5[[#This Row],[Payment date]]<>"",(SUMIFS(Table4[Loan Amount],Table4[Loan Payment Start Date],"<="&Table5[[#This Row],[Payment date]]) - SUM($S$5:$S19) - - SUM($W$5:W19))*Table5[[#This Row],[Delay in Payment ]]*($E$16+ InterestRate)/365,"") -> 0 | Z20: =IF(Table5[[#This Row],[Payment date]]<>"",Table5[[#This Row],[Payment date]]+Table5[[#This Row],[Delay in Payment ]],"") -> 45778 | AA20: =IF(Table5[[#This Row],[Payment date]]<>"",Table5[[#This Row],[Beginning balance]]-Table5[[#This Row],[Principal Payment]] - Table5[[#This Row],[Extra Payment]],"") -> 1.4551915e-11 | AB20: =IF(Table5[[#This Row],[Payment date]]<>"",Table5[[#This Row],[Draw Fee]]+Table5[[#This Row],[Interest]]+Table5[[#This Row],[Principal Payment]]+Table5[[#This Row],[Overdue Interest]],"") -> 2537.5
Q21: =IF($E$14="Mid of Month",(IF(EDATE(MIN(Table4[[#All],[Loan Date]]), ROW()-ROW($Q$6)) > EDATE(MAX(Table4[[#All],[Loan Payment End Date]]),1), "", (EOMONTH(EDATE(MIN(Table4[[#All],[Loan Date]]), ROW()-ROW($Q$6)),IF(DAY(EOMONTH(MIN(Table4[[#All],[Loan Date]]),0)) - DAY(MIN(Table4[[#All],[Loan Date]])) <= $E$15, 0, -1))+ 15))), IF($E$14="End of Month",(IF(EDATE(MIN(Table4[[#All],[Loan Date]]), ROW()-ROW($Q$6)) > MAX(Table4[[#All],[Loan Payment End Date]]), "", (EOMONTH(EDATE(MIN(Table4[[#All],[Loan Date]]), ROW()-ROW($Q$6)),IF(31 - DAY(MIN(Table4[[#All],[Loan Date]])) <= $E$15, 1, 0))))), IF($E$14="Start of Month",(IF(EDATE(MIN(Table4[[#All],[Loan Date]]), ROW()-ROW($Q$6)) > MAX(Table4[[#All],[Loan Payment End Date]]), "", (EOMONTH(EDATE(MIN(Table4[[#All],[Loan Date]]), ROW()-ROW($Q$6)),IF(31 - DAY(MIN(Table4[[#All],[Loan Date]])) <= $E$15, 1, 0))) + 1 ))) ) ) -> 45809 | R21: =IF(Table5[[#This Row],[Payment date]]<>"", SUMIFS(Table4[[#All],[Loan Amount]],Table4[[#All],[Loan Date]],"<="&Table5[[#This Row],[Payment date]]) - SUM($S$5:S20)- SUM($W$5:W20),"") -> 1.4551915e-11 | S21: =IF(Table5[[#This Row],[Payment date]]<>"",SUM('Individual Loan Schedule'!C24:HR24) - SUM('Early Payments'!D24:HS24),"") -> 0 | T21: {=IF(Table5[[#This Row],[Payment date]]<>"",((SUMIFS(Table4[Loan Amount],Table4[Loan Payment Start Date],"<"&Table5[[#This Row],[Payment date]]) - SUM($S$5:$S20) - SUM($W$5:W20))*InterestRate*(Table5[[#This Row],[Payment date]] - IF($E$14="End of Month",EOMONTH(Table5[[#This Row],[Payment date]],-1), IF($E$14="Mid of Month",EOMONTH(Table5[[#This Row],[Payment date]],-2)+15, IF($E$14="Start of Month",EOMONTH(Table5[[#This Row],[Payment date]],-2) + 1))) )/360) + (SUM(IFERROR((IF(Table4[Loan Payment Start Date]=Table5[[#This Row],[Payment date]],Table4[Loan Amount],"")*(Table4[Loan Payment Start Date]-Table4[Loan Date])*InterestRate/360),0),0)),"")} -> 2.2555469e-13 | U21: =IF(Table5[[#This Row],[Payment date]]<>"",SUMIFS(Table4[[#All],[Loan Amount]],Table4[[#All],[Loan Payment Start Date]],"="&Table5[[#This Row],[Payment date]])*($E$7),"") -> 0 | V21: {=IF(Table5[[#This Row],[Payment date]]<>"",IF(Table5[[#This Row],[Payment date]]=MIN(Table4[[#All],[Loan Payment Start Date]]),$E$8+$E$10*LoanAmount,0) + IF(Table5[[#This Row],[Payment date]] =MIN(_xlfn._xlws.FILTER(Table5[Payment date],(Table5[Payment date]>=EDATE(LoanStartDate,12*DATEDIF(LoanStartDate,Table5[[#This Row],[Payment date]],"y")))*(Table5[Beginning balance]<>0))), $E$9*LoanAmount,0),"")} -> 0 | Y21: =IF(Table5[[#This Row],[Payment date]]<>"",(SUMIFS(Table4[Loan Amount],Table4[Loan Payment Start Date],"<="&Table5[[#This Row],[Payment date]]) - SUM($S$5:$S20) - - SUM($W$5:W20))*Table5[[#This Row],[Delay in Payment ]]*($E$16+ InterestRate)/365,"") -> 0 | Z21: =IF(Table5[[#This Row],[Payment date]]<>"",Table5[[#This Row],[Payment date]]+Table5[[#This Row],[Delay in Payment ]],"") -> 45809 | AA21: =IF(Table5[[#This Row],[Payment date]]<>"",Table5[[#This Row],[Beginning balance]]-Table5[[#This Row],[Principal Payment]] - Table5[[#This Row],[Extra Payment]],"") -> 1.4551915e-11 | AB21: =IF(Table5[[#This Row],[Payment date]]<>"",Table5[[#This Row],[Draw Fee]]+Table5[[#This Row],[Interest]]+Table5[[#This Row],[Principal Payment]]+Table5[[#This Row],[Overdue Interest]],"") -> 2.2555469e-13
Q22: =IF($E$14="Mid of Month",(IF(EDATE(MIN(Table4[[#All],[Loan Date]]), ROW()-ROW($Q$6)) > EDATE(MAX(Table4[[#All],[Loan Payment End Date]]),1), "", (EOMONTH(EDATE(MIN(Table4[[#All],[Loan Date]]), ROW()-ROW($Q$6)),IF(DAY(EOMONTH(MIN(Table4[[#All],[Loan Date]]),0)) - DAY(MIN(Table4[[#All],[Loan Date]])) <= $E$15, 0, -1))+ 15))), IF($E$14="End of Month",(IF(EDATE(MIN(Table4[[#All],[Loan Date]]), ROW()-ROW($Q$6)) > MAX(Table4[[#All],[Loan Payment End Date]]), "", (EOMONTH(EDATE(MIN(Table4[[#All],[Loan Date]]), ROW()-ROW($Q$6)),IF(31 - DAY(MIN(Table4[[#All],[Loan Date]])) <= $E$15, 1, 0))))), IF($E$14="Start of Month",(IF(EDATE(MIN(Table4[[#All],[Loan Date]]), ROW()-ROW($Q$6)) > MAX(Table4[[#All],[Loan Payment End Date]]), "", (EOMONTH(EDATE(MIN(Table4[[#All],[Loan Date]]), ROW()-ROW($Q$6)),IF(31 - DAY(MIN(Table4[[#All],[Loan Date]])) <= $E$15, 1, 0))) + 1 ))) ) ) | R22: =IF(Table5[[#This Row],[Payment date]]<>"", SUMIFS(Table4[[#All],[Loan Amount]],Table4[[#All],[Loan Date]],"<="&Table5[[#This Row],[Payment date]]) - SUM($S$5:S21)- SUM($W$5:W21),"") | S22: =IF(Table5[[#This Row],[Payment date]]<>"",SUM('Individual Loan Schedule'!C25:HR25) - SUM('Early Payments'!D25:HS25),"") | T22: {=IF(Table5[[#This Row],[Payment date]]<>"",((SUMIFS(Table4[Loan Amount],Table4[Loan Payment Start Date],"<"&Table5[[#This Row],[Payment date]]) - SUM($S$5:$S21) - SUM($W$5:W21))*InterestRate*(Table5[[#This Row],[Payment date]] - IF($E$14="End of Month",EOMONTH(Table5[[#This Row],[Payment date]],-1), IF($E$14="Mid of Month",EOMONTH(Table5[[#This Row],[Payment date]],-2)+15, IF($E$14="Start of Month",EOMONTH(Table5[[#This Row],[Payment date]],-2) + 1))) )/360) + (SUM(IFERROR((IF(Table4[Loan Payment Start Date]=Table5[[#This Row],[Payment date]],Table4[Loan Amount],"")*(Table4[Loan Payment Start Date]-Table4[Loan Date])*InterestRate/360),0),0)),"")} | U22: =IF(Table5[[#This Row],[Payment date]]<>"",SUMIFS(Table4[[#All],[Loan Amount]],Table4[[#All],[Loan Payment Start Date]],"="&Table5[[#This Row],[Payment date]])*($E$7),"") | V22: {=IF(Table5[[#This Row],[Payment date]]<>"",IF(Table5[[#This Row],[Payment date]]=MIN(Table4[[#All],[Loan Payment Start Date]]),$E$8+$E$10*LoanAmount,0) + IF(Table5[[#This Row],[Payment date]] =MIN(_xlfn._xlws.FILTER(Table5[Payment date],(Table5[Payment date]>=EDATE(LoanStartDate,12*DATEDIF(LoanStartDate,Table5[[#This Row],[Payment date]],"y")))*(Table5[Beginning balance]<>0))), $E$9*LoanAmount,0),"")} | Y22: =IF(Table5[[#This Row],[Payment date]]<>"",(SUMIFS(Table4[Loan Amount],Table4[Loan Payment Start Date],"<="&Table5[[#This Row],[Payment date]]) - SUM($S$5:$S21) - - SUM($W$5:W21))*Table5[[#This Row],[Delay in Payment ]]*($E$16+ InterestRate)/365,"") | Z22: =IF(Table5[[#This Row],[Payment date]]<>"",Table5[[#This Row],[Payment date]]+Table5[[#This Row],[Delay in Payment ]],"") | AA22: =IF(Table5[[#This Row],[Payment date]]<>"",Table5[[#This Row],[Beginning balance]]-Table5[[#This Row],[Principal Payment]] - Table5[[#This Row],[Extra Payment]],"") | AB22: =IF(Table5[[#This Row],[Payment date]]<>"",Table5[[#This Row],[Draw Fee]]+Table5[[#This Row],[Interest]]+Table5[[#This Row],[Principal Payment]]+Table5[[#This Row],[Overdue Interest]],"")
Q23: =IF($E$14="Mid of Month",(IF(EDATE(MIN(Table4[[#All],[Loan Date]]), ROW()-ROW($Q$6)) > EDATE(MAX(Table4[[#All],[Loan Payment End Date]]),1), "", (EOMONTH(EDATE(MIN(Table4[[#All],[Loan Date]]), ROW()-ROW($Q$6)),IF(DAY(EOMONTH(MIN(Table4[[#All],[Loan Date]]),0)) - DAY(MIN(Table4[[#All],[Loan Date]])) <= $E$15, 0, -1))+ 15))), IF($E$14="End of Month",(IF(EDATE(MIN(Table4[[#All],[Loan Date]]), ROW()-ROW($Q$6)) > MAX(Table4[[#All],[Loan Payment End Date]]), "", (EOMONTH(EDATE(MIN(Table4[[#All],[Loan Date]]), ROW()-ROW($Q$6)),IF(31 - DAY(MIN(Table4[[#All],[Loan Date]])) <= $E$15, 1, 0))))), IF($E$14="Start of Month",(IF(EDATE(MIN(Table4[[#All],[Loan Date]]), ROW()-ROW($Q$6)) > MAX(Table4[[#All],[Loan Payment End Date]]), "", (EOMONTH(EDATE(MIN(Table4[[#All],[Loan Date]]), ROW()-ROW($Q$6)),IF(31 - DAY(MIN(Table4[[#All],[Loan Date]])) <= $E$15, 1, 0))) + 1 ))) ) ) | R23: =IF(Table5[[#This Row],[Payment date]]<>"", SUMIFS(Table4[[#All],[Loan Amount]],Table4[[#All],[Loan Date]],"<="&Table5[[#This Row],[Payment date]]) - SUM($S$5:S22)- SUM($W$5:W22),"") | S23: =IF(Table5[[#This Row],[Payment date]]<>"",SUM('Individual Loan Schedule'!C26:HR26) - SUM('Early Payments'!D26:HS26),"") | T23: {=IF(Table5[[#This Row],[Payment date]]<>"",((SUMIFS(Table4[Loan Amount],Table4[Loan Payment Start Date],"<"&Table5[[#This Row],[Payment date]]) - SUM($S$5:$S22) - SUM($W$5:W22))*InterestRate*(Table5[[#This Row],[Payment date]] - IF($E$14="End of Month",EOMONTH(Table5[[#This Row],[Payment date]],-1), IF($E$14="Mid of Month",EOMONTH(Table5[[#This Row],[Payment date]],-2)+15, IF($E$14="Start of Month",EOMONTH(Table5[[#This Row],[Payment date]],-2) + 1))) )/360) + (SUM(IFERROR((IF(Table4[Loan Payment Start Date]=Table5[[#This Row],[Payment date]],Table4[Loan Amount],"")*(Table4[Loan Payment Start Date]-Table4[Loan Date])*InterestRate/360),0),0)),"")} | U23: =IF(Table5[[#This Row],[Payment date]]<>"",SUMIFS(Table4[[#All],[Loan Amount]],Table4[[#All],[Loan Payment Start Date]],"="&Table5[[#This Row],[Payment date]])*($E$7),"") | V23: {=IF(Table5[[#This Row],[Payment date]]<>"",IF(Table5[[#This Row],[Payment date]]=MIN(Table4[[#All],[Loan Payment Start Date]]),$E$8+$E$10*LoanAmount,0) + IF(Table5[[#This Row],[Payment date]] =MIN(_xlfn._xlws.FILTER(Table5[Payment date],(Table5[Payment date]>=EDATE(LoanStartDate,12*DATEDIF(LoanStartDate,Table5[[#This Row],[Payment date]],"y")))*(Table5[Beginning balance]<>0))), $E$9*LoanAmount,0),"")} | Y23: =IF(Table5[[#This Row],[Payment date]]<>"",(SUMIFS(Table4[Loan Amount],Table4[Loan Payment Start Date],"<="&Table5[[#This Row],[Payment date]]) - SUM($S$5:$S22) - - SUM($W$5:W22))*Table5[[#This Row],[Delay in Payment ]]*($E$16+ InterestRate)/365,"") | Z23: =IF(Table5[[#This Row],[Payment date]]<>"",Table5[[#This Row],[Payment date]]+Table5[[#This Row],[Delay in Payment ]],"") | AA23: =IF(Table5[[#This Row],[Payment date]]<>"",Table5[[#This Row],[Beginning balance]]-Table5[[#This Row],[Principal Payment]] - Table5[[#This Row],[Extra Payment]],"") | AB23: =IF(Table5[[#This Row],[Payment date]]<>"",Table5[[#This Row],[Draw Fee]]+Table5[[#This Row],[Interest]]+Table5[[#This Row],[Principal Payment]]+Table5[[#This Row],[Overdue Interest]],"")
Q24: =IF($E$14="Mid of Month",(IF(EDATE(MIN(Table4[[#All],[Loan Date]]), ROW()-ROW($Q$6)) > EDATE(MAX(Table4[[#All],[Loan Payment End Date]]),1), "", (EOMONTH(EDATE(MIN(Table4[[#All],[Loan Date]]), ROW()-ROW($Q$6)),IF(DAY(EOMONTH(MIN(Table4[[#All],[Loan Date]]),0)) - DAY(MIN(Table4[[#All],[Loan Date]])) <= $E$15, 0, -1))+ 15))), IF($E$14="End of Month",(IF(EDATE(MIN(Table4[[#All],[Loan Date]]), ROW()-ROW($Q$6)) > MAX(Table4[[#All],[Loan Payment End Date]]), "", (EOMONTH(EDATE(MIN(Table4[[#All],[Loan Date]]), ROW()-ROW($Q$6)),IF(31 - DAY(MIN(Table4[[#All],[Loan Date]])) <= $E$15, 1, 0))))), IF($E$14="Start of Month",(IF(EDATE(MIN(Table4[[#All],[Loan Date]]), ROW()-ROW($Q$6)) > MAX(Table4[[#All],[Loan Payment End Date]]), "", (EOMONTH(EDATE(MIN(Table4[[#All],[Loan Date]]), ROW()-ROW($Q$6)),IF(31 - DAY(MIN(Table4[[#All],[Loan Date]])) <= $E$15, 1, 0))) + 1 ))) ) ) | R24: =IF(Table5[[#This Row],[Payment date]]<>"", SUMIFS(Table4[[#All],[Loan Amount]],Table4[[#All],[Loan Date]],"<="&Table5[[#This Row],[Payment date]]) - SUM($S$5:S23)- SUM($W$5:W23),"") | S24: =IF(Table5[[#This Row],[Payment date]]<>"",SUM('Individual Loan Schedule'!C27:HR27) - SUM('Early Payments'!D27:HS27),"") | T24: {=IF(Table5[[#This Row],[Payment date]]<>"",((SUMIFS(Table4[Loan Amount],Table4[Loan Payment Start Date],"<"&Table5[[#This Row],[Payment date]]) - SUM($S$5:$S23) - SUM($W$5:W23))*InterestRate*(Table5[[#This Row],[Payment date]] - IF($E$14="End of Month",EOMONTH(Table5[[#This Row],[Payment date]],-1), IF($E$14="Mid of Month",EOMONTH(Table5[[#This Row],[Payment date]],-2)+15, IF($E$14="Start of Month",EOMONTH(Table5[[#This Row],[Payment date]],-2) + 1))) )/360) + (SUM(IFERROR((IF(Table4[Loan Payment Start Date]=Table5[[#This Row],[Payment date]],Table4[Loan Amount],"")*(Table4[Loan Payment Start Date]-Table4[Loan Date])*InterestRate/360),0),0)),"")} | U24: =IF(Table5[[#This Row],[Payment date]]<>"",SUMIFS(Table4[[#All],[Loan Amount]],Table4[[#All],[Loan Payment Start Date]],"="&Table5[[#This Row],[Payment date]])*($E$7),"") | V24: {=IF(Table5[[#This Row],[Payment date]]<>"",IF(Table5[[#This Row],[Payment date]]=MIN(Table4[[#All],[Loan Payment Start Date]]),$E$8+$E$10*LoanAmount,0) + IF(Table5[[#This Row],[Payment date]] =MIN(_xlfn._xlws.FILTER(Table5[Payment date],(Table5[Payment date]>=EDATE(LoanStartDate,12*DATEDIF(LoanStartDate,Table5[[#This Row],[Payment date]],"y")))*(Table5[Beginning balance]<>0))), $E$9*LoanAmount,0),"")} | Y24: =IF(Table5[[#This Row],[Payment date]]<>"",(SUMIFS(Table4[Loan Amount],Table4[Loan Payment Start Date],"<="&Table5[[#This Row],[Payment date]]) - SUM($S$5:$S23) - - SUM($W$5:W23))*Table5[[#This Row],[Delay in Payment ]]*($E$16+ InterestRate)/365,"") | Z24: =IF(Table5[[#This Row],[Payment date]]<>"",Table5[[#This Row],[Payment date]]+Table5[[#This Row],[Delay in Payment ]],"") | AA24: =IF(Table5[[#This Row],[Payment date]]<>"",Table5[[#This Row],[Beginning balance]]-Table5[[#This Row],[Principal Payment]] - Table5[[#This Row],[Extra Payment]],"") | AB24: =IF(Table5[[#This Row],[Payment date]]<>"",Table5[[#This Row],[Draw Fee]]+Table5[[#This Row],[Interest]]+Table5[[#This Row],[Principal Payment]]+Table5[[#This Row],[Overdue Interest]],"")
Q25: =IF($E$14="Mid of Month",(IF(EDATE(MIN(Table4[[#All],[Loan Date]]), ROW()-ROW($Q$6)) > EDATE(MAX(Table4[[#All],[Loan Payment End Date]]),1), "", (EOMONTH(EDATE(MIN(Table4[[#All],[Loan Date]]), ROW()-ROW($Q$6)),IF(DAY(EOMONTH(MIN(Table4[[#All],[Loan Date]]),0)) - DAY(MIN(Table4[[#All],[Loan Date]])) <= $E$15, 0, -1))+ 15))), IF($E$14="End of Month",(IF(EDATE(MIN(Table4[[#All],[Loan Date]]), ROW()-ROW($Q$6)) > MAX(Table4[[#All],[Loan Payment End Date]]), "", (EOMONTH(EDATE(MIN(Table4[[#All],[Loan Date]]), ROW()-ROW($Q$6)),IF(31 - DAY(MIN(Table4[[#All],[Loan Date]])) <= $E$15, 1, 0))))), IF($E$14="Start of Month",(IF(EDATE(MIN(Table4[[#All],[Loan Date]]), ROW()-ROW($Q$6)) > MAX(Table4[[#All],[Loan Payment End Date]]), "", (EOMONTH(EDATE(MIN(Table4[[#All],[Loan Date]]), ROW()-ROW($Q$6)),IF(31 - DAY(MIN(Table4[[#All],[Loan Date]])) <= $E$15, 1, 0))) + 1 ))) ) ) | R25: =IF(Table5[[#This Row],[Payment date]]<>"", SUMIFS(Table4[[#All],[Loan Amount]],Table4[[#All],[Loan Date]],"<="&Table5[[#This Row],[Payment date]]) - SUM($S$5:S24)- SUM($W$5:W24),"") | S25: =IF(Table5[[#This Row],[Payment date]]<>"",SUM('Individual Loan Schedule'!C28:HR28) - SUM('Early Payments'!D28:HS28),"") | T25: {=IF(Table5[[#This Row],[Payment date]]<>"",((SUMIFS(Table4[Loan Amount],Table4[Loan Payment Start Date],"<"&Table5[[#This Row],[Payment date]]) - SUM($S$5:$S24) - SUM($W$5:W24))*InterestRate*(Table5[[#This Row],[Payment date]] - IF($E$14="End of Month",EOMONTH(Table5[[#This Row],[Payment date]],-1), IF($E$14="Mid of Month",EOMONTH(Table5[[#This Row],[Payment date]],-2)+15, IF($E$14="Start of Month",EOMONTH(Table5[[#This Row],[Payment date]],-2) + 1))) )/360) + (SUM(IFERROR((IF(Table4[Loan Payment Start Date]=Table5[[#This Row],[Payment date]],Table4[Loan Amount],"")*(Table4[Loan Payment Start Date]-Table4[Loan Date])*InterestRate/360),0),0)),"")} | U25: =IF(Table5[[#This Row],[Payment date]]<>"",SUMIFS(Table4[[#All],[Loan Amount]],Table4[[#All],[Loan Payment Start Date]],"="&Table5[[#This Row],[Payment date]])*($E$7),"") | V25: {=IF(Table5[[#This Row],[Payment date]]<>"",IF(Table5[[#This Row],[Payment date]]=MIN(Table4[[#All],[Loan Payment Start Date]]),$E$8+$E$10*LoanAmount,0) + IF(Table5[[#This Row],[Payment date]] =MIN(_xlfn._xlws.FILTER(Table5[Payment date],(Table5[Payment date]>=EDATE(LoanStartDate,12*DATEDIF(LoanStartDate,Table5[[#This Row],[Payment date]],"y")))*(Table5[Beginning balance]<>0))), $E$9*LoanAmount,0),"")} | Y25: =IF(Table5[[#This Row],[Payment date]]<>"",(SUMIFS(Table4[Loan Amount],Table4[Loan Payment Start Date],"<="&Table5[[#This Row],[Payment date]]) - SUM($S$5:$S24) - - SUM($W$5:W24))*Table5[[#This Row],[Delay in Payment ]]*($E$16+ InterestRate)/365,"") | Z25: =IF(Table5[[#This Row],[Payment date]]<>"",Table5[[#This Row],[Payment date]]+Table5[[#This Row],[Delay in Payment ]],"") | AA25: =IF(Table5[[#This Row],[Payment date]]<>"",Table5[[#This Row],[Beginning balance]]-Table5[[#This Row],[Principal Payment]] - Table5[[#This Row],[Extra Payment]],"") | AB25: =IF(Table5[[#This Row],[Payment date]]<>"",Table5[[#This Row],[Draw Fee]]+Table5[[#This Row],[Interest]]+Table5[[#This Row],[Principal Payment]]+Table5[[#This Row],[Overdue Interest]],"")
Q26: =IF($E$14="Mid of Month",(IF(EDATE(MIN(Table4[[#All],[Loan Date]]), ROW()-ROW($Q$6)) > EDATE(MAX(Table4[[#All],[Loan Payment End Date]]),1), "", (EOMONTH(EDATE(MIN(Table4[[#All],[Loan Date]]), ROW()-ROW($Q$6)),IF(DAY(EOMONTH(MIN(Table4[[#All],[Loan Date]]),0)) - DAY(MIN(Table4[[#All],[Loan Date]])) <= $E$15, 0, -1))+ 15))), IF($E$14="End of Month",(IF(EDATE(MIN(Table4[[#All],[Loan Date]]), ROW()-ROW($Q$6)) > MAX(Table4[[#All],[Loan Payment End Date]]), "", (EOMONTH(EDATE(MIN(Table4[[#All],[Loan Date]]), ROW()-ROW($Q$6)),IF(31 - DAY(MIN(Table4[[#All],[Loan Date]])) <= $E$15, 1, 0))))), IF($E$14="Start of Month",(IF(EDATE(MIN(Table4[[#All],[Loan Date]]), ROW()-ROW($Q$6)) > MAX(Table4[[#All],[Loan Payment End Date]]), "", (EOMONTH(EDATE(MIN(Table4[[#All],[Loan Date]]), ROW()-ROW($Q$6)),IF(31 - DAY(MIN(Table4[[#All],[Loan Date]])) <= $E$15, 1, 0))) + 1 ))) ) ) | R26: =IF(Table5[[#This Row],[Payment date]]<>"", SUMIFS(Table4[[#All],[Loan Amount]],Table4[[#All],[Loan Date]],"<="&Table5[[#This Row],[Payment date]]) - SUM($S$5:S25)- SUM($W$5:W25),"") | S26: =IF(Table5[[#This Row],[Payment date]]<>"",SUM('Individual Loan Schedule'!C29:HR29) - SUM('Early Payments'!D29:HS29),"") | T26: {=IF(Table5[[#This Row],[Payment date]]<>"",((SUMIFS(Table4[Loan Amount],Table4[Loan Payment Start Date],"<"&Table5[[#This Row],[Payment date]]) - SUM($S$5:$S25) - SUM($W$5:W25))*InterestRate*(Table5[[#This Row],[Payment date]] - IF($E$14="End of Month",EOMONTH(Table5[[#This Row],[Payment date]],-1), IF($E$14="Mid of Month",EOMONTH(Table5[[#This Row],[Payment date]],-2)+15, IF($E$14="Start of Month",EOMONTH(Table5[[#This Row],[Payment date]],-2) + 1))) )/360) + (SUM(IFERROR((IF(Table4[Loan Payment Start Date]=Table5[[#This Row],[Payment date]],Table4[Loan Amount],"")*(Table4[Loan Payment Start Date]-Table4[Loan Date])*InterestRate/360),0),0)),"")} | U26: =IF(Table5[[#This Row],[Payment date]]<>"",SUMIFS(Table4[[#All],[Loan Amount]],Table4[[#All],[Loan Payment Start Date]],"="&Table5[[#This Row],[Payment date]])*($E$7),"") | V26: {=IF(Table5[[#This Row],[Payment date]]<>"",IF(Table5[[#This Row],[Payment date]]=MIN(Table4[[#All],[Loan Payment Start Date]]),$E$8+$E$10*LoanAmount,0) + IF(Table5[[#This Row],[Payment date]] =MIN(_xlfn._xlws.FILTER(Table5[Payment date],(Table5[Payment date]>=EDATE(LoanStartDate,12*DATEDIF(LoanStartDate,Table5[[#This Row],[Payment date]],"y")))*(Table5[Beginning balance]<>0))), $E$9*LoanAmount,0),"")} | Y26: =IF(Table5[[#This Row],[Payment date]]<>"",(SUMIFS(Table4[Loan Amount],Table4[Loan Payment Start Date],"<="&Table5[[#This Row],[Payment date]]) - SUM($S$5:$S25) - - SUM($W$5:W25))*Table5[[#This Row],[Delay in Payment ]]*($E$16+ InterestRate)/365,"") | Z26: =IF(Table5[[#This Row],[Payment date]]<>"",Table5[[#This Row],[Payment date]]+Table5[[#This Row],[Delay in Payment ]],"") | AA26: =IF(Table5[[#This Row],[Payment date]]<>"",Table5[[#This Row],[Beginning balance]]-Table5[[#This Row],[Principal Payment]] - Table5[[#This Row],[Extra Payment]],"") | AB26: =IF(Table5[[#This Row],[Payment date]]<>"",Table5[[#This Row],[Draw Fee]]+Table5[[#This Row],[Interest]]+Table5[[#This Row],[Principal Payment]]+Table5[[#This Row],[Overdue Interest]],"")
Q27: =IF($E$14="Mid of Month",(IF(EDATE(MIN(Table4[[#All],[Loan Date]]), ROW()-ROW($Q$6)) > EDATE(MAX(Table4[[#All],[Loan Payment End Date]]),1), "", (EOMONTH(EDATE(MIN(Table4[[#All],[Loan Date]]), ROW()-ROW($Q$6)),IF(DAY(EOMONTH(MIN(Table4[[#All],[Loan Date]]),0)) - DAY(MIN(Table4[[#All],[Loan Date]])) <= $E$15, 0, -1))+ 15))), IF($E$14="End of Month",(IF(EDATE(MIN(Table4[[#All],[Loan Date]]), ROW()-ROW($Q$6)) > MAX(Table4[[#All],[Loan Payment End Date]]), "", (EOMONTH(EDATE(MIN(Table4[[#All],[Loan Date]]), ROW()-ROW($Q$6)),IF(31 - DAY(MIN(Table4[[#All],[Loan Date]])) <= $E$15, 1, 0))))), IF($E$14="Start of Month",(IF(EDATE(MIN(Table4[[#All],[Loan Date]]), ROW()-ROW($Q$6)) > MAX(Table4[[#All],[Loan Payment End Date]]), "", (EOMONTH(EDATE(MIN(Table4[[#All],[Loan Date]]), ROW()-ROW($Q$6)),IF(31 - DAY(MIN(Table4[[#All],[Loan Date]])) <= $E$15, 1, 0))) + 1 ))) ) ) | R27: =IF(Table5[[#This Row],[Payment date]]<>"", SUMIFS(Table4[[#All],[Loan Amount]],Table4[[#All],[Loan Date]],"<="&Table5[[#This Row],[Payment date]]) - SUM($S$5:S26)- SUM($W$5:W26),"") | S27: =IF(Table5[[#This Row],[Payment date]]<>"",SUM('Individual Loan Schedule'!C30:HR30) - SUM('Early Payments'!D30:HS30),"") | T27: {=IF(Table5[[#This Row],[Payment date]]<>"",((SUMIFS(Table4[Loan Amount],Table4[Loan Payment Start Date],"<"&Table5[[#This Row],[Payment date]]) - SUM($S$5:$S26) - SUM($W$5:W26))*InterestRate*(Table5[[#This Row],[Payment date]] - IF($E$14="End of Month",EOMONTH(Table5[[#This Row],[Payment date]],-1), IF($E$14="Mid of Month",EOMONTH(Table5[[#This Row],[Payment date]],-2)+15, IF($E$14="Start of Month",EOMONTH(Table5[[#This Row],[Payment date]],-2) + 1))) )/360) + (SUM(IFERROR((IF(Table4[Loan Payment Start Date]=Table5[[#This Row],[Payment date]],Table4[Loan Amount],"")*(Table4[Loan Payment Start Date]-Table4[Loan Date])*InterestRate/360),0),0)),"")} | U27: =IF(Table5[[#This Row],[Payment date]]<>"",SUMIFS(Table4[[#All],[Loan Amount]],Table4[[#All],[Loan Payment Start Date]],"="&Table5[[#This Row],[Payment date]])*($E$7),"") | V27: {=IF(Table5[[#This Row],[Payment date]]<>"",IF(Table5[[#This Row],[Payment date]]=MIN(Table4[[#All],[Loan Payment Start Date]]),$E$8+$E$10*LoanAmount,0) + IF(Table5[[#This Row],[Payment date]] =MIN(_xlfn._xlws.FILTER(Table5[Payment date],(Table5[Payment date]>=EDATE(LoanStartDate,12*DATEDIF(LoanStartDate,Table5[[#This Row],[Payment date]],"y")))*(Table5[Beginning balance]<>0))), $E$9*LoanAmount,0),"")} | Y27: =IF(Table5[[#This Row],[Payment date]]<>"",(SUMIFS(Table4[Loan Amount],Table4[Loan Payment Start Date],"<="&Table5[[#This Row],[Payment date]]) - SUM($S$5:$S26) - - SUM($W$5:W26))*Table5[[#This Row],[Delay in Payment ]]*($E$16+ InterestRate)/365,"") | Z27: =IF(Table5[[#This Row],[Payment date]]<>"",Table5[[#This Row],[Payment date]]+Table5[[#This Row],[Delay in Payment ]],"") | AA27: =IF(Table5[[#This Row],[Payment date]]<>"",Table5[[#This Row],[Beginning balance]]-Table5[[#This Row],[Principal Payment]] - Table5[[#This Row],[Extra Payment]],"") | AB27: =IF(Table5[[#This Row],[Payment date]]<>"",Table5[[#This Row],[Draw Fee]]+Table5[[#This Row],[Interest]]+Table5[[#This Row],[Principal Payment]]+Table5[[#This Row],[Overdue Interest]],"")
Q28: =IF($E$14="Mid of Month",(IF(EDATE(MIN(Table4[[#All],[Loan Date]]), ROW()-ROW($Q$6)) > EDATE(MAX(Table4[[#All],[Loan Payment End Date]]),1), "", (EOMONTH(EDATE(MIN(Table4[[#All],[Loan Date]]), ROW()-ROW($Q$6)),IF(DAY(EOMONTH(MIN(Table4[[#All],[Loan Date]]),0)) - DAY(MIN(Table4[[#All],[Loan Date]])) <= $E$15, 0, -1))+ 15))), IF($E$14="End of Month",(IF(EDATE(MIN(Table4[[#All],[Loan Date]]), ROW()-ROW($Q$6)) > MAX(Table4[[#All],[Loan Payment End Date]]), "", (EOMONTH(EDATE(MIN(Table4[[#All],[Loan Date]]), ROW()-ROW($Q$6)),IF(31 - DAY(MIN(Table4[[#All],[Loan Date]])) <= $E$15, 1, 0))))), IF($E$14="Start of Month",(IF(EDATE(MIN(Table4[[#All],[Loan Date]]), ROW()-ROW($Q$6)) > MAX(Table4[[#All],[Loan Payment End Date]]), "", (EOMONTH(EDATE(MIN(Table4[[#All],[Loan Date]]), ROW()-ROW($Q$6)),IF(31 - DAY(MIN(Table4[[#All],[Loan Date]])) <= $E$15, 1, 0))) + 1 ))) ) ) | R28: =IF(Table5[[#This Row],[Payment date]]<>"", SUMIFS(Table4[[#All],[Loan Amount]],Table4[[#All],[Loan Date]],"<="&Table5[[#This Row],[Payment date]]) - SUM($S$5:S27)- SUM($W$5:W27),"") | S28: =IF(Table5[[#This Row],[Payment date]]<>"",SUM('Individual Loan Schedule'!C31:HR31) - SUM('Early Payments'!D31:HS31),"") | T28: {=IF(Table5[[#This Row],[Payment date]]<>"",((SUMIFS(Table4[Loan Amount],Table4[Loan Payment Start Date],"<"&Table5[[#This Row],[Payment date]]) - SUM($S$5:$S27) - SUM($W$5:W27))*InterestRate*(Table5[[#This Row],[Payment date]] - IF($E$14="End of Month",EOMONTH(Table5[[#This Row],[Payment date]],-1), IF($E$14="Mid of Month",EOMONTH(Table5[[#This Row],[Payment date]],-2)+15, IF($E$14="Start of Month",EOMONTH(Table5[[#This Row],[Payment date]],-2) + 1))) )/360) + (SUM(IFERROR((IF(Table4[Loan Payment Start Date]=Table5[[#This Row],[Payment date]],Table4[Loan Amount],"")*(Table4[Loan Payment Start Date]-Table4[Loan Date])*InterestRate/360),0),0)),"")} | U28: =IF(Table5[[#This Row],[Payment date]]<>"",SUMIFS(Table4[[#All],[Loan Amount]],Table4[[#All],[Loan Payment Start Date]],"="&Table5[[#This Row],[Payment date]])*($E$7),"") | V28: {=IF(Table5[[#This Row],[Payment date]]<>"",IF(Table5[[#This Row],[Payment date]]=MIN(Table4[[#All],[Loan Payment Start Date]]),$E$8+$E$10*LoanAmount,0) + IF(Table5[[#This Row],[Payment date]] =MIN(_xlfn._xlws.FILTER(Table5[Payment date],(Table5[Payment date]>=EDATE(LoanStartDate,12*DATEDIF(LoanStartDate,Table5[[#This Row],[Payment date]],"y")))*(Table5[Beginning balance]<>0))), $E$9*LoanAmount,0),"")} | Y28: =IF(Table5[[#This Row],[Payment date]]<>"",(SUMIFS(Table4[Loan Amount],Table4[Loan Payment Start Date],"<="&Table5[[#This Row],[Payment date]]) - SUM($S$5:$S27) - - SUM($W$5:W27))*Table5[[#This Row],[Delay in Payment ]]*($E$16+ InterestRate)/365,"") | Z28: =IF(Table5[[#This Row],[Payment date]]<>"",Table5[[#This Row],[Payment date]]+Table5[[#This Row],[Delay in Payment ]],"") | AA28: =IF(Table5[[#This Row],[Payment date]]<>"",Table5[[#This Row],[Beginning balance]]-Table5[[#This Row],[Principal Payment]] - Table5[[#This Row],[Extra Payment]],"") | AB28: =IF(Table5[[#This Row],[Payment date]]<>"",Table5[[#This Row],[Draw Fee]]+Table5[[#This Row],[Interest]]+Table5[[#This Row],[Principal Payment]]+Table5[[#This Row],[Overdue Interest]],"")
Q29: =IF($E$14="Mid of Month",(IF(EDATE(MIN(Table4[[#All],[Loan Date]]), ROW()-ROW($Q$6)) > EDATE(MAX(Table4[[#All],[Loan Payment End Date]]),1), "", (EOMONTH(EDATE(MIN(Table4[[#All],[Loan Date]]), ROW()-ROW($Q$6)),IF(DAY(EOMONTH(MIN(Table4[[#All],[Loan Date]]),0)) - DAY(MIN(Table4[[#All],[Loan Date]])) <= $E$15, 0, -1))+ 15))), IF($E$14="End of Month",(IF(EDATE(MIN(Table4[[#All],[Loan Date]]), ROW()-ROW($Q$6)) > MAX(Table4[[#All],[Loan Payment End Date]]), "", (EOMONTH(EDATE(MIN(Table4[[#All],[Loan Date]]), ROW()-ROW($Q$6)),IF(31 - DAY(MIN(Table4[[#All],[Loan Date]])) <= $E$15, 1, 0))))), IF($E$14="Start of Month",(IF(EDATE(MIN(Table4[[#All],[Loan Date]]), ROW()-ROW($Q$6)) > MAX(Table4[[#All],[Loan Payment End Date]]), "", (EOMONTH(EDATE(MIN(Table4[[#All],[Loan Date]]), ROW()-ROW($Q$6)),IF(31 - DAY(MIN(Table4[[#All],[Loan Date]])) <= $E$15, 1, 0))) + 1 ))) ) ) | R29: =IF(Table5[[#This Row],[Payment date]]<>"", SUMIFS(Table4[[#All],[Loan Amount]],Table4[[#All],[Loan Date]],"<="&Table5[[#This Row],[Payment date]]) - SUM($S$5:S28)- SUM($W$5:W28),"") | S29: =IF(Table5[[#This Row],[Payment date]]<>"",SUM('Individual Loan Schedule'!C32:HR32) - SUM('Early Payments'!D32:HS32),"") | T29: {=IF(Table5[[#This Row],[Payment date]]<>"",((SUMIFS(Table4[Loan Amount],Table4[Loan Payment Start Date],"<"&Table5[[#This Row],[Payment date]]) - SUM($S$5:$S28) - SUM($W$5:W28))*InterestRate*(Table5[[#This Row],[Payment date]] - IF($E$14="End of Month",EOMONTH(Table5[[#This Row],[Payment date]],-1), IF($E$14="Mid of Month",EOMONTH(Table5[[#This Row],[Payment date]],-2)+15, IF($E$14="Start of Month",EOMONTH(Table5[[#This Row],[Payment date]],-2) + 1))) )/360) + (SUM(IFERROR((IF(Table4[Loan Payment Start Date]=Table5[[#This Row],[Payment date]],Table4[Loan Amount],"")*(Table4[Loan Payment Start Date]-Table4[Loan Date])*InterestRate/360),0),0)),"")} | U29: =IF(Table5[[#This Row],[Payment date]]<>"",SUMIFS(Table4[[#All],[Loan Amount]],Table4[[#All],[Loan Payment Start Date]],"="&Table5[[#This Row],[Payment date]])*($E$7),"") | V29: {=IF(Table5[[#This Row],[Payment date]]<>"",IF(Table5[[#This Row],[Payment date]]=MIN(Table4[[#All],[Loan Payment Start Date]]),$E$8+$E$10*LoanAmount,0) + IF(Table5[[#This Row],[Payment date]] =MIN(_xlfn._xlws.FILTER(Table5[Payment date],(Table5[Payment date]>=EDATE(LoanStartDate,12*DATEDIF(LoanStartDate,Table5[[#This Row],[Payment date]],"y")))*(Table5[Beginning balance]<>0))), $E$9*LoanAmount,0),"")} | Y29: =IF(Table5[[#This Row],[Payment date]]<>"",(SUMIFS(Table4[Loan Amount],Table4[Loan Payment Start Date],"<="&Table5[[#This Row],[Payment date]]) - SUM($S$5:$S28) - - SUM($W$5:W28))*Table5[[#This Row],[Delay in Payment ]]*($E$16+ InterestRate)/365,"") | Z29: =IF(Table5[[#This Row],[Payment date]]<>"",Table5[[#This Row],[Payment date]]+Table5[[#This Row],[Delay in Payment ]],"") | AA29: =IF(Table5[[#This Row],[Payment date]]<>"",Table5[[#This Row],[Beginning balance]]-Table5[[#This Row],[Principal Payment]] - Table5[[#This Row],[Extra Payment]],"") | AB29: =IF(Table5[[#This Row],[Payment date]]<>"",Table5[[#This Row],[Draw Fee]]+Table5[[#This Row],[Interest]]+Table5[[#This Row],[Principal Payment]]+Table5[[#This Row],[Overdue Interest]],"")
... Q86: =IF($E$14="Mid of Month",(IF(EDATE(MIN(Table4[[#All],[Loan Date]]), ROW()-ROW($Q$6)) > EDATE(MAX(Table4[[#All],[Loan Payment End Date]]),1), "", (EOMONTH(EDATE(MIN(Table4[[#All],[Loan Date]]), ROW()-ROW($Q$6)),IF(DAY(EOMONTH(MIN(Table4[[#All],[Loan Date]]),0)) - DAY(MIN(Table4[[#All],[Loan Date]])) <= $E$15, 0, -1))+ 15))), IF($E$14="End of Month",(IF(EDATE(MIN(Table4[[#All],[Loan Date]]), ROW()-ROW($Q$6)) > MAX(Table4[[#All],[Loan Payment End Date]]), "", (EOMONTH(EDATE(MIN(Table4[[#All],[Loan Date]]), ROW()-ROW($Q$6)),IF(31 - DAY(MIN(Table4[[#All],[Loan Date]])) <= $E$15, 1, 0))))), IF($E$14="Start of Month",(IF(EDATE(MIN(Table4[[#All],[Loan Date]]), ROW()-ROW($Q$6)) > MAX(Table4[[#All],[Loan Payment End Date]]), "", (EOMONTH(EDATE(MIN(Table4[[#All],[Loan Date]]), ROW()-ROW($Q$6)),IF(31 - DAY(MIN(Table4[[#All],[Loan Date]])) <= $E$15, 1, 0))) + 1 ))) ) ) | R86: =IF(Table5[[#This Row],[Payment date]]<>"", SUMIFS(Table4[[#All],[Loan Amount]],Table4[[#All],[Loan Date]],"<="&Table5[[#This Row],[Payment date]]) - SUM($S$5:S85)- SUM($W$5:W85),"") | S86: =IF(Table5[[#This Row],[Payment date]]<>"",SUM('Individual Loan Schedule'!C89:HR89) - SUM('Early Payments'!D89:HS89),"") | T86: {=IF(Table5[[#This Row],[Payment date]]<>"",((SUMIFS(Table4[Loan Amount],Table4[Loan Payment Start Date],"<"&Table5[[#This Row],[Payment date]]) - SUM($S$5:$S85) - SUM($W$5:W85))*InterestRate*(Table5[[#This Row],[Payment date]] - IF($E$14="End of Month",EOMONTH(Table5[[#This Row],[Payment date]],-1), IF($E$14="Mid of Month",EOMONTH(Table5[[#This Row],[Payment date]],-2)+15, IF($E$14="Start of Month",EOMONTH(Table5[[#This Row],[Payment date]],-2) + 1))) )/360) + (SUM(IFERROR((IF(Table4[Loan Payment Start Date]=Table5[[#This Row],[Payment date]],Table4[Loan Amount],"")*(Table4[Loan Payment Start Date]-Table4[Loan Date])*InterestRate/360),0),0)),"")} | U86: =IF(Table5[[#This Row],[Payment date]]<>"",SUMIFS(Table4[[#All],[Loan Amount]],Table4[[#All],[Loan Payment Start Date]],"="&Table5[[#This Row],[Payment date]])*($E$7),"") | V86: {=IF(Table5[[#This Row],[Payment date]]<>"",IF(Table5[[#This Row],[Payment date]]=MIN(Table4[[#All],[Loan Payment Start Date]]),$E$8+$E$10*LoanAmount,0) + IF(Table5[[#This Row],[Payment date]] =MIN(_xlfn._xlws.FILTER(Table5[Payment date],(Table5[Payment date]>=EDATE(LoanStartDate,12*DATEDIF(LoanStartDate,Table5[[#This Row],[Payment date]],"y")))*(Table5[Beginning balance]<>0))), $E$9*LoanAmount,0),"")} | Y86: =IF(Table5[[#This Row],[Payment date]]<>"",(SUMIFS(Table4[Loan Amount],Table4[Loan Payment Start Date],"<="&Table5[[#This Row],[Payment date]]) - SUM($S$5:$S85) - - SUM($W$5:W85))*Table5[[#This Row],[Delay in Payment ]]*($E$16+ InterestRate)/365,"") | Z86: =IF(Table5[[#This Row],[Payment date]]<>"",Table5[[#This Row],[Payment date]]+Table5[[#This Row],[Delay in Payment ]],"") | AA86: =IF(Table5[[#This Row],[Payment date]]<>"",Table5[[#This Row],[Beginning balance]]-Table5[[#This Row],[Principal Payment]] - Table5[[#This Row],[Extra Payment]],"") | AB86: =IF(Table5[[#This Row],[Payment date]]<>"",Table5[[#This Row],[Draw Fee]]+Table5[[#This Row],[Interest]]+Table5[[#This Row],[Principal Payment]]+Table5[[#This Row],[Overdue Interest]],"")

Sheet Early Payments
C2: Loan # | D2: {=TRANSPOSE(Table4[Loan '#])} -> 1 | E2: 2 | F2: 3 | G2: 4
C3: Loan Amount | D3: {=TRANSPOSE(IFERROR(1/(1/Table4[Loan Amount]),""))} -> 30000 | E3: 20000 | F3: 50000 | G3: 15000
C4: Loan Start Date | D4: {=TRANSPOSE(Table4[Loan Payment Start Date])} -> 45352 | E4: 45383 | F4: 45413 | G4: 45627
C5: Loan End Date | D5: {=TRANSPOSE(Table4[Loan Payment End Date])} -> 45505 | E5: 45536 | F5: 45566 | G5: 45778
C6: Monthly Principal Repayment | D6: {=TRANSPOSE(Table4[Monthly Principal Repayment])} -> 5000 | E6: 3333.3333 | F6: 8333.3333 | G6: 2500
A8: Repayment Date | B8: Extra Repayment | D8: =IF(D2<>"", _xlfn.CONCAT("Loan #",D2," Repayment Schedule"),"") -> Loan #1 Repayment Schedule | E8: =IF(E2<>"", _xlfn.CONCAT("Loan #",E2," Repayment Schedule"),"") -> Loan #2 Repayment Schedule | F8: =IF(F2<>"", _xlfn.CONCAT("Loan #",F2," Repayment Schedule"),"") -> Loan #3 Repayment Schedule | G8: =IF(G2<>"", _xlfn.CONCAT("Loan #",G2," Repayment Schedule"),"") -> Loan #4 Repayment Schedule | H8: =IF(H2<>"", _xlfn.CONCAT("Loan #",H2," Repayment Schedule"),"") | I8: =IF(I2<>"", _xlfn.CONCAT("Loan #",I2," Repayment Schedule"),"") | J8: =IF(J2<>"", _xlfn.CONCAT("Loan #",J2," Repayment Schedule"),"") | K8: =IF(K2<>"", _xlfn.CONCAT("Loan #",K2," Repayment Schedule"),"") | ... HS8: =IF(HS2<>"", _xlfn.CONCAT("Loan #",HS2," Repayment Schedule"),"")
A9: {=Table5[Payment date]} -> 45352 | B9: =VLOOKUP(A9,Table5[],7,FALSE) -> 0 | D9: {=IF(AND(($A9<>"")*($A9>D$4)*($A9<=D$5)),IF(AND((SUMIFS($B$9:$B9,$A$9:$A9,"<"&$A9,$A$9:$A9,">="&D$4,$A$9:$A9,"<="&D$5)>SUM(_xlfn._xlws.FILTER(D10:D89,$A10:$A89>D$4),_xlfn._xlws.FILTER($C$9:C89,$A$9:$A89>D$4))),(SUMIFS($B$9:$B9,$A$9:$A9,"<"&$A9,$A$9:$A9,">="&D$4,$A$9:$A9,"<="&D$5)-SUM(_xlfn._xlws.FILTER(D10:D89,$A10:$A89>D$4),_xlfn._xlws.FILTER($C$9:C89,$A$9:$A89>D$4))>D$6)),D$6,MAX(0,SUMIFS($B$9:$B9,$A$9:$A9,"<"&$A9,$A$9:$A9,">="&D$4,$A$9:$A9,"<="&D$5)-SUM(_xlfn._xlws.FILTER(D10:D89,$A10:$A89>D$4),_xlfn._xlws.FILTER($C$9:C89,$A$9:$A89>D$4)))),"")} | E9: {=IF(AND(($A9<>"")*($A9>E$4)*($A9<=E$5)),IF(AND((SUMIFS($B$9:$B9,$A$9:$A9,"<"&$A9,$A$9:$A9,">="&E$4,$A$9:$A9,"<="&E$5)>SUM(_xlfn._xlws.FILTER(E10:E89,$A10:$A89>E$4),_xlfn._xlws.FILTER($C$9:D89,$A$9:$A89>E$4))),(SUMIFS($B$9:$B9,$A$9:$A9,"<"&$A9,$A$9:$A9,">="&E$4,$A$9:$A9,"<="&E$5)-SUM(_xlfn._xlws.FILTER(E10:E89,$A10:$A89>E$4),_xlfn._xlws.FILTER($C$9:D89,$A$9:$A89>E$4))>E$6)),E$6,MAX(0,SUMIFS($B$9:$B9,$A$9:$A9,"<"&$A9,$A$9:$A9,">="&E$4,$A$9:$A9,"<="&E$5)-SUM(_xlfn._xlws.FILTER(E10:E89,$A10:$A89>E$4),_xlfn._xlws.FILTER($C$9:D89,$A$9:$A89>E$4)))),"")} | F9: {=IF(AND(($A9<>"")*($A9>F$4)*($A9<=F$5)),IF(AND((SUMIFS($B$9:$B9,$A$9:$A9,"<"&$A9,$A$9:$A9,">="&F$4,$A$9:$A9,"<="&F$5)>SUM(_xlfn._xlws.FILTER(F10:F89,$A10:$A89>F$4),_xlfn._xlws.FILTER($C$9:E89,$A$9:$A89>F$4))),(SUMIFS($B$9:$B9,$A$9:$A9,"<"&$A9,$A$9:$A9,">="&F$4,$A$9:$A9,"<="&F$5)-SUM(_xlfn._xlws.FILTER(F10:F89,$A10:$A89>F$4),_xlfn._xlws.FILTER($C$9:E89,$A$9:$A89>F$4))>F$6)),F$6,MAX(0,SUMIFS($B$9:$B9,$A$9:$A9,"<"&$A9,$A$9:$A9,">="&F$4,$A$9:$A9,"<="&F$5)-SUM(_xlfn._xlws.FILTER(F10:F89,$A10:$A89>F$4),_xlfn._xlws.FILTER($C$9:E89,$A$9:$A89>F$4)))),"")} | G9: {=IF(AND(($A9<>"")*($A9>G$4)*($A9<=G$5)),IF(AND((SUMIFS($B$9:$B9,$A$9:$A9,"<"&$A9,$A$9:$A9,">="&G$4,$A$9:$A9,"<="&G$5)>SUM(_xlfn._xlws.FILTER(G10:G89,$A10:$A89>G$4),_xlfn._xlws.FILTER($C$9:F89,$A$9:$A89>G$4))),(SUMIFS($B$9:$B9,$A$9:$A9,"<"&$A9,$A$9:$A9,">="&G$4,$A$9:$A9,"<="&G$5)-SUM(_xlfn._xlws.FILTER(G10:G89,$A10:$A89>G$4),_xlfn._xlws.FILTER($C$9:F89,$A$9:$A89>G$4))>G$6)),G$6,MAX(0,SUMIFS($B$9:$B9,$A$9:$A9,"<"&$A9,$A$9:$A9,">="&G$4,$A$9:$A9,"<="&G$5)-SUM(_xlfn._xlws.FILTER(G10:G89,$A10:$A89>G$4),_xlfn._xlws.FILTER($C$9:F89,$A$9:$A89>G$4)))),"")} | H9: {=IF(AND(($A9<>"")*($A9>H$4)*($A9<=H$5)),IF(AND((SUMIFS($B$9:$B9,$A$9:$A9,"<"&$A9,$A$9:$A9,">="&H$4,$A$9:$A9,"<="&H$5)>SUM(_xlfn._xlws.FILTER(H10:H89,$A10:$A89>H$4),_xlfn._xlws.FILTER($C$9:G89,$A$9:$A89>H$4))),(SUMIFS($B$9:$B9,$A$9:$A9,"<"&$A9,$A$9:$A9,">="&H$4,$A$9:$A9,"<="&H$5)-SUM(_xlfn._xlws.FILTER(H10:H89,$A10:$A89>H$4),_xlfn._xlws.FILTER($C$9:G89,$A$9:$A89>H$4))>H$6)),H$6,MAX(0,SUMIFS($B$9:$B9,$A$9:$A9,"<"&$A9,$A$9:$A9,">="&H$4,$A$9:$A9,"<="&H$5)-SUM(_xlfn._xlws.FILTER(H10:H89,$A10:$A89>H$4),_xlfn._xlws.FILTER($C$9:G89,$A$9:$A89>H$4)))),"")} | I9: {=IF(AND(($A9<>"")*($A9>I$4)*($A9<=I$5)),IF(AND((SUMIFS($B$9:$B9,$A$9:$A9,"<"&$A9,$A$9:$A9,">="&I$4,$A$9:$A9,"<="&I$5)>SUM(_xlfn._xlws.FILTER(I10:I89,$A10:$A89>I$4),_xlfn._xlws.FILTER($C$9:H89,$A$9:$A89>I$4))),(SUMIFS($B$9:$B9,$A$9:$A9,"<"&$A9,$A$9:$A9,">="&I$4,$A$9:$A9,"<="&I$5)-SUM(_xlfn._xlws.FILTER(I10:I89,$A10:$A89>I$4),_xlfn._xlws.FILTER($C$9:H89,$A$9:$A89>I$4))>I$6)),I$6,MAX(0,SUMIFS($B$9:$B9,$A$9:$A9,"<"&$A9,$A$9:$A9,">="&I$4,$A$9:$A9,"<="&I$5)-SUM(_xlfn._xlws.FILTER(I10:I89,$A10:$A89>I$4),_xlfn._xlws.FILTER($C$9:H89,$A$9:$A89>I$4)))),"")} | J9: {=IF(AND(($A9<>"")*($A9>J$4)*($A9<=J$5)),IF(AND((SUMIFS($B$9:$B9,$A$9:$A9,"<"&$A9,$A$9:$A9,">="&J$4,$A$9:$A9,"<="&J$5)>SUM(_xlfn._xlws.FILTER(J10:J89,$A10:$A89>J$4),_xlfn._xlws.FILTER($C$9:I89,$A$9:$A89>J$4))),(SUMIFS($B$9:$B9,$A$9:$A9,"<"&$A9,$A$9:$A9,">="&J$4,$A$9:$A9,"<="&J$5)-SUM(_xlfn._xlws.FILTER(J10:J89,$A10:$A89>J$4),_xlfn._xlws.FILTER($C$9:I89,$A$9:$A89>J$4))>J$6)),J$6,MAX(0,SUMIFS($B$9:$B9,$A$9:$A9,"<"&$A9,$A$9:$A9,">="&J$4,$A$9:$A9,"<="&J$5)-SUM(_xlfn._xlws.FILTER(J10:J89,$A10:$A89>J$4),_xlfn._xlws.FILTER($C$9:I89,$A$9:$A89>J$4)))),"")} | K9: {=IF(AND(($A9<>"")*($A9>K$4)*($A9<=K$5)),IF(AND((SUMIFS($B$9:$B9,$A$9:$A9,"<"&$A9,$A$9:$A9,">="&K$4,$A$9:$A9,"<="&K$5)>SUM(_xlfn._xlws.FILTER(K10:K89,$A10:$A89>K$4),_xlfn._xlws.FILTER($C$9:J89,$A$9:$A89>K$4))),(SUMIFS($B$9:$B9,$A$9:$A9,"<"&$A9,$A$9:$A9,">="&K$4,$A$9:$A9,"<="&K$5)-SUM(_xlfn._xlws.FILTER(K10:K89,$A10:$A89>K$4),_xlfn._xlws.FILTER($C$9:J89,$A$9:$A89>K$4))>K$6)),K$6,MAX(0,SUMIFS($B$9:$B9,$A$9:$A9,"<"&$A9,$A$9:$A9,">="&K$4,$A$9:$A9,"<="&K$5)-SUM(_xlfn._xlws.FILTER(K10:K89,$A10:$A89>K$4),_xlfn._xlws.FILTER($C$9:J89,$A$9:$A89>K$4)))),"")} | ... HS9: {=IF(AND(($A9<>"")*($A9>HS$4)*($A9<=HS$5)),IF(AND((SUMIFS($B$9:$B9,$A$9:$A9,"<"&$A9,$A$9:$A9,">="&HS$4,$A$9:$A9,"<="&HS$5)>SUM(_xlfn._xlws.FILTER(HS10:HS89,$A10:$A89>HS$4),_xlfn._xlws.FILTER($C$9:HR89,$A$9:$A89>HS$4))),(SUMIFS($B$9:$B9,$A$9:$A9,"<"&$A9,$A$9:$A9,">="&HS$4,$A$9:$A9,"<="&HS$5)-SUM(_xlfn._xlws.FILTER(HS10:HS89,$A10:$A89>HS$4),_xlfn._xlws.FILTER($C$9:HR89,$A$9:$A89>HS$4))>HS$6)),HS$6,MAX(0,SUMIFS($B$9:$B9,$A$9:$A9,"<"&$A9,$A$9:$A9,">="&HS$4,$A$9:$A9,"<="&HS$5)-SUM(_xlfn._xlws.FILTER(HS10:HS89,$A10:$A89>HS$4),_xlfn._xlws.FILTER($C$9:HR89,$A$9:$A89>HS$4)))),"")}
A10: 45383 | B10: =VLOOKUP(A10,Table5[],7,FALSE) -> 0 | D10: {=IF(AND(($A10<>"")*($A10>D$4)*($A10<=D$5)),IF(AND((SUMIFS($B$9:$B10,$A$9:$A10,"<"&$A10,$A$9:$A10,">="&D$4,$A$9:$A10,"<="&D$5)>SUM(_xlfn._xlws.FILTER(D11:D90,$A11:$A90>D$4),_xlfn._xlws.FILTER($C$9:C90,$A$9:$A90>D$4))),(SUMIFS($B$9:$B10,$A$9:$A10,"<"&$A10,$A$9:$A10,">="&D$4,$A$9:$A10,"<="&D$5)-SUM(_xlfn._xlws.FILTER(D11:D90,$A11:$A90>D$4),_xlfn._xlws.FILTER($C$9:C90,$A$9:$A90>D$4))>D$6)),D$6,MAX(0,SUMIFS($B$9:$B10,$A$9:$A10,"<"&$A10,$A$9:$A10,">="&D$4,$A$9:$A10,"<="&D$5)-SUM(_xlfn._xlws.FILTER(D11:D90,$A11:$A90>D$4),_xlfn._xlws.FILTER($C$9:C90,$A$9:$A90>D$4)))),"")} -> 0 | E10: {=IF(AND(($A10<>"")*($A10>E$4)*($A10<=E$5)),IF(AND((SUMIFS($B$9:$B10,$A$9:$A10,"<"&$A10,$A$9:$A10,">="&E$4,$A$9:$A10,"<="&E$5)>SUM(_xlfn._xlws.FILTER(E11:E90,$A11:$A90>E$4),_xlfn._xlws.FILTER($C$9:D90,$A$9:$A90>E$4))),(SUMIFS($B$9:$B10,$A$9:$A10,"<"&$A10,$A$9:$A10,">="&E$4,$A$9:$A10,"<="&E$5)-SUM(_xlfn._xlws.FILTER(E11:E90,$A11:$A90>E$4),_xlfn._xlws.FILTER($C$9:D90,$A$9:$A90>E$4))>E$6)),E$6,MAX(0,SUMIFS($B$9:$B10,$A$9:$A10,"<"&$A10,$A$9:$A10,">="&E$4,$A$9:$A10,"<="&E$5)-SUM(_xlfn._xlws.FILTER(E11:E90,$A11:$A90>E$4),_xlfn._xlws.FILTER($C$9:D90,$A$9:$A90>E$4)))),"")} | F10: {=IF(AND(($A10<>"")*($A10>F$4)*($A10<=F$5)),IF(AND((SUMIFS($B$9:$B10,$A$9:$A10,"<"&$A10,$A$9:$A10,">="&F$4,$A$9:$A10,"<="&F$5)>SUM(_xlfn._xlws.FILTER(F11:F90,$A11:$A90>F$4),_xlfn._xlws.FILTER($C$9:E90,$A$9:$A90>F$4))),(SUMIFS($B$9:$B10,$A$9:$A10,"<"&$A10,$A$9:$A10,">="&F$4,$A$9:$A10,"<="&F$5)-SUM(_xlfn._xlws.FILTER(F11:F90,$A11:$A90>F$4),_xlfn._xlws.FILTER($C$9:E90,$A$9:$A90>F$4))>F$6)),F$6,MAX(0,SUMIFS($B$9:$B10,$A$9:$A10,"<"&$A10,$A$9:$A10,">="&F$4,$A$9:$A10,"<="&F$5)-SUM(_xlfn._xlws.FILTER(F11:F90,$A11:$A90>F$4),_xlfn._xlws.FILTER($C$9:E90,$A$9:$A90>F$4)))),"")} | G10: {=IF(AND(($A10<>"")*($A10>G$4)*($A10<=G$5)),IF(AND((SUMIFS($B$9:$B10,$A$9:$A10,"<"&$A10,$A$9:$A10,">="&G$4,$A$9:$A10,"<="&G$5)>SUM(_xlfn._xlws.FILTER(G11:G90,$A11:$A90>G$4),_xlfn._xlws.FILTER($C$9:F90,$A$9:$A90>G$4))),(SUMIFS($B$9:$B10,$A$9:$A10,"<"&$A10,$A$9:$A10,">="&G$4,$A$9:$A10,"<="&G$5)-SUM(_xlfn._xlws.FILTER(G11:G90,$A11:$A90>G$4),_xlfn._xlws.FILTER($C$9:F90,$A$9:$A90>G$4))>G$6)),G$6,MAX(0,SUMIFS($B$9:$B10,$A$9:$A10,"<"&$A10,$A$9:$A10,">="&G$4,$A$9:$A10,"<="&G$5)-SUM(_xlfn._xlws.FILTER(G11:G90,$A11:$A90>G$4),_xlfn._xlws.FILTER($C$9:F90,$A$9:$A90>G$4)))),"")} | H10: {=IF(AND(($A10<>"")*($A10>H$4)*($A10<=H$5)),IF(AND((SUMIFS($B$9:$B10,$A$9:$A10,"<"&$A10,$A$9:$A10,">="&H$4,$A$9:$A10,"<="&H$5)>SUM(_xlfn._xlws.FILTER(H11:H90,$A11:$A90>H$4),_xlfn._xlws.FILTER($C$9:G90,$A$9:$A90>H$4))),(SUMIFS($B$9:$B10,$A$9:$A10,"<"&$A10,$A$9:$A10,">="&H$4,$A$9:$A10,"<="&H$5)-SUM(_xlfn._xlws.FILTER(H11:H90,$A11:$A90>H$4),_xlfn._xlws.FILTER($C$9:G90,$A$9:$A90>H$4))>H$6)),H$6,MAX(0,SUMIFS($B$9:$B10,$A$9:$A10,"<"&$A10,$A$9:$A10,">="&H$4,$A$9:$A10,"<="&H$5)-SUM(_xlfn._xlws.FILTER(H11:H90,$A11:$A90>H$4),_xlfn._xlws.FILTER($C$9:G90,$A$9:$A90>H$4)))),"")} | I10: {=IF(AND(($A10<>"")*($A10>I$4)*($A10<=I$5)),IF(AND((SUMIFS($B$9:$B10,$A$9:$A10,"<"&$A10,$A$9:$A10,">="&I$4,$A$9:$A10,"<="&I$5)>SUM(_xlfn._xlws.FILTER(I11:I90,$A11:$A90>I$4),_xlfn._xlws.FILTER($C$9:H90,$A$9:$A90>I$4))),(SUMIFS($B$9:$B10,$A$9:$A10,"<"&$A10,$A$9:$A10,">="&I$4,$A$9:$A10,"<="&I$5)-SUM(_xlfn._xlws.FILTER(I11:I90,$A11:$A90>I$4),_xlfn._xlws.FILTER($C$9:H90,$A$9:$A90>I$4))>I$6)),I$6,MAX(0,SUMIFS($B$9:$B10,$A$9:$A10,"<"&$A10,$A$9:$A10,">="&I$4,$A$9:$A10,"<="&I$5)-SUM(_xlfn._xlws.FILTER(I11:I90,$A11:$A90>I$4),_xlfn._xlws.FILTER($C$9:H90,$A$9:$A90>I$4)))),"")} | J10: {=IF(AND(($A10<>"")*($A10>J$4)*($A10<=J$5)),IF(AND((SUMIFS($B$9:$B10,$A$9:$A10,"<"&$A10,$A$9:$A10,">="&J$4,$A$9:$A10,"<="&J$5)>SUM(_xlfn._xlws.FILTER(J11:J90,$A11:$A90>J$4),_xlfn._xlws.FILTER($C$9:I90,$A$9:$A90>J$4))),(SUMIFS($B$9:$B10,$A$9:$A10,"<"&$A10,$A$9:$A10,">="&J$4,$A$9:$A10,"<="&J$5)-SUM(_xlfn._xlws.FILTER(J11:J90,$A11:$A90>J$4),_xlfn._xlws.FILTER($C$9:I90,$A$9:$A90>J$4))>J$6)),J$6,MAX(0,SUMIFS($B$9:$B10,$A$9:$A10,"<"&$A10,$A$9:$A10,">="&J$4,$A$9:$A10,"<="&J$5)-SUM(_xlfn._xlws.FILTER(J11:J90,$A11:$A90>J$4),_xlfn._xlws.FILTER($C$9:I90,$A$9:$A90>J$4)))),"")} | K10: {=IF(AND(($A10<>"")*($A10>K$4)*($A10<=K$5)),IF(AND((SUMIFS($B$9:$B10,$A$9:$A10,"<"&$A10,$A$9:$A10,">="&K$4,$A$9:$A10,"<="&K$5)>SUM(_xlfn._xlws.FILTER(K11:K90,$A11:$A90>K$4),_xlfn._xlws.FILTER($C$9:J90,$A$9:$A90>K$4))),(SUMIFS($B$9:$B10,$A$9:$A10,"<"&$A10,$A$9:$A10,">="&K$4,$A$9:$A10,"<="&K$5)-SUM(_xlfn._xlws.FILTER(K11:K90,$A11:$A90>K$4),_xlfn._xlws.FILTER($C$9:J90,$A$9:$A90>K$4))>K$6)),K$6,MAX(0,SUMIFS($B$9:$B10,$A$9:$A10,"<"&$A10,$A$9:$A10,">="&K$4,$A$9:$A10,"<="&K$5)-SUM(_xlfn._xlws.FILTER(K11:K90,$A11:$A90>K$4),_xlfn._xlws.FILTER($C$9:J90,$A$9:$A90>K$4)))),"")} | ... HS10: {=IF(AND(($A10<>"")*($A10>HS$4)*($A10<=HS$5)),IF(AND((SUMIFS($B$9:$B10,$A$9:$A10,"<"&$A10,$A$9:$A10,">="&HS$4,$A$9:$A10,"<="&HS$5)>SUM(_xlfn._xlws.FILTER(HS11:HS90,$A11:$A90>HS$4),_xlfn._xlws.FILTER($C$9:HR90,$A$9:$A90>HS$4))),(SUMIFS($B$9:$B10,$A$9:$A10,"<"&$A10,$A$9:$A10,">="&HS$4,$A$9:$A10,"<="&HS$5)-SUM(_xlfn._xlws.FILTER(HS11:HS90,$A11:$A90>HS$4),_xlfn._xlws.FILTER($C$9:HR90,$A$9:$A90>HS$4))>HS$6)),HS$6,MAX(0,SUMIFS($B$9:$B10,$A$9:$A10,"<"&$A10,$A$9:$A10,">="&HS$4,$A$9:$A10,"<="&HS$5)-SUM(_xlfn._xlws.FILTER(HS11:HS90,$A11:$A90>HS$4),_xlfn._xlws.FILTER($C$9:HR90,$A$9:$A90>HS$4)))),"")}
A11: 45413 | B11: =VLOOKUP(A11,Table5[],7,FALSE) -> 17000 | D11: {=IF(AND(($A11<>"")*($A11>D$4)*($A11<=D$5)),IF(AND((SUMIFS($B$9:$B11,$A$9:$A11,"<"&$A11,$A$9:$A11,">="&D$4,$A$9:$A11,"<="&D$5)>SUM(_xlfn._xlws.FILTER(D12:D91,$A12:$A91>D$4),_xlfn._xlws.FILTER($C$9:C91,$A$9:$A91>D$4))),(SUMIFS($B$9:$B11,$A$9:$A11,"<"&$A11,$A$9:$A11,">="&D$4,$A$9:$A11,"<="&D$5)-SUM(_xlfn._xlws.FILTER(D12:D91,$A12:$A91>D$4),_xlfn._xlws.FILTER($C$9:C91,$A$9:$A91>D$4))>D$6)),D$6,MAX(0,SUMIFS($B$9:$B11,$A$9:$A11,"<"&$A11,$A$9:$A11,">="&D$4,$A$9:$A11,"<="&D$5)-SUM(_xlfn._xlws.FILTER(D12:D91,$A12:$A91>D$4),_xlfn._xlws.FILTER($C$9:C91,$A$9:$A91>D$4)))),"")} -> 0 | E11: {=IF(AND(($A11<>"")*($A11>E$4)*($A11<=E$5)),IF(AND((SUMIFS($B$9:$B11,$A$9:$A11,"<"&$A11,$A$9:$A11,">="&E$4,$A$9:$A11,"<="&E$5)>SUM(_xlfn._xlws.FILTER(E12:E91,$A12:$A91>E$4),_xlfn._xlws.FILTER($C$9:D91,$A$9:$A91>E$4))),(SUMIFS($B$9:$B11,$A$9:$A11,"<"&$A11,$A$9:$A11,">="&E$4,$A$9:$A11,"<="&E$5)-SUM(_xlfn._xlws.FILTER(E12:E91,$A12:$A91>E$4),_xlfn._xlws.FILTER($C$9:D91,$A$9:$A91>E$4))>E$6)),E$6,MAX(0,SUMIFS($B$9:$B11,$A$9:$A11,"<"&$A11,$A$9:$A11,">="&E$4,$A$9:$A11,"<="&E$5)-SUM(_xlfn._xlws.FILTER(E12:E91,$A12:$A91>E$4),_xlfn._xlws.FILTER($C$9:D91,$A$9:$A91>E$4)))),"")} -> 0 | F11: {=IF(AND(($A11<>"")*($A11>F$4)*($A11<=F$5)),IF(AND((SUMIFS($B$9:$B11,$A$9:$A11,"<"&$A11,$A$9:$A11,">="&F$4,$A$9:$A11,"<="&F$5)>SUM(_xlfn._xlws.FILTER(F12:F91,$A12:$A91>F$4),_xlfn._xlws.FILTER($C$9:E91,$A$9:$A91>F$4))),(SUMIFS($B$9:$B11,$A$9:$A11,"<"&$A11,$A$9:$A11,">="&F$4,$A$9:$A11,"<="&F$5)-SUM(_xlfn._xlws.FILTER(F12:F91,$A12:$A91>F$4),_xlfn._xlws.FILTER($C$9:E91,$A$9:$A91>F$4))>F$6)),F$6,MAX(0,SUMIFS($B$9:$B11,$A$9:$A11,"<"&$A11,$A$9:$A11,">="&F$4,$A$9:$A11,"<="&F$5)-SUM(_xlfn._xlws.FILTER(F12:F91,$A12:$A91>F$4),_xlfn._xlws.FILTER($C$9:E91,$A$9:$A91>F$4)))),"")} | G11: {=IF(AND(($A11<>"")*($A11>G$4)*($A11<=G$5)),IF(AND((SUMIFS($B$9:$B11,$A$9:$A11,"<"&$A11,$A$9:$A11,">="&G$4,$A$9:$A11,"<="&G$5)>SUM(_xlfn._xlws.FILTER(G12:G91,$A12:$A91>G$4),_xlfn._xlws.FILTER($C$9:F91,$A$9:$A91>G$4))),(SUMIFS($B$9:$B11,$A$9:$A11,"<"&$A11,$A$9:$A11,">="&G$4,$A$9:$A11,"<="&G$5)-SUM(_xlfn._xlws.FILTER(G12:G91,$A12:$A91>G$4),_xlfn._xlws.FILTER($C$9:F91,$A$9:$A91>G$4))>G$6)),G$6,MAX(0,SUMIFS($B$9:$B11,$A$9:$A11,"<"&$A11,$A$9:$A11,">="&G$4,$A$9:$A11,"<="&G$5)-SUM(_xlfn._xlws.FILTER(G12:G91,$A12:$A91>G$4),_xlfn._xlws.FILTER($C$9:F91,$A$9:$A91>G$4)))),"")} | H11: {=IF(AND(($A11<>"")*($A11>H$4)*($A11<=H$5)),IF(AND((SUMIFS($B$9:$B11,$A$9:$A11,"<"&$A11,$A$9:$A11,">="&H$4,$A$9:$A11,"<="&H$5)>SUM(_xlfn._xlws.FILTER(H12:H91,$A12:$A91>H$4),_xlfn._xlws.FILTER($C$9:G91,$A$9:$A91>H$4))),(SUMIFS($B$9:$B11,$A$9:$A11,"<"&$A11,$A$9:$A11,">="&H$4,$A$9:$A11,"<="&H$5)-SUM(_xlfn._xlws.FILTER(H12:H91,$A12:$A91>H$4),_xlfn._xlws.FILTER($C$9:G91,$A$9:$A91>H$4))>H$6)),H$6,MAX(0,SUMIFS($B$9:$B11,$A$9:$A11,"<"&$A11,$A$9:$A11,">="&H$4,$A$9:$A11,"<="&H$5)-SUM(_xlfn._xlws.FILTER(H12:H91,$A12:$A91>H$4),_xlfn._xlws.FILTER($C$9:G91,$A$9:$A91>H$4)))),"")} | I11: {=IF(AND(($A11<>"")*($A11>I$4)*($A11<=I$5)),IF(AND((SUMIFS($B$9:$B11,$A$9:$A11,"<"&$A11,$A$9:$A11,">="&I$4,$A$9:$A11,"<="&I$5)>SUM(_xlfn._xlws.FILTER(I12:I91,$A12:$A91>I$4),_xlfn._xlws.FILTER($C$9:H91,$A$9:$A91>I$4))),(SUMIFS($B$9:$B11,$A$9:$A11,"<"&$A11,$A$9:$A11,">="&I$4,$A$9:$A11,"<="&I$5)-SUM(_xlfn._xlws.FILTER(I12:I91,$A12:$A91>I$4),_xlfn._xlws.FILTER($C$9:H91,$A$9:$A91>I$4))>I$6)),I$6,MAX(0,SUMIFS($B$9:$B11,$A$9:$A11,"<"&$A11,$A$9:$A11,">="&I$4,$A$9:$A11,"<="&I$5)-SUM(_xlfn._xlws.FILTER(I12:I91,$A12:$A91>I$4),_xlfn._xlws.FILTER($C$9:H91,$A$9:$A91>I$4)))),"")} | J11: {=IF(AND(($A11<>"")*($A11>J$4)*($A11<=J$5)),IF(AND((SUMIFS($B$9:$B11,$A$9:$A11,"<"&$A11,$A$9:$A11,">="&J$4,$A$9:$A11,"<="&J$5)>SUM(_xlfn._xlws.FILTER(J12:J91,$A12:$A91>J$4),_xlfn._xlws.FILTER($C$9:I91,$A$9:$A91>J$4))),(SUMIFS($B$9:$B11,$A$9:$A11,"<"&$A11,$A$9:$A11,">="&J$4,$A$9:$A11,"<="&J$5)-SUM(_xlfn._xlws.FILTER(J12:J91,$A12:$A91>J$4),_xlfn._xlws.FILTER($C$9:I91,$A$9:$A91>J$4))>J$6)),J$6,MAX(0,SUMIFS($B$9:$B11,$A$9:$A11,"<"&$A11,$A$9:$A11,">="&J$4,$A$9:$A11,"<="&J$5)-SUM(_xlfn._xlws.FILTER(J12:J91,$A12:$A91>J$4),_xlfn._xlws.FILTER($C$9:I91,$A$9:$A91>J$4)))),"")} | K11: {=IF(AND(($A11<>"")*($A11>K$4)*($A11<=K$5)),IF(AND((SUMIFS($B$9:$B11,$A$9:$A11,"<"&$A11,$A$9:$A11,">="&K$4,$A$9:$A11,"<="&K$5)>SUM(_xlfn._xlws.FILTER(K12:K91,$A12:$A91>K$4),_xlfn._xlws.FILTER($C$9:J91,$A$9:$A91>K$4))),(SUMIFS($B$9:$B11,$A$9:$A11,"<"&$A11,$A$9:$A11,">="&K$4,$A$9:$A11,"<="&K$5)-SUM(_xlfn._xlws.FILTER(K12:K91,$A12:$A91>K$4),_xlfn._xlws.FILTER($C$9:J91,$A$9:$A91>K$4))>K$6)),K$6,MAX(0,SUMIFS($B$9:$B11,$A$9:$A11,"<"&$A11,$A$9:$A11,">="&K$4,$A$9:$A11,"<="&K$5)-SUM(_xlfn._xlws.FILTER(K12:K91,$A12:$A91>K$4),_xlfn._xlws.FILTER($C$9:J91,$A$9:$A91>K$4)))),"")} | ... HS11: {=IF(AND(($A11<>"")*($A11>HS$4)*($A11<=HS$5)),IF(AND((SUMIFS($B$9:$B11,$A$9:$A11,"<"&$A11,$A$9:$A11,">="&HS$4,$A$9:$A11,"<="&HS$5)>SUM(_xlfn._xlws.FILTER(HS12:HS91,$A12:$A91>HS$4),_xlfn._xlws.FILTER($C$9:HR91,$A$9:$A91>HS$4))),(SUMIFS($B$9:$B11,$A$9:$A11,"<"&$A11,$A$9:$A11,">="&HS$4,$A$9:$A11,"<="&HS$5)-SUM(_xlfn._xlws.FILTER(HS12:HS91,$A12:$A91>HS$4),_xlfn._xlws.FILTER($C$9:HR91,$A$9:$A91>HS$4))>HS$6)),HS$6,MAX(0,SUMIFS($B$9:$B11,$A$9:$A11,"<"&$A11,$A$9:$A11,">="&HS$4,$A$9:$A11,"<="&HS$5)-SUM(_xlfn._xlws.FILTER(HS12:HS91,$A12:$A91>HS$4),_xlfn._xlws.FILTER($C$9:HR91,$A$9:$A91>HS$4)))),"")}
A12: 45444 | B12: =VLOOKUP(A12,Table5[],7,FALSE) -> 0 | D12: {=IF(AND(($A12<>"")*($A12>D$4)*($A12<=D$5)),IF(AND((SUMIFS($B$9:$B12,$A$9:$A12,"<"&$A12,$A$9:$A12,">="&D$4,$A$9:$A12,"<="&D$5)>SUM(_xlfn._xlws.FILTER(D13:D92,$A13:$A92>D$4),_xlfn._xlws.FILTER($C$9:C92,$A$9:$A92>D$4))),(SUMIFS($B$9:$B12,$A$9:$A12,"<"&$A12,$A$9:$A12,">="&D$4,$A$9:$A12,"<="&D$5)-SUM(_xlfn._xlws.FILTER(D13:D92,$A13:$A92>D$4),_xlfn._xlws.FILTER($C$9:C92,$A$9:$A92>D$4))>D$6)),D$6,MAX(0,SUMIFS($B$9:$B12,$A$9:$A12,"<"&$A12,$A$9:$A12,">="&D$4,$A$9:$A12,"<="&D$5)-SUM(_xlfn._xlws.FILTER(D13:D92,$A13:$A92>D$4),_xlfn._xlws.FILTER($C$9:C92,$A$9:$A92>D$4)))),"")} -> 5000 | E12: {=IF(AND(($A12<>"")*($A12>E$4)*($A12<=E$5)),IF(AND((SUMIFS($B$9:$B12,$A$9:$A12,"<"&$A12,$A$9:$A12,">="&E$4,$A$9:$A12,"<="&E$5)>SUM(_xlfn._xlws.FILTER(E13:E92,$A13:$A92>E$4),_xlfn._xlws.FILTER($C$9:D92,$A$9:$A92>E$4))),(SUMIFS($B$9:$B12,$A$9:$A12,"<"&$A12,$A$9:$A12,">="&E$4,$A$9:$A12,"<="&E$5)-SUM(_xlfn._xlws.FILTER(E13:E92,$A13:$A92>E$4),_xlfn._xlws.FILTER($C$9:D92,$A$9:$A92>E$4))>E$6)),E$6,MAX(0,SUMIFS($B$9:$B12,$A$9:$A12,"<"&$A12,$A$9:$A12,">="&E$4,$A$9:$A12,"<="&E$5)-SUM(_xlfn._xlws.FILTER(E13:E92,$A13:$A92>E$4),_xlfn._xlws.FILTER($C$9:D92,$A$9:$A92>E$4)))),"")} -> 0 | F12: {=IF(AND(($A12<>"")*($A12>F$4)*($A12<=F$5)),IF(AND((SUMIFS($B$9:$B12,$A$9:$A12,"<"&$A12,$A$9:$A12,">="&F$4,$A$9:$A12,"<="&F$5)>SUM(_xlfn._xlws.FILTER(F13:F92,$A13:$A92>F$4),_xlfn._xlws.FILTER($C$9:E92,$A$9:$A92>F$4))),(SUMIFS($B$9:$B12,$A$9:$A12,"<"&$A12,$A$9:$A12,">="&F$4,$A$9:$A12,"<="&F$5)-SUM(_xlfn._xlws.FILTER(F13:F92,$A13:$A92>F$4),_xlfn._xlws.FILTER($C$9:E92,$A$9:$A92>F$4))>F$6)),F$6,MAX(0,SUMIFS($B$9:$B12,$A$9:$A12,"<"&$A12,$A$9:$A12,">="&F$4,$A$9:$A12,"<="&F$5)-SUM(_xlfn._xlws.FILTER(F13:F92,$A13:$A92>F$4),_xlfn._xlws.FILTER($C$9:E92,$A$9:$A92>F$4)))),"")} -> 0 | G12: {=IF(AND(($A12<>"")*($A12>G$4)*($A12<=G$5)),IF(AND((SUMIFS($B$9:$B12,$A$9:$A12,"<"&$A12,$A$9:$A12,">="&G$4,$A$9:$A12,"<="&G$5)>SUM(_xlfn._xlws.FILTER(G13:G92,$A13:$A92>G$4),_xlfn._xlws.FILTER($C$9:F92,$A$9:$A92>G$4))),(SUMIFS($B$9:$B12,$A$9:$A12,"<"&$A12,$A$9:$A12,">="&G$4,$A$9:$A12,"<="&G$5)-SUM(_xlfn._xlws.FILTER(G13:G92,$A13:$A92>G$4),_xlfn._xlws.FILTER($C$9:F92,$A$9:$A92>G$4))>G$6)),G$6,MAX(0,SUMIFS($B$9:$B12,$A$9:$A12,"<"&$A12,$A$9:$A12,">="&G$4,$A$9:$A12,"<="&G$5)-SUM(_xlfn._xlws.FILTER(G13:G92,$A13:$A92>G$4),_xlfn._xlws.FILTER($C$9:F92,$A$9:$A92>G$4)))),"")} | H12: {=IF(AND(($A12<>"")*($A12>H$4)*($A12<=H$5)),IF(AND((SUMIFS($B$9:$B12,$A$9:$A12,"<"&$A12,$A$9:$A12,">="&H$4,$A$9:$A12,"<="&H$5)>SUM(_xlfn._xlws.FILTER(H13:H92,$A13:$A92>H$4),_xlfn._xlws.FILTER($C$9:G92,$A$9:$A92>H$4))),(SUMIFS($B$9:$B12,$A$9:$A12,"<"&$A12,$A$9:$A12,">="&H$4,$A$9:$A12,"<="&H$5)-SUM(_xlfn._xlws.FILTER(H13:H92,$A13:$A92>H$4),_xlfn._xlws.FILTER($C$9:G92,$A$9:$A92>H$4))>H$6)),H$6,MAX(0,SUMIFS($B$9:$B12,$A$9:$A12,"<"&$A12,$A$9:$A12,">="&H$4,$A$9:$A12,"<="&H$5)-SUM(_xlfn._xlws.FILTER(H13:H92,$A13:$A92>H$4),_xlfn._xlws.FILTER($C$9:G92,$A$9:$A92>H$4)))),"")} | I12: {=IF(AND(($A12<>"")*($A12>I$4)*($A12<=I$5)),IF(AND((SUMIFS($B$9:$B12,$A$9:$A12,"<"&$A12,$A$9:$A12,">="&I$4,$A$9:$A12,"<="&I$5)>SUM(_xlfn._xlws.FILTER(I13:I92,$A13:$A92>I$4),_xlfn._xlws.FILTER($C$9:H92,$A$9:$A92>I$4))),(SUMIFS($B$9:$B12,$A$9:$A12,"<"&$A12,$A$9:$A12,">="&I$4,$A$9:$A12,"<="&I$5)-SUM(_xlfn._xlws.FILTER(I13:I92,$A13:$A92>I$4),_xlfn._xlws.FILTER($C$9:H92,$A$9:$A92>I$4))>I$6)),I$6,MAX(0,SUMIFS($B$9:$B12,$A$9:$A12,"<"&$A12,$A$9:$A12,">="&I$4,$A$9:$A12,"<="&I$5)-SUM(_xlfn._xlws.FILTER(I13:I92,$A13:$A92>I$4),_xlfn._xlws.FILTER($C$9:H92,$A$9:$A92>I$4)))),"")} | J12: {=IF(AND(($A12<>"")*($A12>J$4)*($A12<=J$5)),IF(AND((SUMIFS($B$9:$B12,$A$9:$A12,"<"&$A12,$A$9:$A12,">="&J$4,$A$9:$A12,"<="&J$5)>SUM(_xlfn._xlws.FILTER(J13:J92,$A13:$A92>J$4),_xlfn._xlws.FILTER($C$9:I92,$A$9:$A92>J$4))),(SUMIFS($B$9:$B12,$A$9:$A12,"<"&$A12,$A$9:$A12,">="&J$4,$A$9:$A12,"<="&J$5)-SUM(_xlfn._xlws.FILTER(J13:J92,$A13:$A92>J$4),_xlfn._xlws.FILTER($C$9:I92,$A$9:$A92>J$4))>J$6)),J$6,MAX(0,SUMIFS($B$9:$B12,$A$9:$A12,"<"&$A12,$A$9:$A12,">="&J$4,$A$9:$A12,"<="&J$5)-SUM(_xlfn._xlws.FILTER(J13:J92,$A13:$A92>J$4),_xlfn._xlws.FILTER($C$9:I92,$A$9:$A92>J$4)))),"")} | K12: {=IF(AND(($A12<>"")*($A12>K$4)*($A12<=K$5)),IF(AND((SUMIFS($B$9:$B12,$A$9:$A12,"<"&$A12,$A$9:$A12,">="&K$4,$A$9:$A12,"<="&K$5)>SUM(_xlfn._xlws.FILTER(K13:K92,$A13:$A92>K$4),_xlfn._xlws.FILTER($C$9:J92,$A$9:$A92>K$4))),(SUMIFS($B$9:$B12,$A$9:$A12,"<"&$A12,$A$9:$A12,">="&K$4,$A$9:$A12,"<="&K$5)-SUM(_xlfn._xlws.FILTER(K13:K92,$A13:$A92>K$4),_xlfn._xlws.FILTER($C$9:J92,$A$9:$A92>K$4))>K$6)),K$6,MAX(0,SUMIFS($B$9:$B12,$A$9:$A12,"<"&$A12,$A$9:$A12,">="&K$4,$A$9:$A12,"<="&K$5)-SUM(_xlfn._xlws.FILTER(K13:K92,$A13:$A92>K$4),_xlfn._xlws.FILTER($C$9:J92,$A$9:$A92>K$4)))),"")} | ... HS12: {=IF(AND(($A12<>"")*($A12>HS$4)*($A12<=HS$5)),IF(AND((SUMIFS($B$9:$B12,$A$9:$A12,"<"&$A12,$A$9:$A12,">="&HS$4,$A$9:$A12,"<="&HS$5)>SUM(_xlfn._xlws.FILTER(HS13:HS92,$A13:$A92>HS$4),_xlfn._xlws.FILTER($C$9:HR92,$A$9:$A92>HS$4))),(SUMIFS($B$9:$B12,$A$9:$A12,"<"&$A12,$A$9:$A12,">="&HS$4,$A$9:$A12,"<="&HS$5)-SUM(_xlfn._xlws.FILTER(HS13:HS92,$A13:$A92>HS$4),_xlfn._xlws.FILTER($C$9:HR92,$A$9:$A92>HS$4))>HS$6)),HS$6,MAX(0,SUMIFS($B$9:$B12,$A$9:$A12,"<"&$A12,$A$9:$A12,">="&HS$4,$A$9:$A12,"<="&HS$5)-SUM(_xlfn._xlws.FILTER(HS13:HS92,$A13:$A92>HS$4),_xlfn._xlws.FILTER($C$9:HR92,$A$9:$A92>HS$4)))),"")}
A13: 45474 | B13: =VLOOKUP(A13,Table5[],7,FALSE) -> 0 | D13: {=IF(AND(($A13<>"")*($A13>D$4)*($A13<=D$5)),IF(AND((SUMIFS($B$9:$B13,$A$9:$A13,"<"&$A13,$A$9:$A13,">="&D$4,$A$9:$A13,"<="&D$5)>SUM(_xlfn._xlws.FILTER(D14:D93,$A14:$A93>D$4),_xlfn._xlws.FILTER($C$9:C93,$A$9:$A93>D$4))),(SUMIFS($B$9:$B13,$A$9:$A13,"<"&$A13,$A$9:$A13,">="&D$4,$A$9:$A13,"<="&D$5)-SUM(_xlfn._xlws.FILTER(D14:D93,$A14:$A93>D$4),_xlfn._xlws.FILTER($C$9:C93,$A$9:$A93>D$4))>D$6)),D$6,MAX(0,SUMIFS($B$9:$B13,$A$9:$A13,"<"&$A13,$A$9:$A13,">="&D$4,$A$9:$A13,"<="&D$5)-SUM(_xlfn._xlws.FILTER(D14:D93,$A14:$A93>D$4),_xlfn._xlws.FILTER($C$9:C93,$A$9:$A93>D$4)))),"")} -> 5000 | E13: {=IF(AND(($A13<>"")*($A13>E$4)*($A13<=E$5)),IF(AND((SUMIFS($B$9:$B13,$A$9:$A13,"<"&$A13,$A$9:$A13,">="&E$4,$A$9:$A13,"<="&E$5)>SUM(_xlfn._xlws.FILTER(E14:E93,$A14:$A93>E$4),_xlfn._xlws.FILTER($C$9:D93,$A$9:$A93>E$4))),(SUMIFS($B$9:$B13,$A$9:$A13,"<"&$A13,$A$9:$A13,">="&E$4,$A$9:$A13,"<="&E$5)-SUM(_xlfn._xlws.FILTER(E14:E93,$A14:$A93>E$4),_xlfn._xlws.FILTER($C$9:D93,$A$9:$A93>E$4))>E$6)),E$6,MAX(0,SUMIFS($B$9:$B13,$A$9:$A13,"<"&$A13,$A$9:$A13,">="&E$4,$A$9:$A13,"<="&E$5)-SUM(_xlfn._xlws.FILTER(E14:E93,$A14:$A93>E$4),_xlfn._xlws.FILTER($C$9:D93,$A$9:$A93>E$4)))),"")} -> 0 | F13: {=IF(AND(($A13<>"")*($A13>F$4)*($A13<=F$5)),IF(AND((SUMIFS($B$9:$B13,$A$9:$A13,"<"&$A13,$A$9:$A13,">="&F$4,$A$9:$A13,"<="&F$5)>SUM(_xlfn._xlws.FILTER(F14:F93,$A14:$A93>F$4),_xlfn._xlws.FILTER($C$9:E93,$A$9:$A93>F$4))),(SUMIFS($B$9:$B13,$A$9:$A13,"<"&$A13,$A$9:$A13,">="&F$4,$A$9:$A13,"<="&F$5)-SUM(_xlfn._xlws.FILTER(F14:F93,$A14:$A93>F$4),_xlfn._xlws.FILTER($C$9:E93,$A$9:$A93>F$4))>F$6)),F$6,MAX(0,SUMIFS($B$9:$B13,$A$9:$A13,"<"&$A13,$A$9:$A13,">="&F$4,$A$9:$A13,"<="&F$5)-SUM(_xlfn._xlws.FILTER(F14:F93,$A14:$A93>F$4),_xlfn._xlws.FILTER($C$9:E93,$A$9:$A93>F$4)))),"")} -> 0 | G13: {=IF(AND(($A13<>"")*($A13>G$4)*($A13<=G$5)),IF(AND((SUMIFS($B$9:$B13,$A$9:$A13,"<"&$A13,$A$9:$A13,">="&G$4,$A$9:$A13,"<="&G$5)>SUM(_xlfn._xlws.FILTER(G14:G93,$A14:$A93>G$4),_xlfn._xlws.FILTER($C$9:F93,$A$9:$A93>G$4))),(SUMIFS($B$9:$B13,$A$9:$A13,"<"&$A13,$A$9:$A13,">="&G$4,$A$9:$A13,"<="&G$5)-SUM(_xlfn._xlws.FILTER(G14:G93,$A14:$A93>G$4),_xlfn._xlws.FILTER($C$9:F93,$A$9:$A93>G$4))>G$6)),G$6,MAX(0,SUMIFS($B$9:$B13,$A$9:$A13,"<"&$A13,$A$9:$A13,">="&G$4,$A$9:$A13,"<="&G$5)-SUM(_xlfn._xlws.FILTER(G14:G93,$A14:$A93>G$4),_xlfn._xlws.FILTER($C$9:F93,$A$9:$A93>G$4)))),"")} | H13: {=IF(AND(($A13<>"")*($A13>H$4)*($A13<=H$5)),IF(AND((SUMIFS($B$9:$B13,$A$9:$A13,"<"&$A13,$A$9:$A13,">="&H$4,$A$9:$A13,"<="&H$5)>SUM(_xlfn._xlws.FILTER(H14:H93,$A14:$A93>H$4),_xlfn._xlws.FILTER($C$9:G93,$A$9:$A93>H$4))),(SUMIFS($B$9:$B13,$A$9:$A13,"<"&$A13,$A$9:$A13,">="&H$4,$A$9:$A13,"<="&H$5)-SUM(_xlfn._xlws.FILTER(H14:H93,$A14:$A93>H$4),_xlfn._xlws.FILTER($C$9:G93,$A$9:$A93>H$4))>H$6)),H$6,MAX(0,SUMIFS($B$9:$B13,$A$9:$A13,"<"&$A13,$A$9:$A13,">="&H$4,$A$9:$A13,"<="&H$5)-SUM(_xlfn._xlws.FILTER(H14:H93,$A14:$A93>H$4),_xlfn._xlws.FILTER($C$9:G93,$A$9:$A93>H$4)))),"")} | I13: {=IF(AND(($A13<>"")*($A13>I$4)*($A13<=I$5)),IF(AND((SUMIFS($B$9:$B13,$A$9:$A13,"<"&$A13,$A$9:$A13,">="&I$4,$A$9:$A13,"<="&I$5)>SUM(_xlfn._xlws.FILTER(I14:I93,$A14:$A93>I$4),_xlfn._xlws.FILTER($C$9:H93,$A$9:$A93>I$4))),(SUMIFS($B$9:$B13,$A$9:$A13,"<"&$A13,$A$9:$A13,">="&I$4,$A$9:$A13,"<="&I$5)-SUM(_xlfn._xlws.FILTER(I14:I93,$A14:$A93>I$4),_xlfn._xlws.FILTER($C$9:H93,$A$9:$A93>I$4))>I$6)),I$6,MAX(0,SUMIFS($B$9:$B13,$A$9:$A13,"<"&$A13,$A$9:$A13,">="&I$4,$A$9:$A13,"<="&I$5)-SUM(_xlfn._xlws.FILTER(I14:I93,$A14:$A93>I$4),_xlfn._xlws.FILTER($C$9:H93,$A$9:$A93>I$4)))),"")} | J13: {=IF(AND(($A13<>"")*($A13>J$4)*($A13<=J$5)),IF(AND((SUMIFS($B$9:$B13,$A$9:$A13,"<"&$A13,$A$9:$A13,">="&J$4,$A$9:$A13,"<="&J$5)>SUM(_xlfn._xlws.FILTER(J14:J93,$A14:$A93>J$4),_xlfn._xlws.FILTER($C$9:I93,$A$9:$A93>J$4))),(SUMIFS($B$9:$B13,$A$9:$A13,"<"&$A13,$A$9:$A13,">="&J$4,$A$9:$A13,"<="&J$5)-SUM(_xlfn._xlws.FILTER(J14:J93,$A14:$A93>J$4),_xlfn._xlws.FILTER($C$9:I93,$A$9:$A93>J$4))>J$6)),J$6,MAX(0,SUMIFS($B$9:$B13,$A$9:$A13,"<"&$A13,$A$9:$A13,">="&J$4,$A$9:$A13,"<="&J$5)-SUM(_xlfn._xlws.FILTER(J14:J93,$A14:$A93>J$4),_xlfn._xlws.FILTER($C$9:I93,$A$9:$A93>J$4)))),"")} | K13: {=IF(AND(($A13<>"")*($A13>K$4)*($A13<=K$5)),IF(AND((SUMIFS($B$9:$B13,$A$9:$A13,"<"&$A13,$A$9:$A13,">="&K$4,$A$9:$A13,"<="&K$5)>SUM(_xlfn._xlws.FILTER(K14:K93,$A14:$A93>K$4),_xlfn._xlws.FILTER($C$9:J93,$A$9:$A93>K$4))),(SUMIFS($B$9:$B13,$A$9:$A13,"<"&$A13,$A$9:$A13,">="&K$4,$A$9:$A13,"<="&K$5)-SUM(_xlfn._xlws.FILTER(K14:K93,$A14:$A93>K$4),_xlfn._xlws.FILTER($C$9:J93,$A$9:$A93>K$4))>K$6)),K$6,MAX(0,SUMIFS($B$9:$B13,$A$9:$A13,"<"&$A13,$A$9:$A13,">="&K$4,$A$9:$A13,"<="&K$5)-SUM(_xlfn._xlws.FILTER(K14:K93,$A14:$A93>K$4),_xlfn._xlws.FILTER($C$9:J93,$A$9:$A93>K$4)))),"")} | ... HS13: {=IF(AND(($A13<>"")*($A13>HS$4)*($A13<=HS$5)),IF(AND((SUMIFS($B$9:$B13,$A$9:$A13,"<"&$A13,$A$9:$A13,">="&HS$4,$A$9:$A13,"<="&HS$5)>SUM(_xlfn._xlws.FILTER(HS14:HS93,$A14:$A93>HS$4),_xlfn._xlws.FILTER($C$9:HR93,$A$9:$A93>HS$4))),(SUMIFS($B$9:$B13,$A$9:$A13,"<"&$A13,$A$9:$A13,">="&HS$4,$A$9:$A13,"<="&HS$5)-SUM(_xlfn._xlws.FILTER(HS14:HS93,$A14:$A93>HS$4),_xlfn._xlws.FILTER($C$9:HR93,$A$9:$A93>HS$4))>HS$6)),HS$6,MAX(0,SUMIFS($B$9:$B13,$A$9:$A13,"<"&$A13,$A$9:$A13,">="&HS$4,$A$9:$A13,"<="&HS$5)-SUM(_xlfn._xlws.FILTER(HS14:HS93,$A14:$A93>HS$4),_xlfn._xlws.FILTER($C$9:HR93,$A$9:$A93>HS$4)))),"")}
A14: 45505 | B14: =VLOOKUP(A14,Table5[],7,FALSE) -> 0 | D14: {=IF(AND(($A14<>"")*($A14>D$4)*($A14<=D$5)),IF(AND((SUMIFS($B$9:$B14,$A$9:$A14,"<"&$A14,$A$9:$A14,">="&D$4,$A$9:$A14,"<="&D$5)>SUM(_xlfn._xlws.FILTER(D15:D94,$A15:$A94>D$4),_xlfn._xlws.FILTER($C$9:C94,$A$9:$A94>D$4))),(SUMIFS($B$9:$B14,$A$9:$A14,"<"&$A14,$A$9:$A14,">="&D$4,$A$9:$A14,"<="&D$5)-SUM(_xlfn._xlws.FILTER(D15:D94,$A15:$A94>D$4),_xlfn._xlws.FILTER($C$9:C94,$A$9:$A94>D$4))>D$6)),D$6,MAX(0,SUMIFS($B$9:$B14,$A$9:$A14,"<"&$A14,$A$9:$A14,">="&D$4,$A$9:$A14,"<="&D$5)-SUM(_xlfn._xlws.FILTER(D15:D94,$A15:$A94>D$4),_xlfn._xlws.FILTER($C$9:C94,$A$9:$A94>D$4)))),"")} -> 5000 | E14: {=IF(AND(($A14<>"")*($A14>E$4)*($A14<=E$5)),IF(AND((SUMIFS($B$9:$B14,$A$9:$A14,"<"&$A14,$A$9:$A14,">="&E$4,$A$9:$A14,"<="&E$5)>SUM(_xlfn._xlws.FILTER(E15:E94,$A15:$A94>E$4),_xlfn._xlws.FILTER($C$9:D94,$A$9:$A94>E$4))),(SUMIFS($B$9:$B14,$A$9:$A14,"<"&$A14,$A$9:$A14,">="&E$4,$A$9:$A14,"<="&E$5)-SUM(_xlfn._xlws.FILTER(E15:E94,$A15:$A94>E$4),_xlfn._xlws.FILTER($C$9:D94,$A$9:$A94>E$4))>E$6)),E$6,MAX(0,SUMIFS($B$9:$B14,$A$9:$A14,"<"&$A14,$A$9:$A14,">="&E$4,$A$9:$A14,"<="&E$5)-SUM(_xlfn._xlws.FILTER(E15:E94,$A15:$A94>E$4),_xlfn._xlws.FILTER($C$9:D94,$A$9:$A94>E$4)))),"")} -> 0 | F14: {=IF(AND(($A14<>"")*($A14>F$4)*($A14<=F$5)),IF(AND((SUMIFS($B$9:$B14,$A$9:$A14,"<"&$A14,$A$9:$A14,">="&F$4,$A$9:$A14,"<="&F$5)>SUM(_xlfn._xlws.FILTER(F15:F94,$A15:$A94>F$4),_xlfn._xlws.FILTER($C$9:E94,$A$9:$A94>F$4))),(SUMIFS($B$9:$B14,$A$9:$A14,"<"&$A14,$A$9:$A14,">="&F$4,$A$9:$A14,"<="&F$5)-SUM(_xlfn._xlws.FILTER(F15:F94,$A15:$A94>F$4),_xlfn._xlws.FILTER($C$9:E94,$A$9:$A94>F$4))>F$6)),F$6,MAX(0,SUMIFS($B$9:$B14,$A$9:$A14,"<"&$A14,$A$9:$A14,">="&F$4,$A$9:$A14,"<="&F$5)-SUM(_xlfn._xlws.FILTER(F15:F94,$A15:$A94>F$4),_xlfn._xlws.FILTER($C$9:E94,$A$9:$A94>F$4)))),"")} -> 0 | G14: {=IF(AND(($A14<>"")*($A14>G$4)*($A14<=G$5)),IF(AND((SUMIFS($B$9:$B14,$A$9:$A14,"<"&$A14,$A$9:$A14,">="&G$4,$A$9:$A14,"<="&G$5)>SUM(_xlfn._xlws.FILTER(G15:G94,$A15:$A94>G$4),_xlfn._xlws.FILTER($C$9:F94,$A$9:$A94>G$4))),(SUMIFS($B$9:$B14,$A$9:$A14,"<"&$A14,$A$9:$A14,">="&G$4,$A$9:$A14,"<="&G$5)-SUM(_xlfn._xlws.FILTER(G15:G94,$A15:$A94>G$4),_xlfn._xlws.FILTER($C$9:F94,$A$9:$A94>G$4))>G$6)),G$6,MAX(0,SUMIFS($B$9:$B14,$A$9:$A14,"<"&$A14,$A$9:$A14,">="&G$4,$A$9:$A14,"<="&G$5)-SUM(_xlfn._xlws.FILTER(G15:G94,$A15:$A94>G$4),_xlfn._xlws.FILTER($C$9:F94,$A$9:$A94>G$4)))),"")} | H14: {=IF(AND(($A14<>"")*($A14>H$4)*($A14<=H$5)),IF(AND((SUMIFS($B$9:$B14,$A$9:$A14,"<"&$A14,$A$9:$A14,">="&H$4,$A$9:$A14,"<="&H$5)>SUM(_xlfn._xlws.FILTER(H15:H94,$A15:$A94>H$4),_xlfn._xlws.FILTER($C$9:G94,$A$9:$A94>H$4))),(SUMIFS($B$9:$B14,$A$9:$A14,"<"&$A14,$A$9:$A14,">="&H$4,$A$9:$A14,"<="&H$5)-SUM(_xlfn._xlws.FILTER(H15:H94,$A15:$A94>H$4),_xlfn._xlws.FILTER($C$9:G94,$A$9:$A94>H$4))>H$6)),H$6,MAX(0,SUMIFS($B$9:$B14,$A$9:$A14,"<"&$A14,$A$9:$A14,">="&H$4,$A$9:$A14,"<="&H$5)-SUM(_xlfn._xlws.FILTER(H15:H94,$A15:$A94>H$4),_xlfn._xlws.FILTER($C$9:G94,$A$9:$A94>H$4)))),"")} | I14: {=IF(AND(($A14<>"")*($A14>I$4)*($A14<=I$5)),IF(AND((SUMIFS($B$9:$B14,$A$9:$A14,"<"&$A14,$A$9:$A14,">="&I$4,$A$9:$A14,"<="&I$5)>SUM(_xlfn._xlws.FILTER(I15:I94,$A15:$A94>I$4),_xlfn._xlws.FILTER($C$9:H94,$A$9:$A94>I$4))),(SUMIFS($B$9:$B14,$A$9:$A14,"<"&$A14,$A$9:$A14,">="&I$4,$A$9:$A14,"<="&I$5)-SUM(_xlfn._xlws.FILTER(I15:I94,$A15:$A94>I$4),_xlfn._xlws.FILTER($C$9:H94,$A$9:$A94>I$4))>I$6)),I$6,MAX(0,SUMIFS($B$9:$B14,$A$9:$A14,"<"&$A14,$A$9:$A14,">="&I$4,$A$9:$A14,"<="&I$5)-SUM(_xlfn._xlws.FILTER(I15:I94,$A15:$A94>I$4),_xlfn._xlws.FILTER($C$9:H94,$A$9:$A94>I$4)))),"")} | J14: {=IF(AND(($A14<>"")*($A14>J$4)*($A14<=J$5)),IF(AND((SUMIFS($B$9:$B14,$A$9:$A14,"<"&$A14,$A$9:$A14,">="&J$4,$A$9:$A14,"<="&J$5)>SUM(_xlfn._xlws.FILTER(J15:J94,$A15:$A94>J$4),_xlfn._xlws.FILTER($C$9:I94,$A$9:$A94>J$4))),(SUMIFS($B$9:$B14,$A$9:$A14,"<"&$A14,$A$9:$A14,">="&J$4,$A$9:$A14,"<="&J$5)-SUM(_xlfn._xlws.FILTER(J15:J94,$A15:$A94>J$4),_xlfn._xlws.FILTER($C$9:I94,$A$9:$A94>J$4))>J$6)),J$6,MAX(0,SUMIFS($B$9:$B14,$A$9:$A14,"<"&$A14,$A$9:$A14,">="&J$4,$A$9:$A14,"<="&J$5)-SUM(_xlfn._xlws.FILTER(J15:J94,$A15:$A94>J$4),_xlfn._xlws.FILTER($C$9:I94,$A$9:$A94>J$4)))),"")} | K14: {=IF(AND(($A14<>"")*($A14>K$4)*($A14<=K$5)),IF(AND((SUMIFS($B$9:$B14,$A$9:$A14,"<"&$A14,$A$9:$A14,">="&K$4,$A$9:$A14,"<="&K$5)>SUM(_xlfn._xlws.FILTER(K15:K94,$A15:$A94>K$4),_xlfn._xlws.FILTER($C$9:J94,$A$9:$A94>K$4))),(SUMIFS($B$9:$B14,$A$9:$A14,"<"&$A14,$A$9:$A14,">="&K$4,$A$9:$A14,"<="&K$5)-SUM(_xlfn._xlws.FILTER(K15:K94,$A15:$A94>K$4),_xlfn._xlws.FILTER($C$9:J94,$A$9:$A94>K$4))>K$6)),K$6,MAX(0,SUMIFS($B$9:$B14,$A$9:$A14,"<"&$A14,$A$9:$A14,">="&K$4,$A$9:$A14,"<="&K$5)-SUM(_xlfn._xlws.FILTER(K15:K94,$A15:$A94>K$4),_xlfn._xlws.FILTER($C$9:J94,$A$9:$A94>K$4)))),"")} | ... HS14: {=IF(AND(($A14<>"")*($A14>HS$4)*($A14<=HS$5)),IF(AND((SUMIFS($B$9:$B14,$A$9:$A14,"<"&$A14,$A$9:$A14,">="&HS$4,$A$9:$A14,"<="&HS$5)>SUM(_xlfn._xlws.FILTER(HS15:HS94,$A15:$A94>HS$4),_xlfn._xlws.FILTER($C$9:HR94,$A$9:$A94>HS$4))),(SUMIFS($B$9:$B14,$A$9:$A14,"<"&$A14,$A$9:$A14,">="&HS$4,$A$9:$A14,"<="&HS$5)-SUM(_xlfn._xlws.FILTER(HS15:HS94,$A15:$A94>HS$4),_xlfn._xlws.FILTER($C$9:HR94,$A$9:$A94>HS$4))>HS$6)),HS$6,MAX(0,SUMIFS($B$9:$B14,$A$9:$A14,"<"&$A14,$A$9:$A14,">="&HS$4,$A$9:$A14,"<="&HS$5)-SUM(_xlfn._xlws.FILTER(HS15:HS94,$A15:$A94>HS$4),_xlfn._xlws.FILTER($C$9:HR94,$A$9:$A94>HS$4)))),"")}
A15: 45536 | B15: =VLOOKUP(A15,Table5[],7,FALSE) -> 0 | D15: {=IF(AND(($A15<>"")*($A15>D$4)*($A15<=D$5)),IF(AND((SUMIFS($B$9:$B15,$A$9:$A15,"<"&$A15,$A$9:$A15,">="&D$4,$A$9:$A15,"<="&D$5)>SUM(_xlfn._xlws.FILTER(D16:D95,$A16:$A95>D$4),_xlfn._xlws.FILTER($C$9:C95,$A$9:$A95>D$4))),(SUMIFS($B$9:$B15,$A$9:$A15,"<"&$A15,$A$9:$A15,">="&D$4,$A$9:$A15,"<="&D$5)-SUM(_xlfn._xlws.FILTER(D16:D95,$A16:$A95>D$4),_xlfn._xlws.FILTER($C$9:C95,$A$9:$A95>D$4))>D$6)),D$6,MAX(0,SUMIFS($B$9:$B15,$A$9:$A15,"<"&$A15,$A$9:$A15,">="&D$4,$A$9:$A15,"<="&D$5)-SUM(_xlfn._xlws.FILTER(D16:D95,$A16:$A95>D$4),_xlfn._xlws.FILTER($C$9:C95,$A$9:$A95>D$4)))),"")} | E15: {=IF(AND(($A15<>"")*($A15>E$4)*($A15<=E$5)),IF(AND((SUMIFS($B$9:$B15,$A$9:$A15,"<"&$A15,$A$9:$A15,">="&E$4,$A$9:$A15,"<="&E$5)>SUM(_xlfn._xlws.FILTER(E16:E95,$A16:$A95>E$4),_xlfn._xlws.FILTER($C$9:D95,$A$9:$A95>E$4))),(SUMIFS($B$9:$B15,$A$9:$A15,"<"&$A15,$A$9:$A15,">="&E$4,$A$9:$A15,"<="&E$5)-SUM(_xlfn._xlws.FILTER(E16:E95,$A16:$A95>E$4),_xlfn._xlws.FILTER($C$9:D95,$A$9:$A95>E$4))>E$6)),E$6,MAX(0,SUMIFS($B$9:$B15,$A$9:$A15,"<"&$A15,$A$9:$A15,">="&E$4,$A$9:$A15,"<="&E$5)-SUM(_xlfn._xlws.FILTER(E16:E95,$A16:$A95>E$4),_xlfn._xlws.FILTER($C$9:D95,$A$9:$A95>E$4)))),"")} -> 2000 | F15: {=IF(AND(($A15<>"")*($A15>F$4)*($A15<=F$5)),IF(AND((SUMIFS($B$9:$B15,$A$9:$A15,"<"&$A15,$A$9:$A15,">="&F$4,$A$9:$A15,"<="&F$5)>SUM(_xlfn._xlws.FILTER(F16:F95,$A16:$A95>F$4),_xlfn._xlws.FILTER($C$9:E95,$A$9:$A95>F$4))),(SUMIFS($B$9:$B15,$A$9:$A15,"<"&$A15,$A$9:$A15,">="&F$4,$A$9:$A15,"<="&F$5)-SUM(_xlfn._xlws.FILTER(F16:F95,$A16:$A95>F$4),_xlfn._xlws.FILTER($C$9:E95,$A$9:$A95>F$4))>F$6)),F$6,MAX(0,SUMIFS($B$9:$B15,$A$9:$A15,"<"&$A15,$A$9:$A15,">="&F$4,$A$9:$A15,"<="&F$5)-SUM(_xlfn._xlws.FILTER(F16:F95,$A16:$A95>F$4),_xlfn._xlws.FILTER($C$9:E95,$A$9:$A95>F$4)))),"")} -> 0 | G15: {=IF(AND(($A15<>"")*($A15>G$4)*($A15<=G$5)),IF(AND((SUMIFS($B$9:$B15,$A$9:$A15,"<"&$A15,$A$9:$A15,">="&G$4,$A$9:$A15,"<="&G$5)>SUM(_xlfn._xlws.FILTER(G16:G95,$A16:$A95>G$4),_xlfn._xlws.FILTER($C$9:F95,$A$9:$A95>G$4))),(SUMIFS($B$9:$B15,$A$9:$A15,"<"&$A15,$A$9:$A15,">="&G$4,$A$9:$A15,"<="&G$5)-SUM(_xlfn._xlws.FILTER(G16:G95,$A16:$A95>G$4),_xlfn._xlws.FILTER($C$9:F95,$A$9:$A95>G$4))>G$6)),G$6,MAX(0,SUMIFS($B$9:$B15,$A$9:$A15,"<"&$A15,$A$9:$A15,">="&G$4,$A$9:$A15,"<="&G$5)-SUM(_xlfn._xlws.FILTER(G16:G95,$A16:$A95>G$4),_xlfn._xlws.FILTER($C$9:F95,$A$9:$A95>G$4)))),"")} | H15: {=IF(AND(($A15<>"")*($A15>H$4)*($A15<=H$5)),IF(AND((SUMIFS($B$9:$B15,$A$9:$A15,"<"&$A15,$A$9:$A15,">="&H$4,$A$9:$A15,"<="&H$5)>SUM(_xlfn._xlws.FILTER(H16:H95,$A16:$A95>H$4),_xlfn._xlws.FILTER($C$9:G95,$A$9:$A95>H$4))),(SUMIFS($B$9:$B15,$A$9:$A15,"<"&$A15,$A$9:$A15,">="&H$4,$A$9:$A15,"<="&H$5)-SUM(_xlfn._xlws.FILTER(H16:H95,$A16:$A95>H$4),_xlfn._xlws.FILTER($C$9:G95,$A$9:$A95>H$4))>H$6)),H$6,MAX(0,SUMIFS($B$9:$B15,$A$9:$A15,"<"&$A15,$A$9:$A15,">="&H$4,$A$9:$A15,"<="&H$5)-SUM(_xlfn._xlws.FILTER(H16:H95,$A16:$A95>H$4),_xlfn._xlws.FILTER($C$9:G95,$A$9:$A95>H$4)))),"")} | I15: {=IF(AND(($A15<>"")*($A15>I$4)*($A15<=I$5)),IF(AND((SUMIFS($B$9:$B15,$A$9:$A15,"<"&$A15,$A$9:$A15,">="&I$4,$A$9:$A15,"<="&I$5)>SUM(_xlfn._xlws.FILTER(I16:I95,$A16:$A95>I$4),_xlfn._xlws.FILTER($C$9:H95,$A$9:$A95>I$4))),(SUMIFS($B$9:$B15,$A$9:$A15,"<"&$A15,$A$9:$A15,">="&I$4,$A$9:$A15,"<="&I$5)-SUM(_xlfn._xlws.FILTER(I16:I95,$A16:$A95>I$4),_xlfn._xlws.FILTER($C$9:H95,$A$9:$A95>I$4))>I$6)),I$6,MAX(0,SUMIFS($B$9:$B15,$A$9:$A15,"<"&$A15,$A$9:$A15,">="&I$4,$A$9:$A15,"<="&I$5)-SUM(_xlfn._xlws.FILTER(I16:I95,$A16:$A95>I$4),_xlfn._xlws.FILTER($C$9:H95,$A$9:$A95>I$4)))),"")} | J15: {=IF(AND(($A15<>"")*($A15>J$4)*($A15<=J$5)),IF(AND((SUMIFS($B$9:$B15,$A$9:$A15,"<"&$A15,$A$9:$A15,">="&J$4,$A$9:$A15,"<="&J$5)>SUM(_xlfn._xlws.FILTER(J16:J95,$A16:$A95>J$4),_xlfn._xlws.FILTER($C$9:I95,$A$9:$A95>J$4))),(SUMIFS($B$9:$B15,$A$9:$A15,"<"&$A15,$A$9:$A15,">="&J$4,$A$9:$A15,"<="&J$5)-SUM(_xlfn._xlws.FILTER(J16:J95,$A16:$A95>J$4),_xlfn._xlws.FILTER($C$9:I95,$A$9:$A95>J$4))>J$6)),J$6,MAX(0,SUMIFS($B$9:$B15,$A$9:$A15,"<"&$A15,$A$9:$A15,">="&J$4,$A$9:$A15,"<="&J$5)-SUM(_xlfn._xlws.FILTER(J16:J95,$A16:$A95>J$4),_xlfn._xlws.FILTER($C$9:I95,$A$9:$A95>J$4)))),"")} | K15: {=IF(AND(($A15<>"")*($A15>K$4)*($A15<=K$5)),IF(AND((SUMIFS($B$9:$B15,$A$9:$A15,"<"&$A15,$A$9:$A15,">="&K$4,$A$9:$A15,"<="&K$5)>SUM(_xlfn._xlws.FILTER(K16:K95,$A16:$A95>K$4),_xlfn._xlws.FILTER($C$9:J95,$A$9:$A95>K$4))),(SUMIFS($B$9:$B15,$A$9:$A15,"<"&$A15,$A$9:$A15,">="&K$4,$A$9:$A15,"<="&K$5)-SUM(_xlfn._xlws.FILTER(K16:K95,$A16:$A95>K$4),_xlfn._xlws.FILTER($C$9:J95,$A$9:$A95>K$4))>K$6)),K$6,MAX(0,SUMIFS($B$9:$B15,$A$9:$A15,"<"&$A15,$A$9:$A15,">="&K$4,$A$9:$A15,"<="&K$5)-SUM(_xlfn._xlws.FILTER(K16:K95,$A16:$A95>K$4),_xlfn._xlws.FILTER($C$9:J95,$A$9:$A95>K$4)))),"")} | ... HS15: {=IF(AND(($A15<>"")*($A15>HS$4)*($A15<=HS$5)),IF(AND((SUMIFS($B$9:$B15,$A$9:$A15,"<"&$A15,$A$9:$A15,">="&HS$4,$A$9:$A15,"<="&HS$5)>SUM(_xlfn._xlws.FILTER(HS16:HS95,$A16:$A95>HS$4),_xlfn._xlws.FILTER($C$9:HR95,$A$9:$A95>HS$4))),(SUMIFS($B$9:$B15,$A$9:$A15,"<"&$A15,$A$9:$A15,">="&HS$4,$A$9:$A15,"<="&HS$5)-SUM(_xlfn._xlws.FILTER(HS16:HS95,$A16:$A95>HS$4),_xlfn._xlws.FILTER($C$9:HR95,$A$9:$A95>HS$4))>HS$6)),HS$6,MAX(0,SUMIFS($B$9:$B15,$A$9:$A15,"<"&$A15,$A$9:$A15,">="&HS$4,$A$9:$A15,"<="&HS$5)-SUM(_xlfn._xlws.FILTER(HS16:HS95,$A16:$A95>HS$4),_xlfn._xlws.FILTER($C$9:HR95,$A$9:$A95>HS$4)))),"")}
A16: 45566 | B16: =VLOOKUP(A16,Table5[],7,FALSE) -> 0 | D16: {=IF(AND(($A16<>"")*($A16>D$4)*($A16<=D$5)),IF(AND((SUMIFS($B$9:$B16,$A$9:$A16,"<"&$A16,$A$9:$A16,">="&D$4,$A$9:$A16,"<="&D$5)>SUM(_xlfn._xlws.FILTER(D17:D96,$A17:$A96>D$4),_xlfn._xlws.FILTER($C$9:C96,$A$9:$A96>D$4))),(SUMIFS($B$9:$B16,$A$9:$A16,"<"&$A16,$A$9:$A16,">="&D$4,$A$9:$A16,"<="&D$5)-SUM(_xlfn._xlws.FILTER(D17:D96,$A17:$A96>D$4),_xlfn._xlws.FILTER($C$9:C96,$A$9:$A96>D$4))>D$6)),D$6,MAX(0,SUMIFS($B$9:$B16,$A$9:$A16,"<"&$A16,$A$9:$A16,">="&D$4,$A$9:$A16,"<="&D$5)-SUM(_xlfn._xlws.FILTER(D17:D96,$A17:$A96>D$4),_xlfn._xlws.FILTER($C$9:C96,$A$9:$A96>D$4)))),"")} | E16: {=IF(AND(($A16<>"")*($A16>E$4)*($A16<=E$5)),IF(AND((SUMIFS($B$9:$B16,$A$9:$A16,"<"&$A16,$A$9:$A16,">="&E$4,$A$9:$A16,"<="&E$5)>SUM(_xlfn._xlws.FILTER(E17:E96,$A17:$A96>E$4),_xlfn._xlws.FILTER($C$9:D96,$A$9:$A96>E$4))),(SUMIFS($B$9:$B16,$A$9:$A16,"<"&$A16,$A$9:$A16,">="&E$4,$A$9:$A16,"<="&E$5)-SUM(_xlfn._xlws.FILTER(E17:E96,$A17:$A96>E$4),_xlfn._xlws.FILTER($C$9:D96,$A$9:$A96>E$4))>E$6)),E$6,MAX(0,SUMIFS($B$9:$B16,$A$9:$A16,"<"&$A16,$A$9:$A16,">="&E$4,$A$9:$A16,"<="&E$5)-SUM(_xlfn._xlws.FILTER(E17:E96,$A17:$A96>E$4),_xlfn._xlws.FILTER($C$9:D96,$A$9:$A96>E$4)))),"")} | F16: {=IF(AND(($A16<>"")*($A16>F$4)*($A16<=F$5)),IF(AND((SUMIFS($B$9:$B16,$A$9:$A16,"<"&$A16,$A$9:$A16,">="&F$4,$A$9:$A16,"<="&F$5)>SUM(_xlfn._xlws.FILTER(F17:F96,$A17:$A96>F$4),_xlfn._xlws.FILTER($C$9:E96,$A$9:$A96>F$4))),(SUMIFS($B$9:$B16,$A$9:$A16,"<"&$A16,$A$9:$A16,">="&F$4,$A$9:$A16,"<="&F$5)-SUM(_xlfn._xlws.FILTER(F17:F96,$A17:$A96>F$4),_xlfn._xlws.FILTER($C$9:E96,$A$9:$A96>F$4))>F$6)),F$6,MAX(0,SUMIFS($B$9:$B16,$A$9:$A16,"<"&$A16,$A$9:$A16,">="&F$4,$A$9:$A16,"<="&F$5)-SUM(_xlfn._xlws.FILTER(F17:F96,$A17:$A96>F$4),_xlfn._xlws.FILTER($C$9:E96,$A$9:$A96>F$4)))),"")} -> 0 | G16: {=IF(AND(($A16<>"")*($A16>G$4)*($A16<=G$5)),IF(AND((SUMIFS($B$9:$B16,$A$9:$A16,"<"&$A16,$A$9:$A16,">="&G$4,$A$9:$A16,"<="&G$5)>SUM(_xlfn._xlws.FILTER(G17:G96,$A17:$A96>G$4),_xlfn._xlws.FILTER($C$9:F96,$A$9:$A96>G$4))),(SUMIFS($B$9:$B16,$A$9:$A16,"<"&$A16,$A$9:$A16,">="&G$4,$A$9:$A16,"<="&G$5)-SUM(_xlfn._xlws.FILTER(G17:G96,$A17:$A96>G$4),_xlfn._xlws.FILTER($C$9:F96,$A$9:$A96>G$4))>G$6)),G$6,MAX(0,SUMIFS($B$9:$B16,$A$9:$A16,"<"&$A16,$A$9:$A16,">="&G$4,$A$9:$A16,"<="&G$5)-SUM(_xlfn._xlws.FILTER(G17:G96,$A17:$A96>G$4),_xlfn._xlws.FILTER($C$9:F96,$A$9:$A96>G$4)))),"")} | H16: {=IF(AND(($A16<>"")*($A16>H$4)*($A16<=H$5)),IF(AND((SUMIFS($B$9:$B16,$A$9:$A16,"<"&$A16,$A$9:$A16,">="&H$4,$A$9:$A16,"<="&H$5)>SUM(_xlfn._xlws.FILTER(H17:H96,$A17:$A96>H$4),_xlfn._xlws.FILTER($C$9:G96,$A$9:$A96>H$4))),(SUMIFS($B$9:$B16,$A$9:$A16,"<"&$A16,$A$9:$A16,">="&H$4,$A$9:$A16,"<="&H$5)-SUM(_xlfn._xlws.FILTER(H17:H96,$A17:$A96>H$4),_xlfn._xlws.FILTER($C$9:G96,$A$9:$A96>H$4))>H$6)),H$6,MAX(0,SUMIFS($B$9:$B16,$A$9:$A16,"<"&$A16,$A$9:$A16,">="&H$4,$A$9:$A16,"<="&H$5)-SUM(_xlfn._xlws.FILTER(H17:H96,$A17:$A96>H$4),_xlfn._xlws.FILTER($C$9:G96,$A$9:$A96>H$4)))),"")} | I16: {=IF(AND(($A16<>"")*($A16>I$4)*($A16<=I$5)),IF(AND((SUMIFS($B$9:$B16,$A$9:$A16,"<"&$A16,$A$9:$A16,">="&I$4,$A$9:$A16,"<="&I$5)>SUM(_xlfn._xlws.FILTER(I17:I96,$A17:$A96>I$4),_xlfn._xlws.FILTER($C$9:H96,$A$9:$A96>I$4))),(SUMIFS($B$9:$B16,$A$9:$A16,"<"&$A16,$A$9:$A16,">="&I$4,$A$9:$A16,"<="&I$5)-SUM(_xlfn._xlws.FILTER(I17:I96,$A17:$A96>I$4),_xlfn._xlws.FILTER($C$9:H96,$A$9:$A96>I$4))>I$6)),I$6,MAX(0,SUMIFS($B$9:$B16,$A$9:$A16,"<"&$A16,$A$9:$A16,">="&I$4,$A$9:$A16,"<="&I$5)-SUM(_xlfn._xlws.FILTER(I17:I96,$A17:$A96>I$4),_xlfn._xlws.FILTER($C$9:H96,$A$9:$A96>I$4)))),"")} | J16: {=IF(AND(($A16<>"")*($A16>J$4)*($A16<=J$5)),IF(AND((SUMIFS($B$9:$B16,$A$9:$A16,"<"&$A16,$A$9:$A16,">="&J$4,$A$9:$A16,"<="&J$5)>SUM(_xlfn._xlws.FILTER(J17:J96,$A17:$A96>J$4),_xlfn._xlws.FILTER($C$9:I96,$A$9:$A96>J$4))),(SUMIFS($B$9:$B16,$A$9:$A16,"<"&$A16,$A$9:$A16,">="&J$4,$A$9:$A16,"<="&J$5)-SUM(_xlfn._xlws.FILTER(J17:J96,$A17:$A96>J$4),_xlfn._xlws.FILTER($C$9:I96,$A$9:$A96>J$4))>J$6)),J$6,MAX(0,SUMIFS($B$9:$B16,$A$9:$A16,"<"&$A16,$A$9:$A16,">="&J$4,$A$9:$A16,"<="&J$5)-SUM(_xlfn._xlws.FILTER(J17:J96,$A17:$A96>J$4),_xlfn._xlws.FILTER($C$9:I96,$A$9:$A96>J$4)))),"")} | K16: {=IF(AND(($A16<>"")*($A16>K$4)*($A16<=K$5)),IF(AND((SUMIFS($B$9:$B16,$A$9:$A16,"<"&$A16,$A$9:$A16,">="&K$4,$A$9:$A16,"<="&K$5)>SUM(_xlfn._xlws.FILTER(K17:K96,$A17:$A96>K$4),_xlfn._xlws.FILTER($C$9:J96,$A$9:$A96>K$4))),(SUMIFS($B$9:$B16,$A$9:$A16,"<"&$A16,$A$9:$A16,">="&K$4,$A$9:$A16,"<="&K$5)-SUM(_xlfn._xlws.FILTER(K17:K96,$A17:$A96>K$4),_xlfn._xlws.FILTER($C$9:J96,$A$9:$A96>K$4))>K$6)),K$6,MAX(0,SUMIFS($B$9:$B16,$A$9:$A16,"<"&$A16,$A$9:$A16,">="&K$4,$A$9:$A16,"<="&K$5)-SUM(_xlfn._xlws.FILTER(K17:K96,$A17:$A96>K$4),_xlfn._xlws.FILTER($C$9:J96,$A$9:$A96>K$4)))),"")} | ... HS16: {=IF(AND(($A16<>"")*($A16>HS$4)*($A16<=HS$5)),IF(AND((SUMIFS($B$9:$B16,$A$9:$A16,"<"&$A16,$A$9:$A16,">="&HS$4,$A$9:$A16,"<="&HS$5)>SUM(_xlfn._xlws.FILTER(HS17:HS96,$A17:$A96>HS$4),_xlfn._xlws.FILTER($C$9:HR96,$A$9:$A96>HS$4))),(SUMIFS($B$9:$B16,$A$9:$A16,"<"&$A16,$A$9:$A16,">="&HS$4,$A$9:$A16,"<="&HS$5)-SUM(_xlfn._xlws.FILTER(HS17:HS96,$A17:$A96>HS$4),_xlfn._xlws.FILTER($C$9:HR96,$A$9:$A96>HS$4))>HS$6)),HS$6,MAX(0,SUMIFS($B$9:$B16,$A$9:$A16,"<"&$A16,$A$9:$A16,">="&HS$4,$A$9:$A16,"<="&HS$5)-SUM(_xlfn._xlws.FILTER(HS17:HS96,$A17:$A96>HS$4),_xlfn._xlws.FILTER($C$9:HR96,$A$9:$A96>HS$4)))),"")}
A17: 45597 | B17: =VLOOKUP(A17,Table5[],7,FALSE) -> 0 | D17: {=IF(AND(($A17<>"")*($A17>D$4)*($A17<=D$5)),IF(AND((SUMIFS($B$9:$B17,$A$9:$A17,"<"&$A17,$A$9:$A17,">="&D$4,$A$9:$A17,"<="&D$5)>SUM(_xlfn._xlws.FILTER(D18:D97,$A18:$A97>D$4),_xlfn._xlws.FILTER($C$9:C97,$A$9:$A97>D$4))),(SUMIFS($B$9:$B17,$A$9:$A17,"<"&$A17,$A$9:$A17,">="&D$4,$A$9:$A17,"<="&D$5)-SUM(_xlfn._xlws.FILTER(D18:D97,$A18:$A97>D$4),_xlfn._xlws.FILTER($C$9:C97,$A$9:$A97>D$4))>D$6)),D$6,MAX(0,SUMIFS($B$9:$B17,$A$9:$A17,"<"&$A17,$A$9:$A17,">="&D$4,$A$9:$A17,"<="&D$5)-SUM(_xlfn._xlws.FILTER(D18:D97,$A18:$A97>D$4),_xlfn._xlws.FILTER($C$9:C97,$A$9:$A97>D$4)))),"")} | E17: {=IF(AND(($A17<>"")*($A17>E$4)*($A17<=E$5)),IF(AND((SUMIFS($B$9:$B17,$A$9:$A17,"<"&$A17,$A$9:$A17,">="&E$4,$A$9:$A17,"<="&E$5)>SUM(_xlfn._xlws.FILTER(E18:E97,$A18:$A97>E$4),_xlfn._xlws.FILTER($C$9:D97,$A$9:$A97>E$4))),(SUMIFS($B$9:$B17,$A$9:$A17,"<"&$A17,$A$9:$A17,">="&E$4,$A$9:$A17,"<="&E$5)-SUM(_xlfn._xlws.FILTER(E18:E97,$A18:$A97>E$4),_xlfn._xlws.FILTER($C$9:D97,$A$9:$A97>E$4))>E$6)),E$6,MAX(0,SUMIFS($B$9:$B17,$A$9:$A17,"<"&$A17,$A$9:$A17,">="&E$4,$A$9:$A17,"<="&E$5)-SUM(_xlfn._xlws.FILTER(E18:E97,$A18:$A97>E$4),_xlfn._xlws.FILTER($C$9:D97,$A$9:$A97>E$4)))),"")} | F17: {=IF(AND(($A17<>"")*($A17>F$4)*($A17<=F$5)),IF(AND((SUMIFS($B$9:$B17,$A$9:$A17,"<"&$A17,$A$9:$A17,">="&F$4,$A$9:$A17,"<="&F$5)>SUM(_xlfn._xlws.FILTER(F18:F97,$A18:$A97>F$4),_xlfn._xlws.FILTER($C$9:E97,$A$9:$A97>F$4))),(SUMIFS($B$9:$B17,$A$9:$A17,"<"&$A17,$A$9:$A17,">="&F$4,$A$9:$A17,"<="&F$5)-SUM(_xlfn._xlws.FILTER(F18:F97,$A18:$A97>F$4),_xlfn._xlws.FILTER($C$9:E97,$A$9:$A97>F$4))>F$6)),F$6,MAX(0,SUMIFS($B$9:$B17,$A$9:$A17,"<"&$A17,$A$9:$A17,">="&F$4,$A$9:$A17,"<="&F$5)-SUM(_xlfn._xlws.FILTER(F18:F97,$A18:$A97>F$4),_xlfn._xlws.FILTER($C$9:E97,$A$9:$A97>F$4)))),"")} | G17: {=IF(AND(($A17<>"")*($A17>G$4)*($A17<=G$5)),IF(AND((SUMIFS($B$9:$B17,$A$9:$A17,"<"&$A17,$A$9:$A17,">="&G$4,$A$9:$A17,"<="&G$5)>SUM(_xlfn._xlws.FILTER(G18:G97,$A18:$A97>G$4),_xlfn._xlws.FILTER($C$9:F97,$A$9:$A97>G$4))),(SUMIFS($B$9:$B17,$A$9:$A17,"<"&$A17,$A$9:$A17,">="&G$4,$A$9:$A17,"<="&G$5)-SUM(_xlfn._xlws.FILTER(G18:G97,$A18:$A97>G$4),_xlfn._xlws.FILTER($C$9:F97,$A$9:$A97>G$4))>G$6)),G$6,MAX(0,SUMIFS($B$9:$B17,$A$9:$A17,"<"&$A17,$A$9:$A17,">="&G$4,$A$9:$A17,"<="&G$5)-SUM(_xlfn._xlws.FILTER(G18:G97,$A18:$A97>G$4),_xlfn._xlws.FILTER($C$9:F97,$A$9:$A97>G$4)))),"")} | H17: {=IF(AND(($A17<>"")*($A17>H$4)*($A17<=H$5)),IF(AND((SUMIFS($B$9:$B17,$A$9:$A17,"<"&$A17,$A$9:$A17,">="&H$4,$A$9:$A17,"<="&H$5)>SUM(_xlfn._xlws.FILTER(H18:H97,$A18:$A97>H$4),_xlfn._xlws.FILTER($C$9:G97,$A$9:$A97>H$4))),(SUMIFS($B$9:$B17,$A$9:$A17,"<"&$A17,$A$9:$A17,">="&H$4,$A$9:$A17,"<="&H$5)-SUM(_xlfn._xlws.FILTER(H18:H97,$A18:$A97>H$4),_xlfn._xlws.FILTER($C$9:G97,$A$9:$A97>H$4))>H$6)),H$6,MAX(0,SUMIFS($B$9:$B17,$A$9:$A17,"<"&$A17,$A$9:$A17,">="&H$4,$A$9:$A17,"<="&H$5)-SUM(_xlfn._xlws.FILTER(H18:H97,$A18:$A97>H$4),_xlfn._xlws.FILTER($C$9:G97,$A$9:$A97>H$4)))),"")} | I17: {=IF(AND(($A17<>"")*($A17>I$4)*($A17<=I$5)),IF(AND((SUMIFS($B$9:$B17,$A$9:$A17,"<"&$A17,$A$9:$A17,">="&I$4,$A$9:$A17,"<="&I$5)>SUM(_xlfn._xlws.FILTER(I18:I97,$A18:$A97>I$4),_xlfn._xlws.FILTER($C$9:H97,$A$9:$A97>I$4))),(SUMIFS($B$9:$B17,$A$9:$A17,"<"&$A17,$A$9:$A17,">="&I$4,$A$9:$A17,"<="&I$5)-SUM(_xlfn._xlws.FILTER(I18:I97,$A18:$A97>I$4),_xlfn._xlws.FILTER($C$9:H97,$A$9:$A97>I$4))>I$6)),I$6,MAX(0,SUMIFS($B$9:$B17,$A$9:$A17,"<"&$A17,$A$9:$A17,">="&I$4,$A$9:$A17,"<="&I$5)-SUM(_xlfn._xlws.FILTER(I18:I97,$A18:$A97>I$4),_xlfn._xlws.FILTER($C$9:H97,$A$9:$A97>I$4)))),"")} | J17: {=IF(AND(($A17<>"")*($A17>J$4)*($A17<=J$5)),IF(AND((SUMIFS($B$9:$B17,$A$9:$A17,"<"&$A17,$A$9:$A17,">="&J$4,$A$9:$A17,"<="&J$5)>SUM(_xlfn._xlws.FILTER(J18:J97,$A18:$A97>J$4),_xlfn._xlws.FILTER($C$9:I97,$A$9:$A97>J$4))),(SUMIFS($B$9:$B17,$A$9:$A17,"<"&$A17,$A$9:$A17,">="&J$4,$A$9:$A17,"<="&J$5)-SUM(_xlfn._xlws.FILTER(J18:J97,$A18:$A97>J$4),_xlfn._xlws.FILTER($C$9:I97,$A$9:$A97>J$4))>J$6)),J$6,MAX(0,SUMIFS($B$9:$B17,$A$9:$A17,"<"&$A17,$A$9:$A17,">="&J$4,$A$9:$A17,"<="&J$5)-SUM(_xlfn._xlws.FILTER(J18:J97,$A18:$A97>J$4),_xlfn._xlws.FILTER($C$9:I97,$A$9:$A97>J$4)))),"")} | K17: {=IF(AND(($A17<>"")*($A17>K$4)*($A17<=K$5)),IF(AND((SUMIFS($B$9:$B17,$A$9:$A17,"<"&$A17,$A$9:$A17,">="&K$4,$A$9:$A17,"<="&K$5)>SUM(_xlfn._xlws.FILTER(K18:K97,$A18:$A97>K$4),_xlfn._xlws.FILTER($C$9:J97,$A$9:$A97>K$4))),(SUMIFS($B$9:$B17,$A$9:$A17,"<"&$A17,$A$9:$A17,">="&K$4,$A$9:$A17,"<="&K$5)-SUM(_xlfn._xlws.FILTER(K18:K97,$A18:$A97>K$4),_xlfn._xlws.FILTER($C$9:J97,$A$9:$A97>K$4))>K$6)),K$6,MAX(0,SUMIFS($B$9:$B17,$A$9:$A17,"<"&$A17,$A$9:$A17,">="&K$4,$A$9:$A17,"<="&K$5)-SUM(_xlfn._xlws.FILTER(K18:K97,$A18:$A97>K$4),_xlfn._xlws.FILTER($C$9:J97,$A$9:$A97>K$4)))),"")} | ... HS17: {=IF(AND(($A17<>"")*($A17>HS$4)*($A17<=HS$5)),IF(AND((SUMIFS($B$9:$B17,$A$9:$A17,"<"&$A17,$A$9:$A17,">="&HS$4,$A$9:$A17,"<="&HS$5)>SUM(_xlfn._xlws.FILTER(HS18:HS97,$A18:$A97>HS$4),_xlfn._xlws.FILTER($C$9:HR97,$A$9:$A97>HS$4))),(SUMIFS($B$9:$B17,$A$9:$A17,"<"&$A17,$A$9:$A17,">="&HS$4,$A$9:$A17,"<="&HS$5)-SUM(_xlfn._xlws.FILTER(HS18:HS97,$A18:$A97>HS$4),_xlfn._xlws.FILTER($C$9:HR97,$A$9:$A97>HS$4))>HS$6)),HS$6,MAX(0,SUMIFS($B$9:$B17,$A$9:$A17,"<"&$A17,$A$9:$A17,">="&HS$4,$A$9:$A17,"<="&HS$5)-SUM(_xlfn._xlws.FILTER(HS18:HS97,$A18:$A97>HS$4),_xlfn._xlws.FILTER($C$9:HR97,$A$9:$A97>HS$4)))),"")}
A18: 45627 | B18: =VLOOKUP(A18,Table5[],7,FALSE) -> 0 | D18: {=IF(AND(($A18<>"")*($A18>D$4)*($A18<=D$5)),IF(AND((SUMIFS($B$9:$B18,$A$9:$A18,"<"&$A18,$A$9:$A18,">="&D$4,$A$9:$A18,"<="&D$5)>SUM(_xlfn._xlws.FILTER(D19:D98,$A19:$A98>D$4),_xlfn._xlws.FILTER($C$9:C98,$A$9:$A98>D$4))),(SUMIFS($B$9:$B18,$A$9:$A18,"<"&$A18,$A$9:$A18,">="&D$4,$A$9:$A18,"<="&D$5)-SUM(_xlfn._xlws.FILTER(D19:D98,$A19:$A98>D$4),_xlfn._xlws.FILTER($C$9:C98,$A$9:$A98>D$4))>D$6)),D$6,MAX(0,SUMIFS($B$9:$B18,$A$9:$A18,"<"&$A18,$A$9:$A18,">="&D$4,$A$9:$A18,"<="&D$5)-SUM(_xlfn._xlws.FILTER(D19:D98,$A19:$A98>D$4),_xlfn._xlws.FILTER($C$9:C98,$A$9:$A98>D$4)))),"")} | E18: {=IF(AND(($A18<>"")*($A18>E$4)*($A18<=E$5)),IF(AND((SUMIFS($B$9:$B18,$A$9:$A18,"<"&$A18,$A$9:$A18,">="&E$4,$A$9:$A18,"<="&E$5)>SUM(_xlfn._xlws.FILTER(E19:E98,$A19:$A98>E$4),_xlfn._xlws.FILTER($C$9:D98,$A$9:$A98>E$4))),(SUMIFS($B$9:$B18,$A$9:$A18,"<"&$A18,$A$9:$A18,">="&E$4,$A$9:$A18,"<="&E$5)-SUM(_xlfn._xlws.FILTER(E19:E98,$A19:$A98>E$4),_xlfn._xlws.FILTER($C$9:D98,$A$9:$A98>E$4))>E$6)),E$6,MAX(0,SUMIFS($B$9:$B18,$A$9:$A18,"<"&$A18,$A$9:$A18,">="&E$4,$A$9:$A18,"<="&E$5)-SUM(_xlfn._xlws.FILTER(E19:E98,$A19:$A98>E$4),_xlfn._xlws.FILTER($C$9:D98,$A$9:$A98>E$4)))),"")} | F18: {=IF(AND(($A18<>"")*($A18>F$4)*($A18<=F$5)),IF(AND((SUMIFS($B$9:$B18,$A$9:$A18,"<"&$A18,$A$9:$A18,">="&F$4,$A$9:$A18,"<="&F$5)>SUM(_xlfn._xlws.FILTER(F19:F98,$A19:$A98>F$4),_xlfn._xlws.FILTER($C$9:E98,$A$9:$A98>F$4))),(SUMIFS($B$9:$B18,$A$9:$A18,"<"&$A18,$A$9:$A18,">="&F$4,$A$9:$A18,"<="&F$5)-SUM(_xlfn._xlws.FILTER(F19:F98,$A19:$A98>F$4),_xlfn._xlws.FILTER($C$9:E98,$A$9:$A98>F$4))>F$6)),F$6,MAX(0,SUMIFS($B$9:$B18,$A$9:$A18,"<"&$A18,$A$9:$A18,">="&F$4,$A$9:$A18,"<="&F$5)-SUM(_xlfn._xlws.FILTER(F19:F98,$A19:$A98>F$4),_xlfn._xlws.FILTER($C$9:E98,$A$9:$A98>F$4)))),"")} | G18: {=IF(AND(($A18<>"")*($A18>G$4)*($A18<=G$5)),IF(AND((SUMIFS($B$9:$B18,$A$9:$A18,"<"&$A18,$A$9:$A18,">="&G$4,$A$9:$A18,"<="&G$5)>SUM(_xlfn._xlws.FILTER(G19:G98,$A19:$A98>G$4),_xlfn._xlws.FILTER($C$9:F98,$A$9:$A98>G$4))),(SUMIFS($B$9:$B18,$A$9:$A18,"<"&$A18,$A$9:$A18,">="&G$4,$A$9:$A18,"<="&G$5)-SUM(_xlfn._xlws.FILTER(G19:G98,$A19:$A98>G$4),_xlfn._xlws.FILTER($C$9:F98,$A$9:$A98>G$4))>G$6)),G$6,MAX(0,SUMIFS($B$9:$B18,$A$9:$A18,"<"&$A18,$A$9:$A18,">="&G$4,$A$9:$A18,"<="&G$5)-SUM(_xlfn._xlws.FILTER(G19:G98,$A19:$A98>G$4),_xlfn._xlws.FILTER($C$9:F98,$A$9:$A98>G$4)))),"")} | H18: {=IF(AND(($A18<>"")*($A18>H$4)*($A18<=H$5)),IF(AND((SUMIFS($B$9:$B18,$A$9:$A18,"<"&$A18,$A$9:$A18,">="&H$4,$A$9:$A18,"<="&H$5)>SUM(_xlfn._xlws.FILTER(H19:H98,$A19:$A98>H$4),_xlfn._xlws.FILTER($C$9:G98,$A$9:$A98>H$4))),(SUMIFS($B$9:$B18,$A$9:$A18,"<"&$A18,$A$9:$A18,">="&H$4,$A$9:$A18,"<="&H$5)-SUM(_xlfn._xlws.FILTER(H19:H98,$A19:$A98>H$4),_xlfn._xlws.FILTER($C$9:G98,$A$9:$A98>H$4))>H$6)),H$6,MAX(0,SUMIFS($B$9:$B18,$A$9:$A18,"<"&$A18,$A$9:$A18,">="&H$4,$A$9:$A18,"<="&H$5)-SUM(_xlfn._xlws.FILTER(H19:H98,$A19:$A98>H$4),_xlfn._xlws.FILTER($C$9:G98,$A$9:$A98>H$4)))),"")} | I18: {=IF(AND(($A18<>"")*($A18>I$4)*($A18<=I$5)),IF(AND((SUMIFS($B$9:$B18,$A$9:$A18,"<"&$A18,$A$9:$A18,">="&I$4,$A$9:$A18,"<="&I$5)>SUM(_xlfn._xlws.FILTER(I19:I98,$A19:$A98>I$4),_xlfn._xlws.FILTER($C$9:H98,$A$9:$A98>I$4))),(SUMIFS($B$9:$B18,$A$9:$A18,"<"&$A18,$A$9:$A18,">="&I$4,$A$9:$A18,"<="&I$5)-SUM(_xlfn._xlws.FILTER(I19:I98,$A19:$A98>I$4),_xlfn._xlws.FILTER($C$9:H98,$A$9:$A98>I$4))>I$6)),I$6,MAX(0,SUMIFS($B$9:$B18,$A$9:$A18,"<"&$A18,$A$9:$A18,">="&I$4,$A$9:$A18,"<="&I$5)-SUM(_xlfn._xlws.FILTER(I19:I98,$A19:$A98>I$4),_xlfn._xlws.FILTER($C$9:H98,$A$9:$A98>I$4)))),"")} | J18: {=IF(AND(($A18<>"")*($A18>J$4)*($A18<=J$5)),IF(AND((SUMIFS($B$9:$B18,$A$9:$A18,"<"&$A18,$A$9:$A18,">="&J$4,$A$9:$A18,"<="&J$5)>SUM(_xlfn._xlws.FILTER(J19:J98,$A19:$A98>J$4),_xlfn._xlws.FILTER($C$9:I98,$A$9:$A98>J$4))),(SUMIFS($B$9:$B18,$A$9:$A18,"<"&$A18,$A$9:$A18,">="&J$4,$A$9:$A18,"<="&J$5)-SUM(_xlfn._xlws.FILTER(J19:J98,$A19:$A98>J$4),_xlfn._xlws.FILTER($C$9:I98,$A$9:$A98>J$4))>J$6)),J$6,MAX(0,SUMIFS($B$9:$B18,$A$9:$A18,"<"&$A18,$A$9:$A18,">="&J$4,$A$9:$A18,"<="&J$5)-SUM(_xlfn._xlws.FILTER(J19:J98,$A19:$A98>J$4),_xlfn._xlws.FILTER($C$9:I98,$A$9:$A98>J$4)))),"")} | K18: {=IF(AND(($A18<>"")*($A18>K$4)*($A18<=K$5)),IF(AND((SUMIFS($B$9:$B18,$A$9:$A18,"<"&$A18,$A$9:$A18,">="&K$4,$A$9:$A18,"<="&K$5)>SUM(_xlfn._xlws.FILTER(K19:K98,$A19:$A98>K$4),_xlfn._xlws.FILTER($C$9:J98,$A$9:$A98>K$4))),(SUMIFS($B$9:$B18,$A$9:$A18,"<"&$A18,$A$9:$A18,">="&K$4,$A$9:$A18,"<="&K$5)-SUM(_xlfn._xlws.FILTER(K19:K98,$A19:$A98>K$4),_xlfn._xlws.FILTER($C$9:J98,$A$9:$A98>K$4))>K$6)),K$6,MAX(0,SUMIFS($B$9:$B18,$A$9:$A18,"<"&$A18,$A$9:$A18,">="&K$4,$A$9:$A18,"<="&K$5)-SUM(_xlfn._xlws.FILTER(K19:K98,$A19:$A98>K$4),_xlfn._xlws.FILTER($C$9:J98,$A$9:$A98>K$4)))),"")} | ... HS18: {=IF(AND(($A18<>"")*($A18>HS$4)*($A18<=HS$5)),IF(AND((SUMIFS($B$9:$B18,$A$9:$A18,"<"&$A18,$A$9:$A18,">="&HS$4,$A$9:$A18,"<="&HS$5)>SUM(_xlfn._xlws.FILTER(HS19:HS98,$A19:$A98>HS$4),_xlfn._xlws.FILTER($C$9:HR98,$A$9:$A98>HS$4))),(SUMIFS($B$9:$B18,$A$9:$A18,"<"&$A18,$A$9:$A18,">="&HS$4,$A$9:$A18,"<="&HS$5)-SUM(_xlfn._xlws.FILTER(HS19:HS98,$A19:$A98>HS$4),_xlfn._xlws.FILTER($C$9:HR98,$A$9:$A98>HS$4))>HS$6)),HS$6,MAX(0,SUMIFS($B$9:$B18,$A$9:$A18,"<"&$A18,$A$9:$A18,">="&HS$4,$A$9:$A18,"<="&HS$5)-SUM(_xlfn._xlws.FILTER(HS19:HS98,$A19:$A98>HS$4),_xlfn._xlws.FILTER($C$9:HR98,$A$9:$A98>HS$4)))),"")}
A19: 45658 | B19: =VLOOKUP(A19,Table5[],7,FALSE) -> 0 | D19: {=IF(AND(($A19<>"")*($A19>D$4)*($A19<=D$5)),IF(AND((SUMIFS($B$9:$B19,$A$9:$A19,"<"&$A19,$A$9:$A19,">="&D$4,$A$9:$A19,"<="&D$5)>SUM(_xlfn._xlws.FILTER(D20:D99,$A20:$A99>D$4),_xlfn._xlws.FILTER($C$9:C99,$A$9:$A99>D$4))),(SUMIFS($B$9:$B19,$A$9:$A19,"<"&$A19,$A$9:$A19,">="&D$4,$A$9:$A19,"<="&D$5)-SUM(_xlfn._xlws.FILTER(D20:D99,$A20:$A99>D$4),_xlfn._xlws.FILTER($C$9:C99,$A$9:$A99>D$4))>D$6)),D$6,MAX(0,SUMIFS($B$9:$B19,$A$9:$A19,"<"&$A19,$A$9:$A19,">="&D$4,$A$9:$A19,"<="&D$5)-SUM(_xlfn._xlws.FILTER(D20:D99,$A20:$A99>D$4),_xlfn._xlws.FILTER($C$9:C99,$A$9:$A99>D$4)))),"")} | E19: {=IF(AND(($A19<>"")*($A19>E$4)*($A19<=E$5)),IF(AND((SUMIFS($B$9:$B19,$A$9:$A19,"<"&$A19,$A$9:$A19,">="&E$4,$A$9:$A19,"<="&E$5)>SUM(_xlfn._xlws.FILTER(E20:E99,$A20:$A99>E$4),_xlfn._xlws.FILTER($C$9:D99,$A$9:$A99>E$4))),(SUMIFS($B$9:$B19,$A$9:$A19,"<"&$A19,$A$9:$A19,">="&E$4,$A$9:$A19,"<="&E$5)-SUM(_xlfn._xlws.FILTER(E20:E99,$A20:$A99>E$4),_xlfn._xlws.FILTER($C$9:D99,$A$9:$A99>E$4))>E$6)),E$6,MAX(0,SUMIFS($B$9:$B19,$A$9:$A19,"<"&$A19,$A$9:$A19,">="&E$4,$A$9:$A19,"<="&E$5)-SUM(_xlfn._xlws.FILTER(E20:E99,$A20:$A99>E$4),_xlfn._xlws.FILTER($C$9:D99,$A$9:$A99>E$4)))),"")} | F19: {=IF(AND(($A19<>"")*($A19>F$4)*($A19<=F$5)),IF(AND((SUMIFS($B$9:$B19,$A$9:$A19,"<"&$A19,$A$9:$A19,">="&F$4,$A$9:$A19,"<="&F$5)>SUM(_xlfn._xlws.FILTER(F20:F99,$A20:$A99>F$4),_xlfn._xlws.FILTER($C$9:E99,$A$9:$A99>F$4))),(SUMIFS($B$9:$B19,$A$9:$A19,"<"&$A19,$A$9:$A19,">="&F$4,$A$9:$A19,"<="&F$5)-SUM(_xlfn._xlws.FILTER(F20:F99,$A20:$A99>F$4),_xlfn._xlws.FILTER($C$9:E99,$A$9:$A99>F$4))>F$6)),F$6,MAX(0,SUMIFS($B$9:$B19,$A$9:$A19,"<"&$A19,$A$9:$A19,">="&F$4,$A$9:$A19,"<="&F$5)-SUM(_xlfn._xlws.FILTER(F20:F99,$A20:$A99>F$4),_xlfn._xlws.FILTER($C$9:E99,$A$9:$A99>F$4)))),"")} | G19: {=IF(AND(($A19<>"")*($A19>G$4)*($A19<=G$5)),IF(AND((SUMIFS($B$9:$B19,$A$9:$A19,"<"&$A19,$A$9:$A19,">="&G$4,$A$9:$A19,"<="&G$5)>SUM(_xlfn._xlws.FILTER(G20:G99,$A20:$A99>G$4),_xlfn._xlws.FILTER($C$9:F99,$A$9:$A99>G$4))),(SUMIFS($B$9:$B19,$A$9:$A19,"<"&$A19,$A$9:$A19,">="&G$4,$A$9:$A19,"<="&G$5)-SUM(_xlfn._xlws.FILTER(G20:G99,$A20:$A99>G$4),_xlfn._xlws.FILTER($C$9:F99,$A$9:$A99>G$4))>G$6)),G$6,MAX(0,SUMIFS($B$9:$B19,$A$9:$A19,"<"&$A19,$A$9:$A19,">="&G$4,$A$9:$A19,"<="&G$5)-SUM(_xlfn._xlws.FILTER(G20:G99,$A20:$A99>G$4),_xlfn._xlws.FILTER($C$9:F99,$A$9:$A99>G$4)))),"")} -> 0 | H19: {=IF(AND(($A19<>"")*($A19>H$4)*($A19<=H$5)),IF(AND((SUMIFS($B$9:$B19,$A$9:$A19,"<"&$A19,$A$9:$A19,">="&H$4,$A$9:$A19,"<="&H$5)>SUM(_xlfn._xlws.FILTER(H20:H99,$A20:$A99>H$4),_xlfn._xlws.FILTER($C$9:G99,$A$9:$A99>H$4))),(SUMIFS($B$9:$B19,$A$9:$A19,"<"&$A19,$A$9:$A19,">="&H$4,$A$9:$A19,"<="&H$5)-SUM(_xlfn._xlws.FILTER(H20:H99,$A20:$A99>H$4),_xlfn._xlws.FILTER($C$9:G99,$A$9:$A99>H$4))>H$6)),H$6,MAX(0,SUMIFS($B$9:$B19,$A$9:$A19,"<"&$A19,$A$9:$A19,">="&H$4,$A$9:$A19,"<="&H$5)-SUM(_xlfn._xlws.FILTER(H20:H99,$A20:$A99>H$4),_xlfn._xlws.FILTER($C$9:G99,$A$9:$A99>H$4)))),"")} | I19: {=IF(AND(($A19<>"")*($A19>I$4)*($A19<=I$5)),IF(AND((SUMIFS($B$9:$B19,$A$9:$A19,"<"&$A19,$A$9:$A19,">="&I$4,$A$9:$A19,"<="&I$5)>SUM(_xlfn._xlws.FILTER(I20:I99,$A20:$A99>I$4),_xlfn._xlws.FILTER($C$9:H99,$A$9:$A99>I$4))),(SUMIFS($B$9:$B19,$A$9:$A19,"<"&$A19,$A$9:$A19,">="&I$4,$A$9:$A19,"<="&I$5)-SUM(_xlfn._xlws.FILTER(I20:I99,$A20:$A99>I$4),_xlfn._xlws.FILTER($C$9:H99,$A$9:$A99>I$4))>I$6)),I$6,MAX(0,SUMIFS($B$9:$B19,$A$9:$A19,"<"&$A19,$A$9:$A19,">="&I$4,$A$9:$A19,"<="&I$5)-SUM(_xlfn._xlws.FILTER(I20:I99,$A20:$A99>I$4),_xlfn._xlws.FILTER($C$9:H99,$A$9:$A99>I$4)))),"")} | J19: {=IF(AND(($A19<>"")*($A19>J$4)*($A19<=J$5)),IF(AND((SUMIFS($B$9:$B19,$A$9:$A19,"<"&$A19,$A$9:$A19,">="&J$4,$A$9:$A19,"<="&J$5)>SUM(_xlfn._xlws.FILTER(J20:J99,$A20:$A99>J$4),_xlfn._xlws.FILTER($C$9:I99,$A$9:$A99>J$4))),(SUMIFS($B$9:$B19,$A$9:$A19,"<"&$A19,$A$9:$A19,">="&J$4,$A$9:$A19,"<="&J$5)-SUM(_xlfn._xlws.FILTER(J20:J99,$A20:$A99>J$4),_xlfn._xlws.FILTER($C$9:I99,$A$9:$A99>J$4))>J$6)),J$6,MAX(0,SUMIFS($B$9:$B19,$A$9:$A19,"<"&$A19,$A$9:$A19,">="&J$4,$A$9:$A19,"<="&J$5)-SUM(_xlfn._xlws.FILTER(J20:J99,$A20:$A99>J$4),_xlfn._xlws.FILTER($C$9:I99,$A$9:$A99>J$4)))),"")} | K19: {=IF(AND(($A19<>"")*($A19>K$4)*($A19<=K$5)),IF(AND((SUMIFS($B$9:$B19,$A$9:$A19,"<"&$A19,$A$9:$A19,">="&K$4,$A$9:$A19,"<="&K$5)>SUM(_xlfn._xlws.FILTER(K20:K99,$A20:$A99>K$4),_xlfn._xlws.FILTER($C$9:J99,$A$9:$A99>K$4))),(SUMIFS($B$9:$B19,$A$9:$A19,"<"&$A19,$A$9:$A19,">="&K$4,$A$9:$A19,"<="&K$5)-SUM(_xlfn._xlws.FILTER(K20:K99,$A20:$A99>K$4),_xlfn._xlws.FILTER($C$9:J99,$A$9:$A99>K$4))>K$6)),K$6,MAX(0,SUMIFS($B$9:$B19,$A$9:$A19,"<"&$A19,$A$9:$A19,">="&K$4,$A$9:$A19,"<="&K$5)-SUM(_xlfn._xlws.FILTER(K20:K99,$A20:$A99>K$4),_xlfn._xlws.FILTER($C$9:J99,$A$9:$A99>K$4)))),"")} | ... HS19: {=IF(AND(($A19<>"")*($A19>HS$4)*($A19<=HS$5)),IF(AND((SUMIFS($B$9:$B19,$A$9:$A19,"<"&$A19,$A$9:$A19,">="&HS$4,$A$9:$A19,"<="&HS$5)>SUM(_xlfn._xlws.FILTER(HS20:HS99,$A20:$A99>HS$4),_xlfn._xlws.FILTER($C$9:HR99,$A$9:$A99>HS$4))),(SUMIFS($B$9:$B19,$A$9:$A19,"<"&$A19,$A$9:$A19,">="&HS$4,$A$9:$A19,"<="&HS$5)-SUM(_xlfn._xlws.FILTER(HS20:HS99,$A20:$A99>HS$4),_xlfn._xlws.FILTER($C$9:HR99,$A$9:$A99>HS$4))>HS$6)),HS$6,MAX(0,SUMIFS($B$9:$B19,$A$9:$A19,"<"&$A19,$A$9:$A19,">="&HS$4,$A$9:$A19,"<="&HS$5)-SUM(_xlfn._xlws.FILTER(HS20:HS99,$A20:$A99>HS$4),_xlfn._xlws.FILTER($C$9:HR99,$A$9:$A99>HS$4)))),"")}
A20: 45689 | B20: =VLOOKUP(A20,Table5[],7,FALSE) -> 0 | D20: {=IF(AND(($A20<>"")*($A20>D$4)*($A20<=D$5)),IF(AND((SUMIFS($B$9:$B20,$A$9:$A20,"<"&$A20,$A$9:$A20,">="&D$4,$A$9:$A20,"<="&D$5)>SUM(_xlfn._xlws.FILTER(D21:D100,$A21:$A100>D$4),_xlfn._xlws.FILTER($C$9:C100,$A$9:$A100>D$4))),(SUMIFS($B$9:$B20,$A$9:$A20,"<"&$A20,$A$9:$A20,">="&D$4,$A$9:$A20,"<="&D$5)-SUM(_xlfn._xlws.FILTER(D21:D100,$A21:$A100>D$4),_xlfn._xlws.FILTER($C$9:C100,$A$9:$A100>D$4))>D$6)),D$6,MAX(0,SUMIFS($B$9:$B20,$A$9:$A20,"<"&$A20,$A$9:$A20,">="&D$4,$A$9:$A20,"<="&D$5)-SUM(_xlfn._xlws.FILTER(D21:D100,$A21:$A100>D$4),_xlfn._xlws.FILTER($C$9:C100,$A$9:$A100>D$4)))),"")} | E20: {=IF(AND(($A20<>"")*($A20>E$4)*($A20<=E$5)),IF(AND((SUMIFS($B$9:$B20,$A$9:$A20,"<"&$A20,$A$9:$A20,">="&E$4,$A$9:$A20,"<="&E$5)>SUM(_xlfn._xlws.FILTER(E21:E100,$A21:$A100>E$4),_xlfn._xlws.FILTER($C$9:D100,$A$9:$A100>E$4))),(SUMIFS($B$9:$B20,$A$9:$A20,"<"&$A20,$A$9:$A20,">="&E$4,$A$9:$A20,"<="&E$5)-SUM(_xlfn._xlws.FILTER(E21:E100,$A21:$A100>E$4),_xlfn._xlws.FILTER($C$9:D100,$A$9:$A100>E$4))>E$6)),E$6,MAX(0,SUMIFS($B$9:$B20,$A$9:$A20,"<"&$A20,$A$9:$A20,">="&E$4,$A$9:$A20,"<="&E$5)-SUM(_xlfn._xlws.FILTER(E21:E100,$A21:$A100>E$4),_xlfn._xlws.FILTER($C$9:D100,$A$9:$A100>E$4)))),"")} | F20: {=IF(AND(($A20<>"")*($A20>F$4)*($A20<=F$5)),IF(AND((SUMIFS($B$9:$B20,$A$9:$A20,"<"&$A20,$A$9:$A20,">="&F$4,$A$9:$A20,"<="&F$5)>SUM(_xlfn._xlws.FILTER(F21:F100,$A21:$A100>F$4),_xlfn._xlws.FILTER($C$9:E100,$A$9:$A100>F$4))),(SUMIFS($B$9:$B20,$A$9:$A20,"<"&$A20,$A$9:$A20,">="&F$4,$A$9:$A20,"<="&F$5)-SUM(_xlfn._xlws.FILTER(F21:F100,$A21:$A100>F$4),_xlfn._xlws.FILTER($C$9:E100,$A$9:$A100>F$4))>F$6)),F$6,MAX(0,SUMIFS($B$9:$B20,$A$9:$A20,"<"&$A20,$A$9:$A20,">="&F$4,$A$9:$A20,"<="&F$5)-SUM(_xlfn._xlws.FILTER(F21:F100,$A21:$A100>F$4),_xlfn._xlws.FILTER($C$9:E100,$A$9:$A100>F$4)))),"")} | G20: {=IF(AND(($A20<>"")*($A20>G$4)*($A20<=G$5)),IF(AND((SUMIFS($B$9:$B20,$A$9:$A20,"<"&$A20,$A$9:$A20,">="&G$4,$A$9:$A20,"<="&G$5)>SUM(_xlfn._xlws.FILTER(G21:G100,$A21:$A100>G$4),_xlfn._xlws.FILTER($C$9:F100,$A$9:$A100>G$4))),(SUMIFS($B$9:$B20,$A$9:$A20,"<"&$A20,$A$9:$A20,">="&G$4,$A$9:$A20,"<="&G$5)-SUM(_xlfn._xlws.FILTER(G21:G100,$A21:$A100>G$4),_xlfn._xlws.FILTER($C$9:F100,$A$9:$A100>G$4))>G$6)),G$6,MAX(0,SUMIFS($B$9:$B20,$A$9:$A20,"<"&$A20,$A$9:$A20,">="&G$4,$A$9:$A20,"<="&G$5)-SUM(_xlfn._xlws.FILTER(G21:G100,$A21:$A100>G$4),_xlfn._xlws.FILTER($C$9:F100,$A$9:$A100>G$4)))),"")} -> 0 | H20: {=IF(AND(($A20<>"")*($A20>H$4)*($A20<=H$5)),IF(AND((SUMIFS($B$9:$B20,$A$9:$A20,"<"&$A20,$A$9:$A20,">="&H$4,$A$9:$A20,"<="&H$5)>SUM(_xlfn._xlws.FILTER(H21:H100,$A21:$A100>H$4),_xlfn._xlws.FILTER($C$9:G100,$A$9:$A100>H$4))),(SUMIFS($B$9:$B20,$A$9:$A20,"<"&$A20,$A$9:$A20,">="&H$4,$A$9:$A20,"<="&H$5)-SUM(_xlfn._xlws.FILTER(H21:H100,$A21:$A100>H$4),_xlfn._xlws.FILTER($C$9:G100,$A$9:$A100>H$4))>H$6)),H$6,MAX(0,SUMIFS($B$9:$B20,$A$9:$A20,"<"&$A20,$A$9:$A20,">="&H$4,$A$9:$A20,"<="&H$5)-SUM(_xlfn._xlws.FILTER(H21:H100,$A21:$A100>H$4),_xlfn._xlws.FILTER($C$9:G100,$A$9:$A100>H$4)))),"")} | I20: {=IF(AND(($A20<>"")*($A20>I$4)*($A20<=I$5)),IF(AND((SUMIFS($B$9:$B20,$A$9:$A20,"<"&$A20,$A$9:$A20,">="&I$4,$A$9:$A20,"<="&I$5)>SUM(_xlfn._xlws.FILTER(I21:I100,$A21:$A100>I$4),_xlfn._xlws.FILTER($C$9:H100,$A$9:$A100>I$4))),(SUMIFS($B$9:$B20,$A$9:$A20,"<"&$A20,$A$9:$A20,">="&I$4,$A$9:$A20,"<="&I$5)-SUM(_xlfn._xlws.FILTER(I21:I100,$A21:$A100>I$4),_xlfn._xlws.FILTER($C$9:H100,$A$9:$A100>I$4))>I$6)),I$6,MAX(0,SUMIFS($B$9:$B20,$A$9:$A20,"<"&$A20,$A$9:$A20,">="&I$4,$A$9:$A20,"<="&I$5)-SUM(_xlfn._xlws.FILTER(I21:I100,$A21:$A100>I$4),_xlfn._xlws.FILTER($C$9:H100,$A$9:$A100>I$4)))),"")} | J20: {=IF(AND(($A20<>"")*($A20>J$4)*($A20<=J$5)),IF(AND((SUMIFS($B$9:$B20,$A$9:$A20,"<"&$A20,$A$9:$A20,">="&J$4,$A$9:$A20,"<="&J$5)>SUM(_xlfn._xlws.FILTER(J21:J100,$A21:$A100>J$4),_xlfn._xlws.FILTER($C$9:I100,$A$9:$A100>J$4))),(SUMIFS($B$9:$B20,$A$9:$A20,"<"&$A20,$A$9:$A20,">="&J$4,$A$9:$A20,"<="&J$5)-SUM(_xlfn._xlws.FILTER(J21:J100,$A21:$A100>J$4),_xlfn._xlws.FILTER($C$9:I100,$A$9:$A100>J$4))>J$6)),J$6,MAX(0,SUMIFS($B$9:$B20,$A$9:$A20,"<"&$A20,$A$9:$A20,">="&J$4,$A$9:$A20,"<="&J$5)-SUM(_xlfn._xlws.FILTER(J21:J100,$A21:$A100>J$4),_xlfn._xlws.FILTER($C$9:I100,$A$9:$A100>J$4)))),"")} | K20: {=IF(AND(($A20<>"")*($A20>K$4)*($A20<=K$5)),IF(AND((SUMIFS($B$9:$B20,$A$9:$A20,"<"&$A20,$A$9:$A20,">="&K$4,$A$9:$A20,"<="&K$5)>SUM(_xlfn._xlws.FILTER(K21:K100,$A21:$A100>K$4),_xlfn._xlws.FILTER($C$9:J100,$A$9:$A100>K$4))),(SUMIFS($B$9:$B20,$A$9:$A20,"<"&$A20,$A$9:$A20,">="&K$4,$A$9:$A20,"<="&K$5)-SUM(_xlfn._xlws.FILTER(K21:K100,$A21:$A100>K$4),_xlfn._xlws.FILTER($C$9:J100,$A$9:$A100>K$4))>K$6)),K$6,MAX(0,SUMIFS($B$9:$B20,$A$9:$A20,"<"&$A20,$A$9:$A20,">="&K$4,$A$9:$A20,"<="&K$5)-SUM(_xlfn._xlws.FILTER(K21:K100,$A21:$A100>K$4),_xlfn._xlws.FILTER($C$9:J100,$A$9:$A100>K$4)))),"")} | ... HS20: {=IF(AND(($A20<>"")*($A20>HS$4)*($A20<=HS$5)),IF(AND((SUMIFS($B$9:$B20,$A$9:$A20,"<"&$A20,$A$9:$A20,">="&HS$4,$A$9:$A20,"<="&HS$5)>SUM(_xlfn._xlws.FILTER(HS21:HS100,$A21:$A100>HS$4),_xlfn._xlws.FILTER($C$9:HR100,$A$9:$A100>HS$4))),(SUMIFS($B$9:$B20,$A$9:$A20,"<"&$A20,$A$9:$A20,">="&HS$4,$A$9:$A20,"<="&HS$5)-SUM(_xlfn._xlws.FILTER(HS21:HS100,$A21:$A100>HS$4),_xlfn._xlws.FILTER($C$9:HR100,$A$9:$A100>HS$4))>HS$6)),HS$6,MAX(0,SUMIFS($B$9:$B20,$A$9:$A20,"<"&$A20,$A$9:$A20,">="&HS$4,$A$9:$A20,"<="&HS$5)-SUM(_xlfn._xlws.FILTER(HS21:HS100,$A21:$A100>HS$4),_xlfn._xlws.FILTER($C$9:HR100,$A$9:$A100>HS$4)))),"")}
A21: 45717 | B21: =VLOOKUP(A21,Table5[],7,FALSE) -> 0 | D21: {=IF(AND(($A21<>"")*($A21>D$4)*($A21<=D$5)),IF(AND((SUMIFS($B$9:$B21,$A$9:$A21,"<"&$A21,$A$9:$A21,">="&D$4,$A$9:$A21,"<="&D$5)>SUM(_xlfn._xlws.FILTER(D22:D101,$A22:$A101>D$4),_xlfn._xlws.FILTER($C$9:C101,$A$9:$A101>D$4))),(SUMIFS($B$9:$B21,$A$9:$A21,"<"&$A21,$A$9:$A21,">="&D$4,$A$9:$A21,"<="&D$5)-SUM(_xlfn._xlws.FILTER(D22:D101,$A22:$A101>D$4),_xlfn._xlws.FILTER($C$9:C101,$A$9:$A101>D$4))>D$6)),D$6,MAX(0,SUMIFS($B$9:$B21,$A$9:$A21,"<"&$A21,$A$9:$A21,">="&D$4,$A$9:$A21,"<="&D$5)-SUM(_xlfn._xlws.FILTER(D22:D101,$A22:$A101>D$4),_xlfn._xlws.FILTER($C$9:C101,$A$9:$A101>D$4)))),"")} | E21: {=IF(AND(($A21<>"")*($A21>E$4)*($A21<=E$5)),IF(AND((SUMIFS($B$9:$B21,$A$9:$A21,"<"&$A21,$A$9:$A21,">="&E$4,$A$9:$A21,"<="&E$5)>SUM(_xlfn._xlws.FILTER(E22:E101,$A22:$A101>E$4),_xlfn._xlws.FILTER($C$9:D101,$A$9:$A101>E$4))),(SUMIFS($B$9:$B21,$A$9:$A21,"<"&$A21,$A$9:$A21,">="&E$4,$A$9:$A21,"<="&E$5)-SUM(_xlfn._xlws.FILTER(E22:E101,$A22:$A101>E$4),_xlfn._xlws.FILTER($C$9:D101,$A$9:$A101>E$4))>E$6)),E$6,MAX(0,SUMIFS($B$9:$B21,$A$9:$A21,"<"&$A21,$A$9:$A21,">="&E$4,$A$9:$A21,"<="&E$5)-SUM(_xlfn._xlws.FILTER(E22:E101,$A22:$A101>E$4),_xlfn._xlws.FILTER($C$9:D101,$A$9:$A101>E$4)))),"")} | F21: {=IF(AND(($A21<>"")*($A21>F$4)*($A21<=F$5)),IF(AND((SUMIFS($B$9:$B21,$A$9:$A21,"<"&$A21,$A$9:$A21,">="&F$4,$A$9:$A21,"<="&F$5)>SUM(_xlfn._xlws.FILTER(F22:F101,$A22:$A101>F$4),_xlfn._xlws.FILTER($C$9:E101,$A$9:$A101>F$4))),(SUMIFS($B$9:$B21,$A$9:$A21,"<"&$A21,$A$9:$A21,">="&F$4,$A$9:$A21,"<="&F$5)-SUM(_xlfn._xlws.FILTER(F22:F101,$A22:$A101>F$4),_xlfn._xlws.FILTER($C$9:E101,$A$9:$A101>F$4))>F$6)),F$6,MAX(0,SUMIFS($B$9:$B21,$A$9:$A21,"<"&$A21,$A$9:$A21,">="&F$4,$A$9:$A21,"<="&F$5)-SUM(_xlfn._xlws.FILTER(F22:F101,$A22:$A101>F$4),_xlfn._xlws.FILTER($C$9:E101,$A$9:$A101>F$4)))),"")} | G21: {=IF(AND(($A21<>"")*($A21>G$4)*($A21<=G$5)),IF(AND((SUMIFS($B$9:$B21,$A$9:$A21,"<"&$A21,$A$9:$A21,">="&G$4,$A$9:$A21,"<="&G$5)>SUM(_xlfn._xlws.FILTER(G22:G101,$A22:$A101>G$4),_xlfn._xlws.FILTER($C$9:F101,$A$9:$A101>G$4))),(SUMIFS($B$9:$B21,$A$9:$A21,"<"&$A21,$A$9:$A21,">="&G$4,$A$9:$A21,"<="&G$5)-SUM(_xlfn._xlws.FILTER(G22:G101,$A22:$A101>G$4),_xlfn._xlws.FILTER($C$9:F101,$A$9:$A101>G$4))>G$6)),G$6,MAX(0,SUMIFS($B$9:$B21,$A$9:$A21,"<"&$A21,$A$9:$A21,">="&G$4,$A$9:$A21,"<="&G$5)-SUM(_xlfn._xlws.FILTER(G22:G101,$A22:$A101>G$4),_xlfn._xlws.FILTER($C$9:F101,$A$9:$A101>G$4)))),"")} -> 0 | H21: {=IF(AND(($A21<>"")*($A21>H$4)*($A21<=H$5)),IF(AND((SUMIFS($B$9:$B21,$A$9:$A21,"<"&$A21,$A$9:$A21,">="&H$4,$A$9:$A21,"<="&H$5)>SUM(_xlfn._xlws.FILTER(H22:H101,$A22:$A101>H$4),_xlfn._xlws.FILTER($C$9:G101,$A$9:$A101>H$4))),(SUMIFS($B$9:$B21,$A$9:$A21,"<"&$A21,$A$9:$A21,">="&H$4,$A$9:$A21,"<="&H$5)-SUM(_xlfn._xlws.FILTER(H22:H101,$A22:$A101>H$4),_xlfn._xlws.FILTER($C$9:G101,$A$9:$A101>H$4))>H$6)),H$6,MAX(0,SUMIFS($B$9:$B21,$A$9:$A21,"<"&$A21,$A$9:$A21,">="&H$4,$A$9:$A21,"<="&H$5)-SUM(_xlfn._xlws.FILTER(H22:H101,$A22:$A101>H$4),_xlfn._xlws.FILTER($C$9:G101,$A$9:$A101>H$4)))),"")} | I21: {=IF(AND(($A21<>"")*($A21>I$4)*($A21<=I$5)),IF(AND((SUMIFS($B$9:$B21,$A$9:$A21,"<"&$A21,$A$9:$A21,">="&I$4,$A$9:$A21,"<="&I$5)>SUM(_xlfn._xlws.FILTER(I22:I101,$A22:$A101>I$4),_xlfn._xlws.FILTER($C$9:H101,$A$9:$A101>I$4))),(SUMIFS($B$9:$B21,$A$9:$A21,"<"&$A21,$A$9:$A21,">="&I$4,$A$9:$A21,"<="&I$5)-SUM(_xlfn._xlws.FILTER(I22:I101,$A22:$A101>I$4),_xlfn._xlws.FILTER($C$9:H101,$A$9:$A101>I$4))>I$6)),I$6,MAX(0,SUMIFS($B$9:$B21,$A$9:$A21,"<"&$A21,$A$9:$A21,">="&I$4,$A$9:$A21,"<="&I$5)-SUM(_xlfn._xlws.FILTER(I22:I101,$A22:$A101>I$4),_xlfn._xlws.FILTER($C$9:H101,$A$9:$A101>I$4)))),"")} | J21: {=IF(AND(($A21<>"")*($A21>J$4)*($A21<=J$5)),IF(AND((SUMIFS($B$9:$B21,$A$9:$A21,"<"&$A21,$A$9:$A21,">="&J$4,$A$9:$A21,"<="&J$5)>SUM(_xlfn._xlws.FILTER(J22:J101,$A22:$A101>J$4),_xlfn._xlws.FILTER($C$9:I101,$A$9:$A101>J$4))),(SUMIFS($B$9:$B21,$A$9:$A21,"<"&$A21,$A$9:$A21,">="&J$4,$A$9:$A21,"<="&J$5)-SUM(_xlfn._xlws.FILTER(J22:J101,$A22:$A101>J$4),_xlfn._xlws.FILTER($C$9:I101,$A$9:$A101>J$4))>J$6)),J$6,MAX(0,SUMIFS($B$9:$B21,$A$9:$A21,"<"&$A21,$A$9:$A21,">="&J$4,$A$9:$A21,"<="&J$5)-SUM(_xlfn._xlws.FILTER(J22:J101,$A22:$A101>J$4),_xlfn._xlws.FILTER($C$9:I101,$A$9:$A101>J$4)))),"")} | K21: {=IF(AND(($A21<>"")*($A21>K$4)*($A21<=K$5)),IF(AND((SUMIFS($B$9:$B21,$A$9:$A21,"<"&$A21,$A$9:$A21,">="&K$4,$A$9:$A21,"<="&K$5)>SUM(_xlfn._xlws.FILTER(K22:K101,$A22:$A101>K$4),_xlfn._xlws.FILTER($C$9:J101,$A$9:$A101>K$4))),(SUMIFS($B$9:$B21,$A$9:$A21,"<"&$A21,$A$9:$A21,">="&K$4,$A$9:$A21,"<="&K$5)-SUM(_xlfn._xlws.FILTER(K22:K101,$A22:$A101>K$4),_xlfn._xlws.FILTER($C$9:J101,$A$9:$A101>K$4))>K$6)),K$6,MAX(0,SUMIFS($B$9:$B21,$A$9:$A21,"<"&$A21,$A$9:$A21,">="&K$4,$A$9:$A21,"<="&K$5)-SUM(_xlfn._xlws.FILTER(K22:K101,$A22:$A101>K$4),_xlfn._xlws.FILTER($C$9:J101,$A$9:$A101>K$4)))),"")} | ... HS21: {=IF(AND(($A21<>"")*($A21>HS$4)*($A21<=HS$5)),IF(AND((SUMIFS($B$9:$B21,$A$9:$A21,"<"&$A21,$A$9:$A21,">="&HS$4,$A$9:$A21,"<="&HS$5)>SUM(_xlfn._xlws.FILTER(HS22:HS101,$A22:$A101>HS$4),_xlfn._xlws.FILTER($C$9:HR101,$A$9:$A101>HS$4))),(SUMIFS($B$9:$B21,$A$9:$A21,"<"&$A21,$A$9:$A21,">="&HS$4,$A$9:$A21,"<="&HS$5)-SUM(_xlfn._xlws.FILTER(HS22:HS101,$A22:$A101>HS$4),_xlfn._xlws.FILTER($C$9:HR101,$A$9:$A101>HS$4))>HS$6)),HS$6,MAX(0,SUMIFS($B$9:$B21,$A$9:$A21,"<"&$A21,$A$9:$A21,">="&HS$4,$A$9:$A21,"<="&HS$5)-SUM(_xlfn._xlws.FILTER(HS22:HS101,$A22:$A101>HS$4),_xlfn._xlws.FILTER($C$9:HR101,$A$9:$A101>HS$4)))),"")}
... A24: 45809 | B24: =VLOOKUP(A24,Table5[],7,FALSE) -> 0 | D24: {=IF(AND(($A24<>"")*($A24>D$4)*($A24<=D$5)),IF(AND((SUMIFS($B$9:$B24,$A$9:$A24,"<"&$A24,$A$9:$A24,">="&D$4,$A$9:$A24,"<="&D$5)>SUM(_xlfn._xlws.FILTER(D25:D104,$A25:$A104>D$4),_xlfn._xlws.FILTER($C$9:C104,$A$9:$A104>D$4))),(SUMIFS($B$9:$B24,$A$9:$A24,"<"&$A24,$A$9:$A24,">="&D$4,$A$9:$A24,"<="&D$5)-SUM(_xlfn._xlws.FILTER(D25:D104,$A25:$A104>D$4),_xlfn._xlws.FILTER($C$9:C104,$A$9:$A104>D$4))>D$6)),D$6,MAX(0,SUMIFS($B$9:$B24,$A$9:$A24,"<"&$A24,$A$9:$A24,">="&D$4,$A$9:$A24,"<="&D$5)-SUM(_xlfn._xlws.FILTER(D25:D104,$A25:$A104>D$4),_xlfn._xlws.FILTER($C$9:C104,$A$9:$A104>D$4)))),"")} | E24: {=IF(AND(($A24<>"")*($A24>E$4)*($A24<=E$5)),IF(AND((SUMIFS($B$9:$B24,$A$9:$A24,"<"&$A24,$A$9:$A24,">="&E$4,$A$9:$A24,"<="&E$5)>SUM(_xlfn._xlws.FILTER(E25:E104,$A25:$A104>E$4),_xlfn._xlws.FILTER($C$9:D104,$A$9:$A104>E$4))),(SUMIFS($B$9:$B24,$A$9:$A24,"<"&$A24,$A$9:$A24,">="&E$4,$A$9:$A24,"<="&E$5)-SUM(_xlfn._xlws.FILTER(E25:E104,$A25:$A104>E$4),_xlfn._xlws.FILTER($C$9:D104,$A$9:$A104>E$4))>E$6)),E$6,MAX(0,SUMIFS($B$9:$B24,$A$9:$A24,"<"&$A24,$A$9:$A24,">="&E$4,$A$9:$A24,"<="&E$5)-SUM(_xlfn._xlws.FILTER(E25:E104,$A25:$A104>E$4),_xlfn._xlws.FILTER($C$9:D104,$A$9:$A104>E$4)))),"")} | F24: {=IF(AND(($A24<>"")*($A24>F$4)*($A24<=F$5)),IF(AND((SUMIFS($B$9:$B24,$A$9:$A24,"<"&$A24,$A$9:$A24,">="&F$4,$A$9:$A24,"<="&F$5)>SUM(_xlfn._xlws.FILTER(F25:F104,$A25:$A104>F$4),_xlfn._xlws.FILTER($C$9:E104,$A$9:$A104>F$4))),(SUMIFS($B$9:$B24,$A$9:$A24,"<"&$A24,$A$9:$A24,">="&F$4,$A$9:$A24,"<="&F$5)-SUM(_xlfn._xlws.FILTER(F25:F104,$A25:$A104>F$4),_xlfn._xlws.FILTER($C$9:E104,$A$9:$A104>F$4))>F$6)),F$6,MAX(0,SUMIFS($B$9:$B24,$A$9:$A24,"<"&$A24,$A$9:$A24,">="&F$4,$A$9:$A24,"<="&F$5)-SUM(_xlfn._xlws.FILTER(F25:F104,$A25:$A104>F$4),_xlfn._xlws.FILTER($C$9:E104,$A$9:$A104>F$4)))),"")} | G24: {=IF(AND(($A24<>"")*($A24>G$4)*($A24<=G$5)),IF(AND((SUMIFS($B$9:$B24,$A$9:$A24,"<"&$A24,$A$9:$A24,">="&G$4,$A$9:$A24,"<="&G$5)>SUM(_xlfn._xlws.FILTER(G25:G104,$A25:$A104>G$4),_xlfn._xlws.FILTER($C$9:F104,$A$9:$A104>G$4))),(SUMIFS($B$9:$B24,$A$9:$A24,"<"&$A24,$A$9:$A24,">="&G$4,$A$9:$A24,"<="&G$5)-SUM(_xlfn._xlws.FILTER(G25:G104,$A25:$A104>G$4),_xlfn._xlws.FILTER($C$9:F104,$A$9:$A104>G$4))>G$6)),G$6,MAX(0,SUMIFS($B$9:$B24,$A$9:$A24,"<"&$A24,$A$9:$A24,">="&G$4,$A$9:$A24,"<="&G$5)-SUM(_xlfn._xlws.FILTER(G25:G104,$A25:$A104>G$4),_xlfn._xlws.FILTER($C$9:F104,$A$9:$A104>G$4)))),"")} | H24: {=IF(AND(($A24<>"")*($A24>H$4)*($A24<=H$5)),IF(AND((SUMIFS($B$9:$B24,$A$9:$A24,"<"&$A24,$A$9:$A24,">="&H$4,$A$9:$A24,"<="&H$5)>SUM(_xlfn._xlws.FILTER(H25:H104,$A25:$A104>H$4),_xlfn._xlws.FILTER($C$9:G104,$A$9:$A104>H$4))),(SUMIFS($B$9:$B24,$A$9:$A24,"<"&$A24,$A$9:$A24,">="&H$4,$A$9:$A24,"<="&H$5)-SUM(_xlfn._xlws.FILTER(H25:H104,$A25:$A104>H$4),_xlfn._xlws.FILTER($C$9:G104,$A$9:$A104>H$4))>H$6)),H$6,MAX(0,SUMIFS($B$9:$B24,$A$9:$A24,"<"&$A24,$A$9:$A24,">="&H$4,$A$9:$A24,"<="&H$5)-SUM(_xlfn._xlws.FILTER(H25:H104,$A25:$A104>H$4),_xlfn._xlws.FILTER($C$9:G104,$A$9:$A104>H$4)))),"")} | I24: {=IF(AND(($A24<>"")*($A24>I$4)*($A24<=I$5)),IF(AND((SUMIFS($B$9:$B24,$A$9:$A24,"<"&$A24,$A$9:$A24,">="&I$4,$A$9:$A24,"<="&I$5)>SUM(_xlfn._xlws.FILTER(I25:I104,$A25:$A104>I$4),_xlfn._xlws.FILTER($C$9:H104,$A$9:$A104>I$4))),(SUMIFS($B$9:$B24,$A$9:$A24,"<"&$A24,$A$9:$A24,">="&I$4,$A$9:$A24,"<="&I$5)-SUM(_xlfn._xlws.FILTER(I25:I104,$A25:$A104>I$4),_xlfn._xlws.FILTER($C$9:H104,$A$9:$A104>I$4))>I$6)),I$6,MAX(0,SUMIFS($B$9:$B24,$A$9:$A24,"<"&$A24,$A$9:$A24,">="&I$4,$A$9:$A24,"<="&I$5)-SUM(_xlfn._xlws.FILTER(I25:I104,$A25:$A104>I$4),_xlfn._xlws.FILTER($C$9:H104,$A$9:$A104>I$4)))),"")} | J24: {=IF(AND(($A24<>"")*($A24>J$4)*($A24<=J$5)),IF(AND((SUMIFS($B$9:$B24,$A$9:$A24,"<"&$A24,$A$9:$A24,">="&J$4,$A$9:$A24,"<="&J$5)>SUM(_xlfn._xlws.FILTER(J25:J104,$A25:$A104>J$4),_xlfn._xlws.FILTER($C$9:I104,$A$9:$A104>J$4))),(SUMIFS($B$9:$B24,$A$9:$A24,"<"&$A24,$A$9:$A24,">="&J$4,$A$9:$A24,"<="&J$5)-SUM(_xlfn._xlws.FILTER(J25:J104,$A25:$A104>J$4),_xlfn._xlws.FILTER($C$9:I104,$A$9:$A104>J$4))>J$6)),J$6,MAX(0,SUMIFS($B$9:$B24,$A$9:$A24,"<"&$A24,$A$9:$A24,">="&J$4,$A$9:$A24,"<="&J$5)-SUM(_xlfn._xlws.FILTER(J25:J104,$A25:$A104>J$4),_xlfn._xlws.FILTER($C$9:I104,$A$9:$A104>J$4)))),"")} | K24: {=IF(AND(($A24<>"")*($A24>K$4)*($A24<=K$5)),IF(AND((SUMIFS($B$9:$B24,$A$9:$A24,"<"&$A24,$A$9:$A24,">="&K$4,$A$9:$A24,"<="&K$5)>SUM(_xlfn._xlws.FILTER(K25:K104,$A25:$A104>K$4),_xlfn._xlws.FILTER($C$9:J104,$A$9:$A104>K$4))),(SUMIFS($B$9:$B24,$A$9:$A24,"<"&$A24,$A$9:$A24,">="&K$4,$A$9:$A24,"<="&K$5)-SUM(_xlfn._xlws.FILTER(K25:K104,$A25:$A104>K$4),_xlfn._xlws.FILTER($C$9:J104,$A$9:$A104>K$4))>K$6)),K$6,MAX(0,SUMIFS($B$9:$B24,$A$9:$A24,"<"&$A24,$A$9:$A24,">="&K$4,$A$9:$A24,"<="&K$5)-SUM(_xlfn._xlws.FILTER(K25:K104,$A25:$A104>K$4),_xlfn._xlws.FILTER($C$9:J104,$A$9:$A104>K$4)))),"")} | ... HS24: {=IF(AND(($A24<>"")*($A24>HS$4)*($A24<=HS$5)),IF(AND((SUMIFS($B$9:$B24,$A$9:$A24,"<"&$A24,$A$9:$A24,">="&HS$4,$A$9:$A24,"<="&HS$5)>SUM(_xlfn._xlws.FILTER(HS25:HS104,$A25:$A104>HS$4),_xlfn._xlws.FILTER($C$9:HR104,$A$9:$A104>HS$4))),(SUMIFS($B$9:$B24,$A$9:$A24,"<"&$A24,$A$9:$A24,">="&HS$4,$A$9:$A24,"<="&HS$5)-SUM(_xlfn._xlws.FILTER(HS25:HS104,$A25:$A104>HS$4),_xlfn._xlws.FILTER($C$9:HR104,$A$9:$A104>HS$4))>HS$6)),HS$6,MAX(0,SUMIFS($B$9:$B24,$A$9:$A24,"<"&$A24,$A$9:$A24,">="&HS$4,$A$9:$A24,"<="&HS$5)-SUM(_xlfn._xlws.FILTER(HS25:HS104,$A25:$A104>HS$4),_xlfn._xlws.FILTER($C$9:HR104,$A$9:$A104>HS$4)))),"")}
